{"history": {"dailysummary": [{"since1julsnowfallm": "", "maxpressurei": "30.19", "mindewpti": "32", "meanwdird": "247", "mintempm": "3", "since1julsnowfalli": "", "meanwindspdm": "5", "since1jancoolingdegreedays": "", "meandewptm": "4", "heatingdegreedays": "12", "snowdepthi": "", "since1sepcoolingdegreedaysnormal": "", "tornado": "0", "snowdepthm": "", "maxvism": "30.0", "meanvism": "16.3", "heatingdegreedaysnormal": "", "meantempm": "12", "since1sepcoolingdegreedays": "", "meanpressurem": "1016.57", "monthtodatesnowfalli": "", "meantempi": "52", "minpressurem": "1010", "humidity": "54", "hail": "0", "since1sepheatingdegreedaysnormal": "", "since1julheatingdegreedaysnormal": "", "maxtempi": "68", "maxtempm": "20", "fog": "0", "precipsource": "3Or6HourObs", "precipi": "0.00", "since1jancoolingdegreedaysnormal": "", "maxdewpti": "46", "meanwindspdi": "3", "minhumidity": "19", "maxvisi": "19.0", "meanwdire": "WSW", "monthtodatecoolingdegreedaysnormal": "", "meandewpti": "38", "minpressurei": "29.83", "maxwspdm": "18", "maxhumidity": "93", "rain": "0", "monthtodateheatingdegreedays": "", "snow": "0", "monthtodatesnowfallm": "", "monthtodateheatingdegreedaysnormal": "", "precipm": "0.0", "minwspdi": "0", "minvisi": "6.2", "since1sepheatingdegreedays": "", "minwspdm": "0", "mintempi": "37", "coolingdegreedaysnormal": "", "maxwspdi": "11", "snowfallm": "", "monthtodatecoolingdegreedays": "", "mindewptm": "0", "since1julheatingdegreedays": "", "maxdewptm": "8", "snowfalli": "", "thunder": "0", "gdegreedays": "2", "minvism": "10.0", "meanpressurei": "30.02", "coolingdegreedays": "0", "date": {"mday": "18", "hour": "00", "min": "00", "mon": "05", "year": "2015", "pretty": "12:00 AM CEST on May 18, 2015", "tzname": "Europe/Warsaw"}, "meanvisi": "10.1", "maxpressurem": "1022"}], "observations": [{"metar": "AAXX 17221 12566 42882 52601 10087 20029 39927 40222 52001 85500 333 91202 555 60132 90005", "hail": "0", "rain": "0", "conds": "Mostly Cloudy", "dewpti": "37", "wgusti": "", "tornado": "0", "tempi": "48", "snow": "0", "windchilli": "-999", "precipm": "", "heatindexm": "-9999", "visi": "25", "wdird": "260", "wdire": "West", "wspdi": "2.2", "pressurei": "30.19", "wspdm": "3.6", "utcdate": {"mday": "17", "hour": "22", "min": "00", "mon": "05", "year": "2015", "pretty": "10:00 PM GMT on May 17, 2015", "tzname": "UTC"}, "thunder": "0", "pressurem": "1022", "fog": "0", "tempm": "9", "icon": "mostlycloudy", "precipi": "", "wgustm": "", "dewptm": "3", "hum": "56", "heatindexi": "-9999", "windchillm": "-999", "vism": "40", "date": {"mday": "18", "hour": "00", "min": "00", "mon": "05", "year": "2015", "pretty": "12:00 AM CEST on May 18, 2015", "tzname": "Europe/Warsaw"}}, {"metar": "METAR EPKK 172200Z 27002KT 9999 BKN066 08/03 Q1021", "hail": "0", "rain": "0", "conds": "Mostly Cloudy", "dewpti": "37.4", "wgusti": "-9999.0", "tornado": "0", "tempi": "46.4", "snow": "0", "windchilli": "-999", "precipm": "-9999.00", "heatindexm": "-9999", "visi": "6.2", "wdird": "270", "wdire": "West", "wspdi": "2.3", "pressurei": "30.15", "wspdm": "3.7", "utcdate": {"mday": "17", "hour": "22", "min": "00", "mon": "05", "year": "2015", "pretty": "10:00 PM GMT on May 17, 2015", "tzname": "UTC"}, "thunder": "0", "pressurem": "1021", "fog": "0", "tempm": "8.0", "icon": "mostlycloudy", "precipi": "-9999.00", "wgustm": "-9999.0", "dewptm": "3.0", "hum": "71", "heatindexi": "-9999", "windchillm": "-999", "vism": "10.0", "date": {"mday": "18", "hour": "00", "min": "00", "mon": "05", "year": "2015", "pretty": "12:00 AM CEST on May 18, 2015", "tzname": "Europe/Warsaw"}}, {"metar": "METAR EPKK 172230Z 24004KT 9999 SCT066 08/03 Q1021", "hail": "0", "rain": "0", "conds": "Scattered Clouds", "dewpti": "37.4", "wgusti": "-9999.0", "tornado": "0", "tempi": "46.4", "snow": "0", "windchilli": "44.3", "precipm": "-9999.00", "heatindexm": "-9999", "visi": "6.2", "wdird": "240", "wdire": "WSW", "wspdi": "4.6", "pressurei": "30.15", "wspdm": "7.4", "utcdate": {"mday": "17", "hour": "22", "min": "30", "mon": "05", "year": "2015", "pretty": "10:30 PM GMT on May 17, 2015", "tzname": "UTC"}, "thunder": "0", "pressurem": "1021", "fog": "0", "tempm": "8.0", "icon": "partlycloudy", "precipi": "-9999.00", "wgustm": "-9999.0", "dewptm": "3.0", "hum": "71", "heatindexi": "-9999", "windchillm": "6.8", "vism": "10.0", "date": {"mday": "18", "hour": "00", "min": "30", "mon": "05", "year": "2015", "pretty": "12:30 AM CEST on May 18, 2015", "tzname": "Europe/Warsaw"}}, {"metar": "AAXX 17231 12566 42880 22202 10081 20025 39925 40220 57003 82500 333 91202 555 90005", "hail": "0", "rain": "0", "conds": "Scattered Clouds", "dewpti": "36", "wgusti": "", "tornado": "0", "tempi": "47", "snow": "0", "windchilli": "-999", "precipm": "", "heatindexm": "-9999", "visi": "19", "wdird": "220", "wdire": "SW", "wspdi": "4.5", "pressurei": "30.18", "wspdm": "7.2", "utcdate": {"mday": "17", "hour": "23", "min": "00", "mon": "05", "year": "2015", "pretty": "11:00 PM GMT on May 17, 2015", "tzname": "UTC"}, "thunder": "0", "pressurem": "1022", "fog": "0", "tempm": "8", "icon": "partlycloudy", "precipi": "", "wgustm": "", "dewptm": "2", "hum": "57", "heatindexi": "-9999", "windchillm": "-999", "vism": "30", "date": {"mday": "18", "hour": "01", "min": "00", "mon": "05", "year": "2015", "pretty": "1:00 AM CEST on May 18, 2015", "tzname": "Europe/Warsaw"}}, {"metar": "METAR EPKK 172300Z 22003KT 9999 FEW066 08/03 Q1021", "hail": "0", "rain": "0", "conds": "Partly Cloudy", "dewpti": "37.4", "wgusti": "-9999.0", "tornado": "0", "tempi": "46.4", "snow": "0", "windchilli": "45.2", "precipm": "-9999.00", "heatindexm": "-9999", "visi": "6.2", "wdird": "220", "wdire": "SW", "wspdi": "3.5", "pressurei": "30.15", "wspdm": "5.6", "utcdate": {"mday": "17", "hour": "23", "min": "00", "mon": "05", "year": "2015", "pretty": "11:00 PM GMT on May 17, 2015", "tzname": "UTC"}, "thunder": "0", "pressurem": "1021", "fog": "0", "tempm": "8.0", "icon": "partlycloudy", "precipi": "-9999.00", "wgustm": "-9999.0", "dewptm": "3.0", "hum": "71", "heatindexi": "-9999", "windchillm": "7.3", "vism": "10.0", "date": {"mday": "18", "hour": "01", "min": "00", "mon": "05", "year": "2015", "pretty": "1:00 AM CEST on May 18, 2015", "tzname": "Europe/Warsaw"}}, {"metar": "METAR EPKK 172330Z 25004KT CAVOK 06/03 Q1021", "hail": "0", "rain": "0", "conds": "Clear", "dewpti": "37.4", "wgusti": "-9999.0", "tornado": "0", "tempi": "42.8", "snow": "0", "windchilli": "40.1", "precipm": "-9999.00", "heatindexm": "-9999", "visi": "-9999.0", "wdird": "250", "wdire": "WSW", "wspdi": "4.6", "pressurei": "30.15", "wspdm": "7.4", "utcdate": {"mday": "17", "hour": "23", "min": "30", "mon": "05", "year": "2015", "pretty": "11:30 PM GMT on May 17, 2015", "tzname": "UTC"}, "thunder": "0", "pressurem": "1021", "fog": "0", "tempm": "6.0", "icon": "clear", "precipi": "-9999.00", "wgustm": "-9999.0", "dewptm": "3.0", "hum": "81", "heatindexi": "-9999", "windchillm": "4.5", "vism": "-9999.0", "date": {"mday": "18", "hour": "01", "min": "30", "mon": "05", "year": "2015", "pretty": "1:30 AM CEST on May 18, 2015", "tzname": "Europe/Warsaw"}}, {"metar": "AAXX 18001 12566 12980 02501 10064 20019 39924 40221 58002 60001 333 91203 93000", "hail": "0", "rain": "0", "conds": "", "dewpti": "35", "wgusti": "", "tornado": "0", "tempi": "44", "snow": "0", "windchilli": "-999", "precipm": "", "heatindexm": "-9999", "visi": "19", "wdird": "250", "wdire": "WSW", "wspdi": "2.2", "pressurei": "30.19", "wspdm": "3.6", "utcdate": {"mday": "18", "hour": "00", "min": "00", "mon": "05", "year": "2015", "pretty": "12:00 AM GMT on May 18, 2015", "tzname": "UTC"}, "thunder": "0", "pressurem": "1022", "fog": "0", "tempm": "6", "icon": "", "precipi": "", "wgustm": "", "dewptm": "2", "hum": "63", "heatindexi": "-9999", "windchillm": "-999", "vism": "30", "date": {"mday": "18", "hour": "02", "min": "00", "mon": "05", "year": "2015", "pretty": "2:00 AM CEST on May 18, 2015", "tzname": "Europe/Warsaw"}}, {"metar": "METAR EPKK 180000Z 00000KT CAVOK 07/02 Q1021", "hail": "0", "rain": "0", "conds": "Clear", "dewpti": "35.6", "wgusti": "-9999.0", "tornado": "0", "tempi": "44.6", "snow": "0", "windchilli": "-999", "precipm": "-9999.00", "heatindexm": "-9999", "visi": "-9999.0", "wdird": "0", "wdire": "North", "wspdi": "0.0", "pressurei": "30.15", "wspdm": "0.0", "utcdate": {"mday": "18", "hour": "00", "min": "00", "mon": "05", "year": "2015", "pretty": "12:00 AM GMT on May 18, 2015", "tzname": "UTC"}, "thunder": "0", "pressurem": "1021", "fog": "0", "tempm": "7.0", "icon": "clear", "precipi": "-9999.00", "wgustm": "-9999.0", "dewptm": "2.0", "hum": "71", "heatindexi": "-9999", "windchillm": "-999", "vism": "-9999.0", "date": {"mday": "18", "hour": "02", "min": "00", "mon": "05", "year": "2015", "pretty": "2:00 AM CEST on May 18, 2015", "tzname": "Europe/Warsaw"}}, {"metar": "METAR EPKK 180030Z 00000KT CAVOK 06/02 Q1021", "hail": "0", "rain": "0", "conds": "Clear", "dewpti": "35.6", "wgusti": "-9999.0", "tornado": "0", "tempi": "42.8", "snow": "0", "windchilli": "-999", "precipm": "-9999.00", "heatindexm": "-9999", "visi": "-9999.0", "wdird": "0", "wdire": "North", "wspdi": "0.0", "pressurei": "30.15", "wspdm": "0.0", "utcdate": {"mday": "18", "hour": "00", "min": "30", "mon": "05", "year": "2015", "pretty": "12:30 AM GMT on May 18, 2015", "tzname": "UTC"}, "thunder": "0", "pressurem": "1021", "fog": "0", "tempm": "6.0", "icon": "clear", "precipi": "-9999.00", "wgustm": "-9999.0", "dewptm": "2.0", "hum": "76", "heatindexi": "-9999", "windchillm": "-999", "vism": "-9999.0", "date": {"mday": "18", "hour": "02", "min": "30", "mon": "05", "year": "2015", "pretty": "2:30 AM CEST on May 18, 2015", "tzname": "Europe/Warsaw"}}, {"metar": "AAXX 18011 12566 42970 00000 10046 20018 39922 40221 57005 333 91200 555 57026 90005", "hail": "0", "rain": "0", "conds": "", "dewpti": "35", "wgusti": "", "tornado": "0", "tempi": "40", "snow": "0", "windchilli": "-999", "precipm": "", "heatindexm": "-9999", "visi": "12", "wdird": "", "wdire": "", "wspdi": "0.0", "pressurei": "30.19", "wspdm": "0.0", "utcdate": {"mday": "18", "hour": "01", "min": "00", "mon": "05", "year": "2015", "pretty": "1:00 AM GMT on May 18, 2015", "tzname": "UTC"}, "thunder": "0", "pressurem": "1022", "fog": "0", "tempm": "5", "icon": "", "precipi": "", "wgustm": "", "dewptm": "2", "hum": "77", "heatindexi": "-9999", "windchillm": "-999", "vism": "20", "date": {"mday": "18", "hour": "03", "min": "00", "mon": "05", "year": "2015", "pretty": "3:00 AM CEST on May 18, 2015", "tzname": "Europe/Warsaw"}}, {"metar": "METAR EPKK 180100Z 00000KT CAVOK 05/02 Q1021", "hail": "0", "rain": "0", "conds": "Clear", "dewpti": "35.6", "wgusti": "-9999.0", "tornado": "0", "tempi": "41.0", "snow": "0", "windchilli": "-999", "precipm": "-9999.00", "heatindexm": "-9999", "visi": "-9999.0", "wdird": "0", "wdire": "North", "wspdi": "0.0", "pressurei": "30.15", "wspdm": "0.0", "utcdate": {"mday": "18", "hour": "01", "min": "00", "mon": "05", "year": "2015", "pretty": "1:00 AM GMT on May 18, 2015", "tzname": "UTC"}, "thunder": "0", "pressurem": "1021", "fog": "0", "tempm": "5.0", "icon": "clear", "precipi": "-9999.00", "wgustm": "-9999.0", "dewptm": "2.0", "hum": "81", "heatindexi": "-9999", "windchillm": "-999", "vism": "-9999.0", "date": {"mday": "18", "hour": "03", "min": "00", "mon": "05", "year": "2015", "pretty": "3:00 AM CEST on May 18, 2015", "tzname": "Europe/Warsaw"}}, {"metar": "METAR EPKK 180130Z 04001KT CAVOK 04/03 Q1021", "hail": "0", "rain": "0", "conds": "Clear", "dewpti": "37.4", "wgusti": "-9999.0", "tornado": "0", "tempi": "39.2", "snow": "0", "windchilli": "-999", "precipm": "-9999.00", "heatindexm": "-9999", "visi": "-9999.0", "wdird": "40", "wdire": "NE", "wspdi": "1.2", "pressurei": "30.15", "wspdm": "1.9", "utcdate": {"mday": "18", "hour": "01", "min": "30", "mon": "05", "year": "2015", "pretty": "1:30 AM GMT on May 18, 2015", "tzname": "UTC"}, "thunder": "0", "pressurem": "1021", "fog": "0", "tempm": "4.0", "icon": "clear", "precipi": "-9999.00", "wgustm": "-9999.0", "dewptm": "3.0", "hum": "93", "heatindexi": "-9999", "windchillm": "-999", "vism": "-9999.0", "date": {"mday": "18", "hour": "03", "min": "30", "mon": "05", "year": "2015", "pretty": "3:30 AM CEST on May 18, 2015", "tzname": "Europe/Warsaw"}}, {"metar": "AAXX 18021 12566 42970 00000 10039 20024 39919 40219 58006 333 91201 555 90005", "hail": "0", "rain": "0", "conds": "", "dewpti": "36", "wgusti": "", "tornado": "0", "tempi": "39", "snow": "0", "windchilli": "-999", "precipm": "", "heatindexm": "-9999", "visi": "12", "wdird": "", "wdire": "", "wspdi": "0.0", "pressurei": "30.18", "wspdm": "0.0", "utcdate": {"mday": "18", "hour": "02", "min": "00", "mon": "05", "year": "2015", "pretty": "2:00 AM GMT on May 18, 2015", "tzname": "UTC"}, "thunder": "0", "pressurem": "1022", "fog": "0", "tempm": "4", "icon": "", "precipi": "", "wgustm": "", "dewptm": "2", "hum": "86", "heatindexi": "-9999", "windchillm": "-999", "vism": "20", "date": {"mday": "18", "hour": "04", "min": "00", "mon": "05", "year": "2015", "pretty": "4:00 AM CEST on May 18, 2015", "tzname": "Europe/Warsaw"}}, {"metar": "METAR EPKK 180200Z 00000KT CAVOK 04/02 Q1020", "hail": "0", "rain": "0", "conds": "Clear", "dewpti": "35.6", "wgusti": "-9999.0", "tornado": "0", "tempi": "39.2", "snow": "0", "windchilli": "-999", "precipm": "-9999.00", "heatindexm": "-9999", "visi": "-9999.0", "wdird": "0", "wdire": "North", "wspdi": "0.0", "pressurei": "30.12", "wspdm": "0.0", "utcdate": {"mday": "18", "hour": "02", "min": "00", "mon": "05", "year": "2015", "pretty": "2:00 AM GMT on May 18, 2015", "tzname": "UTC"}, "thunder": "0", "pressurem": "1020", "fog": "0", "tempm": "4.0", "icon": "clear", "precipi": "-9999.00", "wgustm": "-9999.0", "dewptm": "2.0", "hum": "87", "heatindexi": "-9999", "windchillm": "-999", "vism": "-9999.0", "date": {"mday": "18", "hour": "04", "min": "00", "mon": "05", "year": "2015", "pretty": "4:00 AM CEST on May 18, 2015", "tzname": "Europe/Warsaw"}}, {"metar": "METAR EPKK 180230Z 00000KT CAVOK 04/02 Q1020", "hail": "0", "rain": "0", "conds": "Clear", "dewpti": "35.6", "wgusti": "-9999.0", "tornado": "0", "tempi": "39.2", "snow": "0", "windchilli": "-999", "precipm": "-9999.00", "heatindexm": "-9999", "visi": "-9999.0", "wdird": "0", "wdire": "North", "wspdi": "0.0", "pressurei": "30.12", "wspdm": "0.0", "utcdate": {"mday": "18", "hour": "02", "min": "30", "mon": "05", "year": "2015", "pretty": "2:30 AM GMT on May 18, 2015", "tzname": "UTC"}, "thunder": "0", "pressurem": "1020", "fog": "0", "tempm": "4.0", "icon": "clear", "precipi": "-9999.00", "wgustm": "-9999.0", "dewptm": "2.0", "hum": "87", "heatindexi": "-9999", "windchillm": "-999", "vism": "-9999.0", "date": {"mday": "18", "hour": "04", "min": "30", "mon": "05", "year": "2015", "pretty": "4:30 AM CEST on May 18, 2015", "tzname": "Europe/Warsaw"}}, {"metar": "AAXX 18031 12566 42970 10000 10037 20024 39917 40217 57007 80001 333 91201", "hail": "0", "rain": "0", "conds": "Clear", "dewpti": "36", "wgusti": "", "tornado": "0", "tempi": "39", "snow": "0", "windchilli": "-999", "precipm": "", "heatindexm": "-9999", "visi": "12", "wdird": "", "wdire": "", "wspdi": "0.0", "pressurei": "30.17", "wspdm": "0.0", "utcdate": {"mday": "18", "hour": "03", "min": "00", "mon": "05", "year": "2015", "pretty": "3:00 AM GMT on May 18, 2015", "tzname": "UTC"}, "thunder": "0", "pressurem": "1022", "fog": "0", "tempm": "4", "icon": "clear", "precipi": "", "wgustm": "", "dewptm": "2", "hum": "86", "heatindexi": "-9999", "windchillm": "-999", "vism": "20", "date": {"mday": "18", "hour": "05", "min": "00", "mon": "05", "year": "2015", "pretty": "5:00 AM CEST on May 18, 2015", "tzname": "Europe/Warsaw"}}, {"metar": "METAR EPKK 180300Z 00000KT CAVOK 04/02 Q1020", "hail": "0", "rain": "0", "conds": "Clear", "dewpti": "35.6", "wgusti": "-9999.0", "tornado": "0", "tempi": "39.2", "snow": "0", "windchilli": "-999", "precipm": "-9999.00", "heatindexm": "-9999", "visi": "-9999.0", "wdird": "0", "wdire": "North", "wspdi": "0.0", "pressurei": "30.12", "wspdm": "0.0", "utcdate": {"mday": "18", "hour": "03", "min": "00", "mon": "05", "year": "2015", "pretty": "3:00 AM GMT on May 18, 2015", "tzname": "UTC"}, "thunder": "0", "pressurem": "1020", "fog": "0", "tempm": "4.0", "icon": "clear", "precipi": "-9999.00", "wgustm": "-9999.0", "dewptm": "2.0", "hum": "87", "heatindexi": "-9999", "windchillm": "-999", "vism": "-9999.0", "date": {"mday": "18", "hour": "05", "min": "00", "mon": "05", "year": "2015", "pretty": "5:00 AM CEST on May 18, 2015", "tzname": "Europe/Warsaw"}}, {"metar": "METAR EPKK 180330Z 00000KT CAVOK 03/02 Q1020", "hail": "0", "rain": "0", "conds": "Clear", "dewpti": "35.6", "wgusti": "-9999.0", "tornado": "0", "tempi": "37.4", "snow": "0", "windchilli": "-999", "precipm": "-9999.00", "heatindexm": "-9999", "visi": "-9999.0", "wdird": "0", "wdire": "North", "wspdi": "0.0", "pressurei": "30.12", "wspdm": "0.0", "utcdate": {"mday": "18", "hour": "03", "min": "30", "mon": "05", "year": "2015", "pretty": "3:30 AM GMT on May 18, 2015", "tzname": "UTC"}, "thunder": "0", "pressurem": "1020", "fog": "0", "tempm": "3.0", "icon": "clear", "precipi": "-9999.00", "wgustm": "-9999.0", "dewptm": "2.0", "hum": "93", "heatindexi": "-9999", "windchillm": "-999", "vism": "-9999.0", "date": {"mday": "18", "hour": "05", "min": "30", "mon": "05", "year": "2015", "pretty": "5:30 AM CEST on May 18, 2015", "tzname": "Europe/Warsaw"}}, {"metar": "AAXX 18041 12566 42970 10000 10047 20030 39915 40214 57007 80001 333 91201 555 90005", "hail": "0", "rain": "0", "conds": "Clear", "dewpti": "37", "wgusti": "", "tornado": "0", "tempi": "40", "snow": "0", "windchilli": "-999", "precipm": "", "heatindexm": "-9999", "visi": "12", "wdird": "", "wdire": "", "wspdi": "0.0", "pressurei": "30.17", "wspdm": "0.0", "utcdate": {"mday": "18", "hour": "04", "min": "00", "mon": "05", "year": "2015", "pretty": "4:00 AM GMT on May 18, 2015", "tzname": "UTC"}, "thunder": "0", "pressurem": "1021", "fog": "0", "tempm": "5", "icon": "clear", "precipi": "", "wgustm": "", "dewptm": "3", "hum": "87", "heatindexi": "-9999", "windchillm": "-999", "vism": "20", "date": {"mday": "18", "hour": "06", "min": "00", "mon": "05", "year": "2015", "pretty": "6:00 AM CEST on May 18, 2015", "tzname": "Europe/Warsaw"}}, {"metar": "METAR EPKK 180400Z 00000KT CAVOK 06/04 Q1020", "hail": "0", "rain": "0", "conds": "Clear", "dewpti": "39.2", "wgusti": "-9999.0", "tornado": "0", "tempi": "42.8", "snow": "0", "windchilli": "-999", "precipm": "-9999.00", "heatindexm": "-9999", "visi": "-9999.0", "wdird": "0", "wdire": "North", "wspdi": "0.0", "pressurei": "30.12", "wspdm": "0.0", "utcdate": {"mday": "18", "hour": "04", "min": "00", "mon": "05", "year": "2015", "pretty": "4:00 AM GMT on May 18, 2015", "tzname": "UTC"}, "thunder": "0", "pressurem": "1020", "fog": "0", "tempm": "6.0", "icon": "clear", "precipi": "-9999.00", "wgustm": "-9999.0", "dewptm": "4.0", "hum": "87", "heatindexi": "-9999", "windchillm": "-999", "vism": "-9999.0", "date": {"mday": "18", "hour": "06", "min": "00", "mon": "05", "year": "2015", "pretty": "6:00 AM CEST on May 18, 2015", "tzname": "Europe/Warsaw"}}, {"metar": "METAR EPKK 180430Z 02001KT CAVOK 06/04 Q1020", "hail": "0", "rain": "0", "conds": "Clear", "dewpti": "39.2", "wgusti": "-9999.0", "tornado": "0", "tempi": "42.8", "snow": "0", "windchilli": "-999", "precipm": "-9999.00", "heatindexm": "-9999", "visi": "-9999.0", "wdird": "20", "wdire": "NNE", "wspdi": "1.2", "pressurei": "30.12", "wspdm": "1.9", "utcdate": {"mday": "18", "hour": "04", "min": "30", "mon": "05", "year": "2015", "pretty": "4:30 AM GMT on May 18, 2015", "tzname": "UTC"}, "thunder": "0", "pressurem": "1020", "fog": "0", "tempm": "6.0", "icon": "clear", "precipi": "-9999.00", "wgustm": "-9999.0", "dewptm": "4.0", "hum": "87", "heatindexi": "-9999", "windchillm": "-999", "vism": "-9999.0", "date": {"mday": "18", "hour": "06", "min": "30", "mon": "05", "year": "2015", "pretty": "6:30 AM CEST on May 18, 2015", "tzname": "Europe/Warsaw"}}, {"metar": "AAXX 18051 12566 42970 10000 10086 20038 39914 40208 57005 80001 333 91201 555 90005", "hail": "0", "rain": "0", "conds": "Clear", "dewpti": "39", "wgusti": "", "tornado": "0", "tempi": "47", "snow": "0", "windchilli": "-999", "precipm": "", "heatindexm": "-9999", "visi": "12", "wdird": "", "wdire": "", "wspdi": "0.0", "pressurei": "30.15", "wspdm": "0.0", "utcdate": {"mday": "18", "hour": "05", "min": "00", "mon": "05", "year": "2015", "pretty": "5:00 AM GMT on May 18, 2015", "tzname": "UTC"}, "thunder": "0", "pressurem": "1021", "fog": "0", "tempm": "9", "icon": "clear", "precipi": "", "wgustm": "", "dewptm": "4", "hum": "65", "heatindexi": "-9999", "windchillm": "-999", "vism": "20", "date": {"mday": "18", "hour": "07", "min": "00", "mon": "05", "year": "2015", "pretty": "7:00 AM CEST on May 18, 2015", "tzname": "Europe/Warsaw"}}, {"metar": "METAR EPKK 180500Z 00000KT CAVOK 09/04 Q1020", "hail": "0", "rain": "0", "conds": "Clear", "dewpti": "39.2", "wgusti": "-9999.0", "tornado": "0", "tempi": "48.2", "snow": "0", "windchilli": "-999", "precipm": "-9999.00", "heatindexm": "-9999", "visi": "-9999.0", "wdird": "0", "wdire": "North", "wspdi": "0.0", "pressurei": "30.12", "wspdm": "0.0", "utcdate": {"mday": "18", "hour": "05", "min": "00", "mon": "05", "year": "2015", "pretty": "5:00 AM GMT on May 18, 2015", "tzname": "UTC"}, "thunder": "0", "pressurem": "1020", "fog": "0", "tempm": "9.0", "icon": "clear", "precipi": "-9999.00", "wgustm": "-9999.0", "dewptm": "4.0", "hum": "71", "heatindexi": "-9999", "windchillm": "-999", "vism": "-9999.0", "date": {"mday": "18", "hour": "07", "min": "00", "mon": "05", "year": "2015", "pretty": "7:00 AM CEST on May 18, 2015", "tzname": "Europe/Warsaw"}}, {"metar": "METAR EPKK 180530Z 00000KT CAVOK 10/05 Q1020", "hail": "0", "rain": "0", "conds": "Clear", "dewpti": "41.0", "wgusti": "-9999.0", "tornado": "0", "tempi": "50.0", "snow": "0", "windchilli": "-999", "precipm": "-9999.00", "heatindexm": "-9999", "visi": "-9999.0", "wdird": "0", "wdire": "North", "wspdi": "0.0", "pressurei": "30.12", "wspdm": "0.0", "utcdate": {"mday": "18", "hour": "05", "min": "30", "mon": "05", "year": "2015", "pretty": "5:30 AM GMT on May 18, 2015", "tzname": "UTC"}, "thunder": "0", "pressurem": "1020", "fog": "0", "tempm": "10.0", "icon": "clear", "precipi": "-9999.00", "wgustm": "-9999.0", "dewptm": "5.0", "hum": "71", "heatindexi": "-9999", "windchillm": "-999", "vism": "-9999.0", "date": {"mday": "18", "hour": "07", "min": "30", "mon": "05", "year": "2015", "pretty": "7:30 AM CEST on May 18, 2015", "tzname": "Europe/Warsaw"}}, {"metar": "AAXX 18061 12566 12980 11901 10104 20041 39913 40206 57004 60002 80001 333 10129 20031 30003 91201 93000", "hail": "0", "rain": "0", "conds": "Clear", "dewpti": "39", "wgusti": "", "tornado": "0", "tempi": "51", "snow": "0", "windchilli": "-999", "precipm": "", "heatindexm": "-9999", "visi": "19", "wdird": "190", "wdire": "South", "wspdi": "2.2", "pressurei": "30.14", "wspdm": "3.6", "utcdate": {"mday": "18", "hour": "06", "min": "00", "mon": "05", "year": "2015", "pretty": "6:00 AM GMT on May 18, 2015", "tzname": "UTC"}, "thunder": "0", "pressurem": "1021", "fog": "0", "tempm": "10", "icon": "clear", "precipi": "", "wgustm": "", "dewptm": "4", "hum": "54", "heatindexi": "-9999", "windchillm": "-999", "vism": "30", "date": {"mday": "18", "hour": "08", "min": "00", "mon": "05", "year": "2015", "pretty": "8:00 AM CEST on May 18, 2015", "tzname": "Europe/Warsaw"}}, {"metar": "METAR EPKK 180600Z VRB02KT CAVOK 12/05 Q1020", "hail": "0", "rain": "0", "conds": "Clear", "dewpti": "41.0", "wgusti": "-9999.0", "tornado": "0", "tempi": "53.6", "snow": "0", "windchilli": "-999", "precipm": "-9999.00", "heatindexm": "-9999", "visi": "-9999.0", "wdird": "0", "wdire": "Variable", "wspdi": "2.3", "pressurei": "30.12", "wspdm": "3.7", "utcdate": {"mday": "18", "hour": "06", "min": "00", "mon": "05", "year": "2015", "pretty": "6:00 AM GMT on May 18, 2015", "tzname": "UTC"}, "thunder": "0", "pressurem": "1020", "fog": "0", "tempm": "12.0", "icon": "clear", "precipi": "-9999.00", "wgustm": "-9999.0", "dewptm": "5.0", "hum": "62", "heatindexi": "-9999", "windchillm": "-999", "vism": "-9999.0", "date": {"mday": "18", "hour": "08", "min": "00", "mon": "05", "year": "2015", "pretty": "8:00 AM CEST on May 18, 2015", "tzname": "Europe/Warsaw"}}, {"metar": "METAR EPKK 180630Z 23004KT 170V260 CAVOK 11/05 Q1019", "hail": "0", "rain": "0", "conds": "Clear", "dewpti": "41.0", "wgusti": "-9999.0", "tornado": "0", "tempi": "51.8", "snow": "0", "windchilli": "-999", "precipm": "-9999.00", "heatindexm": "-9999", "visi": "-9999.0", "wdird": "230", "wdire": "SW", "wspdi": "4.6", "pressurei": "30.09", "wspdm": "7.4", "utcdate": {"mday": "18", "hour": "06", "min": "30", "mon": "05", "year": "2015", "pretty": "6:30 AM GMT on May 18, 2015", "tzname": "UTC"}, "thunder": "0", "pressurem": "1019", "fog": "0", "tempm": "11.0", "icon": "clear", "precipi": "-9999.00", "wgustm": "-9999.0", "dewptm": "5.0", "hum": "67", "heatindexi": "-9999", "windchillm": "-999", "vism": "-9999.0", "date": {"mday": "18", "hour": "08", "min": "30", "mon": "05", "year": "2015", "pretty": "8:30 AM CEST on May 18, 2015", "tzname": "Europe/Warsaw"}}, {"metar": "AAXX 18071 12566 42980 12204 10126 20033 39908 40198 58007 80001 333 91204 555 57044 90005", "hail": "0", "rain": "0", "conds": "Clear", "dewpti": "38", "wgusti": "", "tornado": "0", "tempi": "55", "snow": "0", "windchilli": "-999", "precipm": "", "heatindexm": "-9999", "visi": "19", "wdird": "220", "wdire": "SW", "wspdi": "8.9", "pressurei": "30.12", "wspdm": "14.4", "utcdate": {"mday": "18", "hour": "07", "min": "00", "mon": "05", "year": "2015", "pretty": "7:00 AM GMT on May 18, 2015", "tzname": "UTC"}, "thunder": "0", "pressurem": "1020", "fog": "0", "tempm": "13", "icon": "clear", "precipi": "", "wgustm": "", "dewptm": "3", "hum": "41", "heatindexi": "-9999", "windchillm": "-999", "vism": "30", "date": {"mday": "18", "hour": "09", "min": "00", "mon": "05", "year": "2015", "pretty": "9:00 AM CEST on May 18, 2015", "tzname": "Europe/Warsaw"}}, {"metar": "METAR EPKK 180700Z 22006KT 190V250 CAVOK 13/05 Q1019", "hail": "0", "rain": "0", "conds": "Clear", "dewpti": "41.0", "wgusti": "-9999.0", "tornado": "0", "tempi": "55.4", "snow": "0", "windchilli": "-999", "precipm": "-9999.00", "heatindexm": "-9999", "visi": "-9999.0", "wdird": "220", "wdire": "SW", "wspdi": "6.9", "pressurei": "30.09", "wspdm": "11.1", "utcdate": {"mday": "18", "hour": "07", "min": "00", "mon": "05", "year": "2015", "pretty": "7:00 AM GMT on May 18, 2015", "tzname": "UTC"}, "thunder": "0", "pressurem": "1019", "fog": "0", "tempm": "13.0", "icon": "clear", "precipi": "-9999.00", "wgustm": "-9999.0", "dewptm": "5.0", "hum": "58", "heatindexi": "-9999", "windchillm": "-999", "vism": "-9999.0", "date": {"mday": "18", "hour": "09", "min": "00", "mon": "05", "year": "2015", "pretty": "9:00 AM CEST on May 18, 2015", "tzname": "Europe/Warsaw"}}, {"metar": "METAR EPKK 180730Z 23008KT 190V270 CAVOK 13/03 Q1019", "hail": "0", "rain": "0", "conds": "Clear", "dewpti": "37.4", "wgusti": "-9999.0", "tornado": "0", "tempi": "55.4", "snow": "0", "windchilli": "-999", "precipm": "-9999.00", "heatindexm": "-9999", "visi": "-9999.0", "wdird": "230", "wdire": "SW", "wspdi": "9.2", "pressurei": "30.09", "wspdm": "14.8", "utcdate": {"mday": "18", "hour": "07", "min": "30", "mon": "05", "year": "2015", "pretty": "7:30 AM GMT on May 18, 2015", "tzname": "UTC"}, "thunder": "0", "pressurem": "1019", "fog": "0", "tempm": "13.0", "icon": "clear", "precipi": "-9999.00", "wgustm": "-9999.0", "dewptm": "3.0", "hum": "51", "heatindexi": "-9999", "windchillm": "-999", "vism": "-9999.0", "date": {"mday": "18", "hour": "09", "min": "30", "mon": "05", "year": "2015", "pretty": "9:30 AM CEST on May 18, 2015", "tzname": "Europe/Warsaw"}}, {"metar": "AAXX 18081 12566 42982 12304 10141 20029 39901 40189 58013 80001 333 91205 555 90005", "hail": "0", "rain": "0", "conds": "Clear", "dewpti": "37", "wgusti": "", "tornado": "0", "tempi": "57", "snow": "0", "windchilli": "-999", "precipm": "", "heatindexm": "-9999", "visi": "25", "wdird": "230", "wdire": "SW", "wspdi": "8.9", "pressurei": "30.09", "wspdm": "14.4", "utcdate": {"mday": "18", "hour": "08", "min": "00", "mon": "05", "year": "2015", "pretty": "8:00 AM GMT on May 18, 2015", "tzname": "UTC"}, "thunder": "0", "pressurem": "1019", "fog": "0", "tempm": "14", "icon": "clear", "precipi": "", "wgustm": "", "dewptm": "3", "hum": "36", "heatindexi": "-9999", "windchillm": "-999", "vism": "40", "date": {"mday": "18", "hour": "10", "min": "00", "mon": "05", "year": "2015", "pretty": "10:00 AM CEST on May 18, 2015", "tzname": "Europe/Warsaw"}}, {"metar": "METAR EPKK 180800Z 24008KT 200V270 CAVOK 14/02 Q1019", "hail": "0", "rain": "0", "conds": "Clear", "dewpti": "35.6", "wgusti": "-9999.0", "tornado": "0", "tempi": "57.2", "snow": "0", "windchilli": "-999", "precipm": "-9999.00", "heatindexm": "-9999", "visi": "-9999.0", "wdird": "240", "wdire": "WSW", "wspdi": "9.2", "pressurei": "30.09", "wspdm": "14.8", "utcdate": {"mday": "18", "hour": "08", "min": "00", "mon": "05", "year": "2015", "pretty": "8:00 AM GMT on May 18, 2015", "tzname": "UTC"}, "thunder": "0", "pressurem": "1019", "fog": "0", "tempm": "14.0", "icon": "clear", "precipi": "-9999.00", "wgustm": "-9999.0", "dewptm": "2.0", "hum": "44", "heatindexi": "-9999", "windchillm": "-999", "vism": "-9999.0", "date": {"mday": "18", "hour": "10", "min": "00", "mon": "05", "year": "2015", "pretty": "10:00 AM CEST on May 18, 2015", "tzname": "Europe/Warsaw"}}, {"metar": "METAR EPKK 180830Z 25007KT 210V280 CAVOK 15/02 Q1018", "hail": "0", "rain": "0", "conds": "Clear", "dewpti": "35.6", "wgusti": "-9999.0", "tornado": "0", "tempi": "59.0", "snow": "0", "windchilli": "-999", "precipm": "-9999.00", "heatindexm": "-9999", "visi": "-9999.0", "wdird": "250", "wdire": "WSW", "wspdi": "8.1", "pressurei": "30.06", "wspdm": "13.0", "utcdate": {"mday": "18", "hour": "08", "min": "30", "mon": "05", "year": "2015", "pretty": "8:30 AM GMT on May 18, 2015", "tzname": "UTC"}, "thunder": "0", "pressurem": "1018", "fog": "0", "tempm": "15.0", "icon": "clear", "precipi": "-9999.00", "wgustm": "-9999.0", "dewptm": "2.0", "hum": "42", "heatindexi": "-9999", "windchillm": "-999", "vism": "-9999.0", "date": {"mday": "18", "hour": "10", "min": "30", "mon": "05", "year": "2015", "pretty": "10:30 AM CEST on May 18, 2015", "tzname": "Europe/Warsaw"}}, {"metar": "AAXX 18091 12566 42984 12304 10151 20019 39896 40183 57017 80001 333 91205", "hail": "0", "rain": "0", "conds": "Clear", "dewpti": "35", "wgusti": "", "tornado": "0", "tempi": "59", "snow": "0", "windchilli": "-999", "precipm": "", "heatindexm": "-9999", "visi": "31", "wdird": "230", "wdire": "SW", "wspdi": "8.9", "pressurei": "30.07", "wspdm": "14.4", "utcdate": {"mday": "18", "hour": "09", "min": "00", "mon": "05", "year": "2015", "pretty": "9:00 AM GMT on May 18, 2015", "tzname": "UTC"}, "thunder": "0", "pressurem": "1018", "fog": "0", "tempm": "15", "icon": "clear", "precipi": "", "wgustm": "", "dewptm": "2", "hum": "29", "heatindexi": "-9999", "windchillm": "-999", "vism": "50", "date": {"mday": "18", "hour": "11", "min": "00", "mon": "05", "year": "2015", "pretty": "11:00 AM CEST on May 18, 2015", "tzname": "Europe/Warsaw"}}, {"metar": "METAR EPKK 180900Z 25006KT 210V280 CAVOK 15/02 Q1018", "hail": "0", "rain": "0", "conds": "Clear", "dewpti": "35.6", "wgusti": "-9999.0", "tornado": "0", "tempi": "59.0", "snow": "0", "windchilli": "-999", "precipm": "-9999.00", "heatindexm": "-9999", "visi": "-9999.0", "wdird": "250", "wdire": "WSW", "wspdi": "6.9", "pressurei": "30.06", "wspdm": "11.1", "utcdate": {"mday": "18", "hour": "09", "min": "00", "mon": "05", "year": "2015", "pretty": "9:00 AM GMT on May 18, 2015", "tzname": "UTC"}, "thunder": "0", "pressurem": "1018", "fog": "0", "tempm": "15.0", "icon": "clear", "precipi": "-9999.00", "wgustm": "-9999.0", "dewptm": "2.0", "hum": "42", "heatindexi": "-9999", "windchillm": "-999", "vism": "-9999.0", "date": {"mday": "18", "hour": "11", "min": "00", "mon": "05", "year": "2015", "pretty": "11:00 AM CEST on May 18, 2015", "tzname": "Europe/Warsaw"}}, {"metar": "METAR EPKK 180930Z 25005KT 210V320 CAVOK 16/02 Q1018", "hail": "0", "rain": "0", "conds": "Clear", "dewpti": "35.6", "wgusti": "-9999.0", "tornado": "0", "tempi": "60.8", "snow": "0", "windchilli": "-999", "precipm": "-9999.00", "heatindexm": "-9999", "visi": "-9999.0", "wdird": "250", "wdire": "WSW", "wspdi": "5.8", "pressurei": "30.06", "wspdm": "9.3", "utcdate": {"mday": "18", "hour": "09", "min": "30", "mon": "05", "year": "2015", "pretty": "9:30 AM GMT on May 18, 2015", "tzname": "UTC"}, "thunder": "0", "pressurem": "1018", "fog": "0", "tempm": "16.0", "icon": "clear", "precipi": "-9999.00", "wgustm": "-9999.0", "dewptm": "2.0", "hum": "39", "heatindexi": "-9999", "windchillm": "-999", "vism": "-9999.0", "date": {"mday": "18", "hour": "11", "min": "30", "mon": "05", "year": "2015", "pretty": "11:30 AM CEST on May 18, 2015", "tzname": "Europe/Warsaw"}}, {"metar": "AAXX 18101 12566 42984 22304 10159 20012 39888 40174 57020 80002 333 91204 555 90005", "hail": "0", "rain": "0", "conds": "Clear", "dewpti": "34", "wgusti": "", "tornado": "0", "tempi": "61", "snow": "0", "windchilli": "-999", "precipm": "", "heatindexm": "-9999", "visi": "31", "wdird": "230", "wdire": "SW", "wspdi": "8.9", "pressurei": "30.05", "wspdm": "14.4", "utcdate": {"mday": "18", "hour": "10", "min": "00", "mon": "05", "year": "2015", "pretty": "10:00 AM GMT on May 18, 2015", "tzname": "UTC"}, "thunder": "0", "pressurem": "1017", "fog": "0", "tempm": "16", "icon": "clear", "precipi": "", "wgustm": "", "dewptm": "1", "hum": "25", "heatindexi": "-9999", "windchillm": "-999", "vism": "50", "date": {"mday": "18", "hour": "12", "min": "00", "mon": "05", "year": "2015", "pretty": "12:00 PM CEST on May 18, 2015", "tzname": "Europe/Warsaw"}}, {"metar": "METAR EPKK 181000Z 24007KT 200V300 CAVOK 16/03 Q1017", "hail": "0", "rain": "0", "conds": "Clear", "dewpti": "37.4", "wgusti": "-9999.0", "tornado": "0", "tempi": "60.8", "snow": "0", "windchilli": "-999", "precipm": "-9999.00", "heatindexm": "-9999", "visi": "-9999.0", "wdird": "240", "wdire": "WSW", "wspdi": "8.1", "pressurei": "30.04", "wspdm": "13.0", "utcdate": {"mday": "18", "hour": "10", "min": "00", "mon": "05", "year": "2015", "pretty": "10:00 AM GMT on May 18, 2015", "tzname": "UTC"}, "thunder": "0", "pressurem": "1017", "fog": "0", "tempm": "16.0", "icon": "clear", "precipi": "-9999.00", "wgustm": "-9999.0", "dewptm": "3.0", "hum": "42", "heatindexi": "-9999", "windchillm": "-999", "vism": "-9999.0", "date": {"mday": "18", "hour": "12", "min": "00", "mon": "05", "year": "2015", "pretty": "12:00 PM CEST on May 18, 2015", "tzname": "Europe/Warsaw"}}, {"metar": "METAR EPKK 181030Z 25007KT CAVOK 17/02 Q1017", "hail": "0", "rain": "0", "conds": "Clear", "dewpti": "35.6", "wgusti": "-9999.0", "tornado": "0", "tempi": "62.6", "snow": "0", "windchilli": "-999", "precipm": "-9999.00", "heatindexm": "-9999", "visi": "-9999.0", "wdird": "250", "wdire": "WSW", "wspdi": "8.1", "pressurei": "30.04", "wspdm": "13.0", "utcdate": {"mday": "18", "hour": "10", "min": "30", "mon": "05", "year": "2015", "pretty": "10:30 AM GMT on May 18, 2015", "tzname": "UTC"}, "thunder": "0", "pressurem": "1017", "fog": "0", "tempm": "17.0", "icon": "clear", "precipi": "-9999.00", "wgustm": "-9999.0", "dewptm": "2.0", "hum": "37", "heatindexi": "-9999", "windchillm": "-999", "vism": "-9999.0", "date": {"mday": "18", "hour": "12", "min": "30", "mon": "05", "year": "2015", "pretty": "12:30 PM CEST on May 18, 2015", "tzname": "Europe/Warsaw"}}, {"metar": "AAXX 18111 12566 42984 32405 10173 20013 39881 40166 57020 80002 333 91205 555 90005", "hail": "0", "rain": "0", "conds": "Clear", "dewpti": "34", "wgusti": "", "tornado": "0", "tempi": "63", "snow": "0", "windchilli": "-999", "precipm": "", "heatindexm": "-9999", "visi": "31", "wdird": "240", "wdire": "WSW", "wspdi": "11.2", "pressurei": "30.02", "wspdm": "18.0", "utcdate": {"mday": "18", "hour": "11", "min": "00", "mon": "05", "year": "2015", "pretty": "11:00 AM GMT on May 18, 2015", "tzname": "UTC"}, "thunder": "0", "pressurem": "1017", "fog": "0", "tempm": "17", "icon": "clear", "precipi": "", "wgustm": "", "dewptm": "1", "hum": "23", "heatindexi": "-9999", "windchillm": "-999", "vism": "50", "date": {"mday": "18", "hour": "13", "min": "00", "mon": "05", "year": "2015", "pretty": "1:00 PM CEST on May 18, 2015", "tzname": "Europe/Warsaw"}}, {"metar": "METAR EPKK 181100Z 24009KT 210V300 CAVOK 18/04 Q1016", "hail": "0", "rain": "0", "conds": "Clear", "dewpti": "39.2", "wgusti": "-9999.0", "tornado": "0", "tempi": "64.4", "snow": "0", "windchilli": "-999", "precipm": "-9999.00", "heatindexm": "-9999", "visi": "-9999.0", "wdird": "240", "wdire": "WSW", "wspdi": "10.4", "pressurei": "30.01", "wspdm": "16.7", "utcdate": {"mday": "18", "hour": "11", "min": "00", "mon": "05", "year": "2015", "pretty": "11:00 AM GMT on May 18, 2015", "tzname": "UTC"}, "thunder": "0", "pressurem": "1016", "fog": "0", "tempm": "18.0", "icon": "clear", "precipi": "-9999.00", "wgustm": "-9999.0", "dewptm": "4.0", "hum": "40", "heatindexi": "-9999", "windchillm": "-999", "vism": "-9999.0", "date": {"mday": "18", "hour": "13", "min": "00", "mon": "05", "year": "2015", "pretty": "1:00 PM CEST on May 18, 2015", "tzname": "Europe/Warsaw"}}, {"metar": "METAR EPKK 181130Z 27007KT 230V330 CAVOK 18/00 Q1016", "hail": "0", "rain": "0", "conds": "Clear", "dewpti": "32.0", "wgusti": "-9999.0", "tornado": "0", "tempi": "64.4", "snow": "0", "windchilli": "-999", "precipm": "-9999.00", "heatindexm": "-9999", "visi": "-9999.0", "wdird": "270", "wdire": "West", "wspdi": "8.1", "pressurei": "30.01", "wspdm": "13.0", "utcdate": {"mday": "18", "hour": "11", "min": "30", "mon": "05", "year": "2015", "pretty": "11:30 AM GMT on May 18, 2015", "tzname": "UTC"}, "thunder": "0", "pressurem": "1016", "fog": "0", "tempm": "18.0", "icon": "clear", "precipi": "-9999.00", "wgustm": "-9999.0", "dewptm": "0.0", "hum": "30", "heatindexi": "-9999", "windchillm": "-999", "vism": "-9999.0", "date": {"mday": "18", "hour": "13", "min": "30", "mon": "05", "year": "2015", "pretty": "1:30 PM CEST on May 18, 2015", "tzname": "Europe/Warsaw"}}, {"metar": "AAXX 18121 12566 12984 32403 10183 20004 39870 40153 58026 60001 80002 333 91108 91205 93000", "hail": "0", "rain": "0", "conds": "Clear", "dewpti": "33", "wgusti": "", "tornado": "0", "tempi": "65", "snow": "0", "windchilli": "-999", "precipm": "", "heatindexm": "-9999", "visi": "31", "wdird": "240", "wdire": "WSW", "wspdi": "6.7", "pressurei": "29.99", "wspdm": "10.8", "utcdate": {"mday": "18", "hour": "12", "min": "00", "mon": "05", "year": "2015", "pretty": "12:00 PM GMT on May 18, 2015", "tzname": "UTC"}, "thunder": "0", "pressurem": "1015", "fog": "0", "tempm": "18", "icon": "clear", "precipi": "", "wgustm": "", "dewptm": "0", "hum": "19", "heatindexi": "-9999", "windchillm": "-999", "vism": "50", "date": {"mday": "18", "hour": "14", "min": "00", "mon": "05", "year": "2015", "pretty": "2:00 PM CEST on May 18, 2015", "tzname": "Europe/Warsaw"}}, {"metar": "METAR EPKK 181200Z 26006KT 210V320 CAVOK 18/01 Q1015", "hail": "0", "rain": "0", "conds": "Clear", "dewpti": "33.8", "wgusti": "-9999.0", "tornado": "0", "tempi": "64.4", "snow": "0", "windchilli": "-999", "precipm": "-9999.00", "heatindexm": "-9999", "visi": "-9999.0", "wdird": "260", "wdire": "West", "wspdi": "6.9", "pressurei": "29.98", "wspdm": "11.1", "utcdate": {"mday": "18", "hour": "12", "min": "00", "mon": "05", "year": "2015", "pretty": "12:00 PM GMT on May 18, 2015", "tzname": "UTC"}, "thunder": "0", "pressurem": "1015", "fog": "0", "tempm": "18.0", "icon": "clear", "precipi": "-9999.00", "wgustm": "-9999.0", "dewptm": "1.0", "hum": "32", "heatindexi": "-9999", "windchillm": "-999", "vism": "-9999.0", "date": {"mday": "18", "hour": "14", "min": "00", "mon": "05", "year": "2015", "pretty": "2:00 PM CEST on May 18, 2015", "tzname": "Europe/Warsaw"}}, {"metar": "METAR EPKK 181230Z 26005KT 200V320 CAVOK 19/02 Q1015", "hail": "0", "rain": "0", "conds": "Clear", "dewpti": "35.6", "wgusti": "-9999.0", "tornado": "0", "tempi": "66.2", "snow": "0", "windchilli": "-999", "precipm": "-9999.00", "heatindexm": "-9999", "visi": "-9999.0", "wdird": "260", "wdire": "West", "wspdi": "5.8", "pressurei": "29.98", "wspdm": "9.3", "utcdate": {"mday": "18", "hour": "12", "min": "30", "mon": "05", "year": "2015", "pretty": "12:30 PM GMT on May 18, 2015", "tzname": "UTC"}, "thunder": "0", "pressurem": "1015", "fog": "0", "tempm": "19.0", "icon": "clear", "precipi": "-9999.00", "wgustm": "-9999.0", "dewptm": "2.0", "hum": "32", "heatindexi": "-9999", "windchillm": "-999", "vism": "-9999.0", "date": {"mday": "18", "hour": "14", "min": "30", "mon": "05", "year": "2015", "pretty": "2:30 PM CEST on May 18, 2015", "tzname": "Europe/Warsaw"}}, {"metar": "AAXX 18131 12566 42984 32703 10189 20009 39860 40142 58028 80002 333 91203 555 57147 90005", "hail": "0", "rain": "0", "conds": "Clear", "dewpti": "34", "wgusti": "", "tornado": "0", "tempi": "66", "snow": "0", "windchilli": "-999", "precipm": "", "heatindexm": "-9999", "visi": "31", "wdird": "270", "wdire": "West", "wspdi": "6.7", "pressurei": "29.95", "wspdm": "10.8", "utcdate": {"mday": "18", "hour": "13", "min": "00", "mon": "05", "year": "2015", "pretty": "1:00 PM GMT on May 18, 2015", "tzname": "UTC"}, "thunder": "0", "pressurem": "1014", "fog": "0", "tempm": "19", "icon": "clear", "precipi": "", "wgustm": "", "dewptm": "1", "hum": "19", "heatindexi": "-9999", "windchillm": "-999", "vism": "50", "date": {"mday": "18", "hour": "15", "min": "00", "mon": "05", "year": "2015", "pretty": "3:00 PM CEST on May 18, 2015", "tzname": "Europe/Warsaw"}}, {"metar": "METAR EPKK 181300Z 25006KT 190V300 CAVOK 19/02 Q1014", "hail": "0", "rain": "0", "conds": "Clear", "dewpti": "35.6", "wgusti": "-9999.0", "tornado": "0", "tempi": "66.2", "snow": "0", "windchilli": "-999", "precipm": "-9999.00", "heatindexm": "-9999", "visi": "-9999.0", "wdird": "250", "wdire": "WSW", "wspdi": "6.9", "pressurei": "29.95", "wspdm": "11.1", "utcdate": {"mday": "18", "hour": "13", "min": "00", "mon": "05", "year": "2015", "pretty": "1:00 PM GMT on May 18, 2015", "tzname": "UTC"}, "thunder": "0", "pressurem": "1014", "fog": "0", "tempm": "19.0", "icon": "clear", "precipi": "-9999.00", "wgustm": "-9999.0", "dewptm": "2.0", "hum": "32", "heatindexi": "-9999", "windchillm": "-999", "vism": "-9999.0", "date": {"mday": "18", "hour": "15", "min": "00", "mon": "05", "year": "2015", "pretty": "3:00 PM CEST on May 18, 2015", "tzname": "Europe/Warsaw"}}, {"metar": "METAR EPKK 181330Z 19005KT 150V250 CAVOK 19/03 Q1014", "hail": "0", "rain": "0", "conds": "Clear", "dewpti": "37.4", "wgusti": "-9999.0", "tornado": "0", "tempi": "66.2", "snow": "0", "windchilli": "-999", "precipm": "-9999.00", "heatindexm": "-9999", "visi": "-9999.0", "wdird": "190", "wdire": "South", "wspdi": "5.8", "pressurei": "29.95", "wspdm": "9.3", "utcdate": {"mday": "18", "hour": "13", "min": "30", "mon": "05", "year": "2015", "pretty": "1:30 PM GMT on May 18, 2015", "tzname": "UTC"}, "thunder": "0", "pressurem": "1014", "fog": "0", "tempm": "19.0", "icon": "clear", "precipi": "-9999.00", "wgustm": "-9999.0", "dewptm": "3.0", "hum": "35", "heatindexi": "-9999", "windchillm": "-999", "vism": "-9999.0", "date": {"mday": "18", "hour": "15", "min": "30", "mon": "05", "year": "2015", "pretty": "3:30 PM CEST on May 18, 2015", "tzname": "Europe/Warsaw"}}, {"metar": "AAXX 18141 12566 42984 22703 10195 20032 39851 40133 56030 80002 333 91204 555 90005", "hail": "0", "rain": "0", "conds": "Clear", "dewpti": "38", "wgusti": "", "tornado": "0", "tempi": "67", "snow": "0", "windchilli": "-999", "precipm": "", "heatindexm": "-9999", "visi": "31", "wdird": "270", "wdire": "West", "wspdi": "6.7", "pressurei": "29.93", "wspdm": "10.8", "utcdate": {"mday": "18", "hour": "14", "min": "00", "mon": "05", "year": "2015", "pretty": "2:00 PM GMT on May 18, 2015", "tzname": "UTC"}, "thunder": "0", "pressurem": "1013", "fog": "0", "tempm": "20", "icon": "clear", "precipi": "", "wgustm": "", "dewptm": "3", "hum": "23", "heatindexi": "-9999", "windchillm": "-999", "vism": "50", "date": {"mday": "18", "hour": "16", "min": "00", "mon": "05", "year": "2015", "pretty": "4:00 PM CEST on May 18, 2015", "tzname": "Europe/Warsaw"}}, {"metar": "METAR EPKK 181400Z 25005KT 220V320 CAVOK 19/03 Q1013", "hail": "0", "rain": "0", "conds": "Clear", "dewpti": "37.4", "wgusti": "-9999.0", "tornado": "0", "tempi": "66.2", "snow": "0", "windchilli": "-999", "precipm": "-9999.00", "heatindexm": "-9999", "visi": "-9999.0", "wdird": "250", "wdire": "WSW", "wspdi": "5.8", "pressurei": "29.92", "wspdm": "9.3", "utcdate": {"mday": "18", "hour": "14", "min": "00", "mon": "05", "year": "2015", "pretty": "2:00 PM GMT on May 18, 2015", "tzname": "UTC"}, "thunder": "0", "pressurem": "1013", "fog": "0", "tempm": "19.0", "icon": "clear", "precipi": "-9999.00", "wgustm": "-9999.0", "dewptm": "3.0", "hum": "35", "heatindexi": "-9999", "windchillm": "-999", "vism": "-9999.0", "date": {"mday": "18", "hour": "16", "min": "00", "mon": "05", "year": "2015", "pretty": "4:00 PM CEST on May 18, 2015", "tzname": "Europe/Warsaw"}}, {"metar": "METAR EPKK 181430Z 26003KT 9999 FEW060 20/04 Q1013", "hail": "0", "rain": "0", "conds": "Partly Cloudy", "dewpti": "39.2", "wgusti": "-9999.0", "tornado": "0", "tempi": "68.0", "snow": "0", "windchilli": "-999", "precipm": "-9999.00", "heatindexm": "-9999", "visi": "6.2", "wdird": "260", "wdire": "West", "wspdi": "3.5", "pressurei": "29.92", "wspdm": "5.6", "utcdate": {"mday": "18", "hour": "14", "min": "30", "mon": "05", "year": "2015", "pretty": "2:30 PM GMT on May 18, 2015", "tzname": "UTC"}, "thunder": "0", "pressurem": "1013", "fog": "0", "tempm": "20.0", "icon": "partlycloudy", "precipi": "-9999.00", "wgustm": "-9999.0", "dewptm": "4.0", "hum": "35", "heatindexi": "-9999", "windchillm": "-999", "vism": "10.0", "date": {"mday": "18", "hour": "16", "min": "30", "mon": "05", "year": "2015", "pretty": "4:30 PM CEST on May 18, 2015", "tzname": "Europe/Warsaw"}}, {"metar": "AAXX 18151 12566 42784 22503 10199 20040 39844 40125 56026 81101 333 91204", "hail": "0", "rain": "0", "conds": "Scattered Clouds", "dewpti": "39", "wgusti": "", "tornado": "0", "tempi": "68", "snow": "0", "windchilli": "-999", "precipm": "", "heatindexm": "-9999", "visi": "31", "wdird": "250", "wdire": "WSW", "wspdi": "6.7", "pressurei": "29.90", "wspdm": "10.8", "utcdate": {"mday": "18", "hour": "15", "min": "00", "mon": "05", "year": "2015", "pretty": "3:00 PM GMT on May 18, 2015", "tzname": "UTC"}, "thunder": "0", "pressurem": "1012", "fog": "0", "tempm": "20", "icon": "partlycloudy", "precipi": "", "wgustm": "", "dewptm": "4", "hum": "24", "heatindexi": "-9999", "windchillm": "-999", "vism": "50", "date": {"mday": "18", "hour": "17", "min": "00", "mon": "05", "year": "2015", "pretty": "5:00 PM CEST on May 18, 2015", "tzname": "Europe/Warsaw"}}, {"metar": "METAR EPKK 181500Z 25005KT 210V300 9999 FEW060 20/04 Q1013", "hail": "0", "rain": "0", "conds": "Partly Cloudy", "dewpti": "39.2", "wgusti": "-9999.0", "tornado": "0", "tempi": "68.0", "snow": "0", "windchilli": "-999", "precipm": "-9999.00", "heatindexm": "-9999", "visi": "6.2", "wdird": "250", "wdire": "WSW", "wspdi": "5.8", "pressurei": "29.92", "wspdm": "9.3", "utcdate": {"mday": "18", "hour": "15", "min": "00", "mon": "05", "year": "2015", "pretty": "3:00 PM GMT on May 18, 2015", "tzname": "UTC"}, "thunder": "0", "pressurem": "1013", "fog": "0", "tempm": "20.0", "icon": "partlycloudy", "precipi": "-9999.00", "wgustm": "-9999.0", "dewptm": "4.0", "hum": "35", "heatindexi": "-9999", "windchillm": "-999", "vism": "10.0", "date": {"mday": "18", "hour": "17", "min": "00", "mon": "05", "year": "2015", "pretty": "5:00 PM CEST on May 18, 2015", "tzname": "Europe/Warsaw"}}, {"metar": "METAR EPKK 181530Z 24005KT 200V290 9999 FEW060 20/04 Q1012", "hail": "0", "rain": "0", "conds": "Partly Cloudy", "dewpti": "39.2", "wgusti": "-9999.0", "tornado": "0", "tempi": "68.0", "snow": "0", "windchilli": "-999", "precipm": "-9999.00", "heatindexm": "-9999", "visi": "6.2", "wdird": "240", "wdire": "WSW", "wspdi": "5.8", "pressurei": "29.89", "wspdm": "9.3", "utcdate": {"mday": "18", "hour": "15", "min": "30", "mon": "05", "year": "2015", "pretty": "3:30 PM GMT on May 18, 2015", "tzname": "UTC"}, "thunder": "0", "pressurem": "1012", "fog": "0", "tempm": "20.0", "icon": "partlycloudy", "precipi": "-9999.00", "wgustm": "-9999.0", "dewptm": "4.0", "hum": "35", "heatindexi": "-9999", "windchillm": "-999", "vism": "10.0", "date": {"mday": "18", "hour": "17", "min": "30", "mon": "05", "year": "2015", "pretty": "5:30 PM CEST on May 18, 2015", "tzname": "Europe/Warsaw"}}, {"metar": "AAXX 18161 12566 42784 22301 10197 20050 39837 40118 57023 81101 333 91203 555 90005", "hail": "0", "rain": "0", "conds": "Scattered Clouds", "dewpti": "41", "wgusti": "", "tornado": "0", "tempi": "67", "snow": "0", "windchilli": "-999", "precipm": "", "heatindexm": "-9999", "visi": "31", "wdird": "230", "wdire": "SW", "wspdi": "2.2", "pressurei": "29.88", "wspdm": "3.6", "utcdate": {"mday": "18", "hour": "16", "min": "00", "mon": "05", "year": "2015", "pretty": "4:00 PM GMT on May 18, 2015", "tzname": "UTC"}, "thunder": "0", "pressurem": "1012", "fog": "0", "tempm": "20", "icon": "partlycloudy", "precipi": "", "wgustm": "", "dewptm": "5", "hum": "27", "heatindexi": "-9999", "windchillm": "-999", "vism": "50", "date": {"mday": "18", "hour": "18", "min": "00", "mon": "05", "year": "2015", "pretty": "6:00 PM CEST on May 18, 2015", "tzname": "Europe/Warsaw"}}, {"metar": "METAR EPKK 181600Z VRB02KT 9999 FEW060 20/03 Q1012", "hail": "0", "rain": "0", "conds": "Partly Cloudy", "dewpti": "37.4", "wgusti": "-9999.0", "tornado": "0", "tempi": "68.0", "snow": "0", "windchilli": "-999", "precipm": "-9999.00", "heatindexm": "-9999", "visi": "6.2", "wdird": "0", "wdire": "Variable", "wspdi": "2.3", "pressurei": "29.89", "wspdm": "3.7", "utcdate": {"mday": "18", "hour": "16", "min": "00", "mon": "05", "year": "2015", "pretty": "4:00 PM GMT on May 18, 2015", "tzname": "UTC"}, "thunder": "0", "pressurem": "1012", "fog": "0", "tempm": "20.0", "icon": "partlycloudy", "precipi": "-9999.00", "wgustm": "-9999.0", "dewptm": "3.0", "hum": "33", "heatindexi": "-9999", "windchillm": "-999", "vism": "10.0", "date": {"mday": "18", "hour": "18", "min": "00", "mon": "05", "year": "2015", "pretty": "6:00 PM CEST on May 18, 2015", "tzname": "Europe/Warsaw"}}, {"metar": "METAR EPKK 181630Z VRB02KT 9999 FEW060 20/05 Q1012", "hail": "0", "rain": "0", "conds": "Partly Cloudy", "dewpti": "41.0", "wgusti": "-9999.0", "tornado": "0", "tempi": "68.0", "snow": "0", "windchilli": "-999", "precipm": "-9999.00", "heatindexm": "-9999", "visi": "6.2", "wdird": "0", "wdire": "Variable", "wspdi": "2.3", "pressurei": "29.89", "wspdm": "3.7", "utcdate": {"mday": "18", "hour": "16", "min": "30", "mon": "05", "year": "2015", "pretty": "4:30 PM GMT on May 18, 2015", "tzname": "UTC"}, "thunder": "0", "pressurem": "1012", "fog": "0", "tempm": "20.0", "icon": "partlycloudy", "precipi": "-9999.00", "wgustm": "-9999.0", "dewptm": "5.0", "hum": "37", "heatindexi": "-9999", "windchillm": "-999", "vism": "10.0", "date": {"mday": "18", "hour": "18", "min": "30", "mon": "05", "year": "2015", "pretty": "6:30 PM CEST on May 18, 2015", "tzname": "Europe/Warsaw"}}, {"metar": "AAXX 18171 12566 42984 11801 10192 20038 39832 40113 57019 80001 333 91202 555 90005", "hail": "0", "rain": "0", "conds": "Clear", "dewpti": "39", "wgusti": "", "tornado": "0", "tempi": "67", "snow": "0", "windchilli": "-999", "precipm": "", "heatindexm": "-9999", "visi": "31", "wdird": "180", "wdire": "South", "wspdi": "2.2", "pressurei": "29.87", "wspdm": "3.6", "utcdate": {"mday": "18", "hour": "17", "min": "00", "mon": "05", "year": "2015", "pretty": "5:00 PM GMT on May 18, 2015", "tzname": "UTC"}, "thunder": "0", "pressurem": "1011", "fog": "0", "tempm": "19", "icon": "clear", "precipi": "", "wgustm": "", "dewptm": "4", "hum": "24", "heatindexi": "-9999", "windchillm": "-999", "vism": "50", "date": {"mday": "18", "hour": "19", "min": "00", "mon": "05", "year": "2015", "pretty": "7:00 PM CEST on May 18, 2015", "tzname": "Europe/Warsaw"}}, {"metar": "METAR EPKK 181700Z VRB02KT CAVOK 19/04 Q1011", "hail": "0", "rain": "0", "conds": "Clear", "dewpti": "39.2", "wgusti": "-9999.0", "tornado": "0", "tempi": "66.2", "snow": "0", "windchilli": "-999", "precipm": "-9999.00", "heatindexm": "-9999", "visi": "-9999.0", "wdird": "0", "wdire": "Variable", "wspdi": "2.3", "pressurei": "29.86", "wspdm": "3.7", "utcdate": {"mday": "18", "hour": "17", "min": "00", "mon": "05", "year": "2015", "pretty": "5:00 PM GMT on May 18, 2015", "tzname": "UTC"}, "thunder": "0", "pressurem": "1011", "fog": "0", "tempm": "19.0", "icon": "clear", "precipi": "-9999.00", "wgustm": "-9999.0", "dewptm": "4.0", "hum": "37", "heatindexi": "-9999", "windchillm": "-999", "vism": "-9999.0", "date": {"mday": "18", "hour": "19", "min": "00", "mon": "05", "year": "2015", "pretty": "7:00 PM CEST on May 18, 2015", "tzname": "Europe/Warsaw"}}, {"metar": "METAR EPKK 181730Z VRB02KT CAVOK 19/05 Q1011", "hail": "0", "rain": "0", "conds": "Clear", "dewpti": "41.0", "wgusti": "-9999.0", "tornado": "0", "tempi": "66.2", "snow": "0", "windchilli": "-999", "precipm": "-9999.00", "heatindexm": "-9999", "visi": "-9999.0", "wdird": "0", "wdire": "Variable", "wspdi": "2.3", "pressurei": "29.86", "wspdm": "3.7", "utcdate": {"mday": "18", "hour": "17", "min": "30", "mon": "05", "year": "2015", "pretty": "5:30 PM GMT on May 18, 2015", "tzname": "UTC"}, "thunder": "0", "pressurem": "1011", "fog": "0", "tempm": "19.0", "icon": "clear", "precipi": "-9999.00", "wgustm": "-9999.0", "dewptm": "5.0", "hum": "40", "heatindexi": "-9999", "windchillm": "-999", "vism": "-9999.0", "date": {"mday": "18", "hour": "19", "min": "30", "mon": "05", "year": "2015", "pretty": "7:30 PM CEST on May 18, 2015", "tzname": "Europe/Warsaw"}}, {"metar": "AAXX 18181 12566 12784 21501 10174 20063 39827 40110 57017 60002 82501 333 10201 20104 91204 93000", "hail": "0", "rain": "0", "conds": "Scattered Clouds", "dewpti": "43", "wgusti": "", "tornado": "0", "tempi": "63", "snow": "0", "windchilli": "-999", "precipm": "", "heatindexm": "-9999", "visi": "31", "wdird": "150", "wdire": "SSE", "wspdi": "2.2", "pressurei": "29.86", "wspdm": "3.6", "utcdate": {"mday": "18", "hour": "18", "min": "00", "mon": "05", "year": "2015", "pretty": "6:00 PM GMT on May 18, 2015", "tzname": "UTC"}, "thunder": "0", "pressurem": "1011", "fog": "0", "tempm": "17", "icon": "partlycloudy", "precipi": "", "wgustm": "", "dewptm": "6", "hum": "37", "heatindexi": "-9999", "windchillm": "-999", "vism": "50", "date": {"mday": "18", "hour": "20", "min": "00", "mon": "05", "year": "2015", "pretty": "8:00 PM CEST on May 18, 2015", "tzname": "Europe/Warsaw"}}, {"metar": "METAR EPKK 181800Z VRB01KT 9999 FEW060 18/06 Q1011", "hail": "0", "rain": "0", "conds": "Partly Cloudy", "dewpti": "42.8", "wgusti": "-9999.0", "tornado": "0", "tempi": "64.4", "snow": "0", "windchilli": "-999", "precipm": "-9999.00", "heatindexm": "-9999", "visi": "6.2", "wdird": "0", "wdire": "Variable", "wspdi": "1.2", "pressurei": "29.86", "wspdm": "1.9", "utcdate": {"mday": "18", "hour": "18", "min": "00", "mon": "05", "year": "2015", "pretty": "6:00 PM GMT on May 18, 2015", "tzname": "UTC"}, "thunder": "0", "pressurem": "1011", "fog": "0", "tempm": "18.0", "icon": "partlycloudy", "precipi": "-9999.00", "wgustm": "-9999.0", "dewptm": "6.0", "hum": "45", "heatindexi": "-9999", "windchillm": "-999", "vism": "10.0", "date": {"mday": "18", "hour": "20", "min": "00", "mon": "05", "year": "2015", "pretty": "8:00 PM CEST on May 18, 2015", "tzname": "Europe/Warsaw"}}, {"metar": "METAR EPKK 181830Z VRB01KT 9999 FEW060 15/08 Q1011", "hail": "0", "rain": "0", "conds": "Partly Cloudy", "dewpti": "46.4", "wgusti": "-9999.0", "tornado": "0", "tempi": "59.0", "snow": "0", "windchilli": "-999", "precipm": "-9999.00", "heatindexm": "-9999", "visi": "6.2", "wdird": "0", "wdire": "Variable", "wspdi": "1.2", "pressurei": "29.86", "wspdm": "1.9", "utcdate": {"mday": "18", "hour": "18", "min": "30", "mon": "05", "year": "2015", "pretty": "6:30 PM GMT on May 18, 2015", "tzname": "UTC"}, "thunder": "0", "pressurem": "1011", "fog": "0", "tempm": "15.0", "icon": "partlycloudy", "precipi": "-9999.00", "wgustm": "-9999.0", "dewptm": "8.0", "hum": "63", "heatindexi": "-9999", "windchillm": "-999", "vism": "10.0", "date": {"mday": "18", "hour": "20", "min": "30", "mon": "05", "year": "2015", "pretty": "8:30 PM CEST on May 18, 2015", "tzname": "Europe/Warsaw"}}, {"metar": "AAXX 18191 12566 42782 53601 10146 20074 39828 40114 55009 85501 333 91202 555 57103 90005", "hail": "0", "rain": "0", "conds": "Mostly Cloudy", "dewpti": "45", "wgusti": "", "tornado": "0", "tempi": "58", "snow": "0", "windchilli": "-999", "precipm": "", "heatindexm": "-9999", "visi": "25", "wdird": "0", "wdire": "North", "wspdi": "2.2", "pressurei": "29.87", "wspdm": "3.6", "utcdate": {"mday": "18", "hour": "19", "min": "00", "mon": "05", "year": "2015", "pretty": "7:00 PM GMT on May 18, 2015", "tzname": "UTC"}, "thunder": "0", "pressurem": "1011", "fog": "0", "tempm": "15", "icon": "mostlycloudy", "precipi": "", "wgustm": "", "dewptm": "7", "hum": "53", "heatindexi": "-9999", "windchillm": "-999", "vism": "40", "date": {"mday": "18", "hour": "21", "min": "00", "mon": "05", "year": "2015", "pretty": "9:00 PM CEST on May 18, 2015", "tzname": "Europe/Warsaw"}}, {"metar": "METAR EPKK 181900Z VRB01KT 9999 BKN060 14/07 Q1011", "hail": "0", "rain": "0", "conds": "Mostly Cloudy", "dewpti": "44.6", "wgusti": "-9999.0", "tornado": "0", "tempi": "57.2", "snow": "0", "windchilli": "-999", "precipm": "-9999.00", "heatindexm": "-9999", "visi": "6.2", "wdird": "0", "wdire": "Variable", "wspdi": "1.2", "pressurei": "29.86", "wspdm": "1.9", "utcdate": {"mday": "18", "hour": "19", "min": "00", "mon": "05", "year": "2015", "pretty": "7:00 PM GMT on May 18, 2015", "tzname": "UTC"}, "thunder": "0", "pressurem": "1011", "fog": "0", "tempm": "14.0", "icon": "mostlycloudy", "precipi": "-9999.00", "wgustm": "-9999.0", "dewptm": "7.0", "hum": "63", "heatindexi": "-9999", "windchillm": "-999", "vism": "10.0", "date": {"mday": "18", "hour": "21", "min": "00", "mon": "05", "year": "2015", "pretty": "9:00 PM CEST on May 18, 2015", "tzname": "Europe/Warsaw"}}, {"metar": "METAR EPKK 181930Z 00000KT 9999 BKN060 14/07 Q1011", "hail": "0", "rain": "0", "conds": "Mostly Cloudy", "dewpti": "44.6", "wgusti": "-9999.0", "tornado": "0", "tempi": "57.2", "snow": "0", "windchilli": "-999", "precipm": "-9999.00", "heatindexm": "-9999", "visi": "6.2", "wdird": "0", "wdire": "North", "wspdi": "0.0", "pressurei": "29.86", "wspdm": "0.0", "utcdate": {"mday": "18", "hour": "19", "min": "30", "mon": "05", "year": "2015", "pretty": "7:30 PM GMT on May 18, 2015", "tzname": "UTC"}, "thunder": "0", "pressurem": "1011", "fog": "0", "tempm": "14.0", "icon": "mostlycloudy", "precipi": "-9999.00", "wgustm": "-9999.0", "dewptm": "7.0", "hum": "63", "heatindexi": "-9999", "windchillm": "-999", "vism": "10.0", "date": {"mday": "18", "hour": "21", "min": "30", "mon": "05", "year": "2015", "pretty": "9:30 PM CEST on May 18, 2015", "tzname": "Europe/Warsaw"}}, {"metar": "AAXX 18201 12566 42780 40501 10135 20068 39826 40113 56006 84500 333 91201 555 00133 10153 20114 30029 90005", "hail": "0", "rain": "0", "conds": "Partly Cloudy", "dewpti": "44", "wgusti": "", "tornado": "0", "tempi": "56", "snow": "0", "windchilli": "-999", "precipm": "", "heatindexm": "-9999", "visi": "19", "wdird": "50", "wdire": "NE", "wspdi": "2.2", "pressurei": "29.87", "wspdm": "3.6", "utcdate": {"mday": "18", "hour": "20", "min": "00", "mon": "05", "year": "2015", "pretty": "8:00 PM GMT on May 18, 2015", "tzname": "UTC"}, "thunder": "0", "pressurem": "1011", "fog": "0", "tempm": "14", "icon": "partlycloudy", "precipi": "", "wgustm": "", "dewptm": "7", "hum": "55", "heatindexi": "-9999", "windchillm": "-999", "vism": "30", "date": {"mday": "18", "hour": "22", "min": "00", "mon": "05", "year": "2015", "pretty": "10:00 PM CEST on May 18, 2015", "tzname": "Europe/Warsaw"}}, {"metar": "METAR EPKK 182000Z 00000KT 9999 SCT060 13/07 Q1011", "hail": "0", "rain": "0", "conds": "Scattered Clouds", "dewpti": "44.6", "wgusti": "-9999.0", "tornado": "0", "tempi": "55.4", "snow": "0", "windchilli": "-999", "precipm": "-9999.00", "heatindexm": "-9999", "visi": "6.2", "wdird": "0", "wdire": "North", "wspdi": "0.0", "pressurei": "29.86", "wspdm": "0.0", "utcdate": {"mday": "18", "hour": "20", "min": "00", "mon": "05", "year": "2015", "pretty": "8:00 PM GMT on May 18, 2015", "tzname": "UTC"}, "thunder": "0", "pressurem": "1011", "fog": "0", "tempm": "13.0", "icon": "partlycloudy", "precipi": "-9999.00", "wgustm": "-9999.0", "dewptm": "7.0", "hum": "67", "heatindexi": "-9999", "windchillm": "-999", "vism": "10.0", "date": {"mday": "18", "hour": "22", "min": "00", "mon": "05", "year": "2015", "pretty": "10:00 PM CEST on May 18, 2015", "tzname": "Europe/Warsaw"}}, {"metar": "METAR EPKK 182030Z VRB01KT 9999 SCT060 13/08 Q1011", "hail": "0", "rain": "0", "conds": "Scattered Clouds", "dewpti": "46.4", "wgusti": "-9999.0", "tornado": "0", "tempi": "55.4", "snow": "0", "windchilli": "-999", "precipm": "-9999.00", "heatindexm": "-9999", "visi": "6.2", "wdird": "0", "wdire": "Variable", "wspdi": "1.2", "pressurei": "29.86", "wspdm": "1.9", "utcdate": {"mday": "18", "hour": "20", "min": "30", "mon": "05", "year": "2015", "pretty": "8:30 PM GMT on May 18, 2015", "tzname": "UTC"}, "thunder": "0", "pressurem": "1011", "fog": "0", "tempm": "13.0", "icon": "partlycloudy", "precipi": "-9999.00", "wgustm": "-9999.0", "dewptm": "8.0", "hum": "72", "heatindexi": "-9999", "windchillm": "-999", "vism": "10.0", "date": {"mday": "18", "hour": "22", "min": "30", "mon": "05", "year": "2015", "pretty": "10:30 PM CEST on May 18, 2015", "tzname": "Europe/Warsaw"}}, {"metar": "AAXX 18211 12566 42780 30101 10121 20064 39823 40111 58004 83500 333 91202", "hail": "0", "rain": "0", "conds": "Partly Cloudy", "dewpti": "44", "wgusti": "", "tornado": "0", "tempi": "54", "snow": "0", "windchilli": "-999", "precipm": "", "heatindexm": "-9999", "visi": "19", "wdird": "10", "wdire": "North", "wspdi": "2.2", "pressurei": "29.86", "wspdm": "3.6", "utcdate": {"mday": "18", "hour": "21", "min": "00", "mon": "05", "year": "2015", "pretty": "9:00 PM GMT on May 18, 2015", "tzname": "UTC"}, "thunder": "0", "pressurem": "1011", "fog": "0", "tempm": "12", "icon": "partlycloudy", "precipi": "", "wgustm": "", "dewptm": "6", "hum": "58", "heatindexi": "-9999", "windchillm": "-999", "vism": "30", "date": {"mday": "18", "hour": "23", "min": "00", "mon": "05", "year": "2015", "pretty": "11:00 PM CEST on May 18, 2015", "tzname": "Europe/Warsaw"}}, {"metar": "METAR EPKK 182100Z VRB01KT 9999 SCT053 12/07 Q1011", "hail": "0", "rain": "0", "conds": "Scattered Clouds", "dewpti": "44.6", "wgusti": "-9999.0", "tornado": "0", "tempi": "53.6", "snow": "0", "windchilli": "-999", "precipm": "-9999.00", "heatindexm": "-9999", "visi": "6.2", "wdird": "0", "wdire": "Variable", "wspdi": "1.2", "pressurei": "29.86", "wspdm": "1.9", "utcdate": {"mday": "18", "hour": "21", "min": "00", "mon": "05", "year": "2015", "pretty": "9:00 PM GMT on May 18, 2015", "tzname": "UTC"}, "thunder": "0", "pressurem": "1011", "fog": "0", "tempm": "12.0", "icon": "partlycloudy", "precipi": "-9999.00", "wgustm": "-9999.0", "dewptm": "7.0", "hum": "72", "heatindexi": "-9999", "windchillm": "-999", "vism": "10.0", "date": {"mday": "18", "hour": "23", "min": "00", "mon": "05", "year": "2015", "pretty": "11:00 PM CEST on May 18, 2015", "tzname": "Europe/Warsaw"}}, {"metar": "METAR EPKK 182130Z VRB02KT 9999 SCT053 13/06 Q1010", "hail": "0", "rain": "0", "conds": "Scattered Clouds", "dewpti": "42.8", "wgusti": "-9999.0", "tornado": "0", "tempi": "55.4", "snow": "0", "windchilli": "-999", "precipm": "-9999.00", "heatindexm": "-9999", "visi": "6.2", "wdird": "0", "wdire": "Variable", "wspdi": "2.3", "pressurei": "29.83", "wspdm": "3.7", "utcdate": {"mday": "18", "hour": "21", "min": "30", "mon": "05", "year": "2015", "pretty": "9:30 PM GMT on May 18, 2015", "tzname": "UTC"}, "thunder": "0", "pressurem": "1010", "fog": "0", "tempm": "13.0", "icon": "partlycloudy", "precipi": "-9999.00", "wgustm": "-9999.0", "dewptm": "6.0", "hum": "63", "heatindexi": "-9999", "windchillm": "-999", "vism": "10.0", "date": {"mday": "18", "hour": "23", "min": "30", "mon": "05", "year": "2015", "pretty": "11:30 PM CEST on May 18, 2015", "tzname": "Europe/Warsaw"}}], "utcdate": {"mday": "17", "hour": "22", "min": "00", "mon": "05", "year": "2015", "pretty": "May 17, 2015", "tzname": "UTC"}, "date": {"mday": "18", "hour": "00", "min": "00", "mon": "05", "year": "2015", "pretty": "May 18, 2015", "tzname": "Europe/Warsaw"}}, "response": {"termsofService": "http://www.wunderground.com/weather/api/d/terms.html", "features": {"history": 1}, "version": "0.1"}}