{"history": {"dailysummary": [{"snowfalli": "", "meanvisi": "8.2", "date": {"mon": "06", "pretty": "12:00 AM CEST on June 20, 2016", "mday": "20", "hour": "00", "min": "00", "tzname": "Europe/Warsaw", "year": "2016"}, "mindewpti": "57", "monthtodatesnowfalli": "", "monthtodatesnowfallm": "", "coolingdegreedays": "0", "meandewptm": "15", "gdegreedays": "15", "since1sepcoolingdegreedays": "", "meandewpti": "59", "fog": "0", "snowfallm": "", "snowdepthi": "", "rain": "1", "coolingdegreedaysnormal": "", "maxvisi": "19.0", "maxvism": "30.0", "maxwspdi": "18", "since1sepheatingdegreedaysnormal": "", "hail": "0", "maxdewptm": "16", "monthtodateheatingdegreedaysnormal": "", "meantempi": "65", "heatingdegreedays": "0", "precipi": "0.01", "thunder": "1", "since1jancoolingdegreedays": "", "since1jancoolingdegreedaysnormal": "", "meanwindspdi": "8", "minwspdm": "2", "meanvism": "13.2", "since1sepcoolingdegreedaysnormal": "", "minvism": "4.0", "meanpressurem": "1017.90", "maxpressurei": "30.16", "minhumidity": "61", "snowdepthm": "", "since1julsnowfalli": "", "maxhumidity": "94", "minpressurem": "1016", "mintempm": "15", "humidity": "82", "precipm": "0.2", "minwspdi": "1", "maxpressurem": "1021", "meantempm": "18", "minpressurei": "30.01", "meanwindspdm": "13", "monthtodatecoolingdegreedaysnormal": "", "since1sepheatingdegreedays": "", "mindewptm": "14", "tornado": "0", "meanpressurei": "30.06", "maxtempm": "21", "maxwspdm": "29", "minvisi": "2.5", "monthtodateheatingdegreedays": "", "maxdewpti": "62", "meanwdire": "WNW", "since1julsnowfallm": "", "mintempi": "60", "precipsource": "Precip6GroupSynop", "heatingdegreedaysnormal": "", "monthtodatecoolingdegreedays": "", "snow": "0", "since1julheatingdegreedays": "", "since1julheatingdegreedaysnormal": "", "maxtempi": "70", "meanwdird": "297"}], "date": {"mon": "06", "pretty": "June 20, 2016", "mday": "20", "hour": "00", "min": "00", "tzname": "Europe/Warsaw", "year": "2016"}, "observations": [{"tempm": "17", "pressurei": "30.04", "date": {"mon": "06", "pretty": "12:00 AM CEST on June 20, 2016", "mday": "20", "hour": "00", "min": "00", "tzname": "Europe/Warsaw", "year": "2016"}, "hum": "81", "icon": "rain", "metar": "AAXX 19221 12566 41650 73304 10167 20143 39886 40171 52001 79298 879// 333 91208 555 60196 90005", "precipm": "", "fog": "0", "wdird": "330", "rain": "1", "pressurem": "1017", "vism": "5", "tempi": "62", "utcdate": {"mon": "06", "pretty": "10:00 PM GMT on June 19, 2016", "mday": "19", "hour": "22", "min": "00", "tzname": "UTC", "year": "2016"}, "visi": "3", "tornado": "0", "hail": "0", "wdire": "NNW", "wspdi": "8.9", "windchilli": "-999", "wgusti": "", "windchillm": "-999", "wspdm": "14.4", "dewptm": "14", "precipi": "", "dewpti": "58", "thunder": "0", "wgustm": "", "conds": "Heavy Rain", "snow": "0", "heatindexm": "-9999", "heatindexi": "-9999"}, {"tempm": "17.0", "pressurei": "30.04", "date": {"mon": "06", "pretty": "12:00 AM CEST on June 20, 2016", "mday": "20", "hour": "00", "min": "00", "tzname": "Europe/Warsaw", "year": "2016"}, "hum": "88", "icon": "rain", "metar": "METAR EPKK 192200Z 33010KT 310V020 4000 SHRA BKN040CB 17/15 Q1017", "precipm": "-9999.00", "fog": "0", "wdird": "330", "rain": "1", "pressurem": "1017", "vism": "4.0", "tempi": "62.6", "utcdate": {"mon": "06", "pretty": "10:00 PM GMT on June 19, 2016", "mday": "19", "hour": "22", "min": "00", "tzname": "UTC", "year": "2016"}, "visi": "2.5", "tornado": "0", "hail": "0", "wdire": "NNW", "wspdi": "11.5", "windchilli": "-999", "wgusti": "-9999.0", "windchillm": "-999", "wspdm": "18.5", "dewptm": "15.0", "precipi": "-9999.00", "dewpti": "59.0", "thunder": "0", "wgustm": "-9999.0", "conds": "Rain Showers", "snow": "0", "heatindexm": "-9999", "heatindexi": "-9999"}, {"tempm": "16.0", "pressurei": "30.01", "date": {"mon": "06", "pretty": "12:30 AM CEST on June 20, 2016", "mday": "20", "hour": "00", "min": "30", "tzname": "Europe/Warsaw", "year": "2016"}, "hum": "94", "icon": "rain", "metar": "METAR EPKK 192230Z 31014KT 8000 -SHRA BKN040CB 16/15 Q1016 RESHRA", "precipm": "-9999.00", "fog": "0", "wdird": "310", "rain": "1", "pressurem": "1016", "vism": "8.0", "tempi": "60.8", "utcdate": {"mon": "06", "pretty": "10:30 PM GMT on June 19, 2016", "mday": "19", "hour": "22", "min": "30", "tzname": "UTC", "year": "2016"}, "visi": "5.0", "tornado": "0", "hail": "0", "wdire": "NW", "wspdi": "16.1", "windchilli": "-999", "wgusti": "-9999.0", "windchillm": "-999", "wspdm": "25.9", "dewptm": "15.0", "precipi": "-9999.00", "dewpti": "59.0", "thunder": "0", "wgustm": "-9999.0", "conds": "Light Rain Showers", "snow": "0", "heatindexm": "-9999", "heatindexi": "-9999"}, {"tempm": "16", "pressurei": "30.02", "date": {"mon": "06", "pretty": "1:00 AM CEST on June 20, 2016", "mday": "20", "hour": "01", "min": "00", "tzname": "Europe/Warsaw", "year": "2016"}, "hum": "84", "icon": "rain", "metar": "AAXX 19231 12566 41670 83108 10164 20146 39880 40165 58006 76188 875// 333 91208 555 90005", "precipm": "", "fog": "0", "wdird": "310", "rain": "1", "pressurem": "1016", "vism": "20", "tempi": "62", "utcdate": {"mon": "06", "pretty": "11:00 PM GMT on June 19, 2016", "mday": "19", "hour": "23", "min": "00", "tzname": "UTC", "year": "2016"}, "visi": "12", "tornado": "0", "hail": "0", "wdire": "NW", "wspdi": "17.9", "windchilli": "-999", "wgusti": "", "windchillm": "-999", "wspdm": "28.8", "dewptm": "15", "precipi": "", "dewpti": "58", "thunder": "0", "wgustm": "", "conds": "Light Rain", "snow": "0", "heatindexm": "-9999", "heatindexi": "-9999"}, {"tempm": "16.0", "pressurei": "30.01", "date": {"mon": "06", "pretty": "1:00 AM CEST on June 20, 2016", "mday": "20", "hour": "01", "min": "00", "tzname": "Europe/Warsaw", "year": "2016"}, "hum": "94", "icon": "rain", "metar": "METAR EPKK 192300Z 32014KT 9999 -RA BKN046 16/15 Q1016", "precipm": "-9999.00", "fog": "0", "wdird": "320", "rain": "1", "pressurem": "1016", "vism": "10.0", "tempi": "60.8", "utcdate": {"mon": "06", "pretty": "11:00 PM GMT on June 19, 2016", "mday": "19", "hour": "23", "min": "00", "tzname": "UTC", "year": "2016"}, "visi": "6.2", "tornado": "0", "hail": "0", "wdire": "NW", "wspdi": "16.1", "windchilli": "-999", "wgusti": "-9999.0", "windchillm": "-999", "wspdm": "25.9", "dewptm": "15.0", "precipi": "-9999.00", "dewpti": "59.0", "thunder": "0", "wgustm": "-9999.0", "conds": "Light Rain", "snow": "0", "heatindexm": "-9999", "heatindexi": "-9999"}, {"tempm": "16.0", "pressurei": "30.01", "date": {"mon": "06", "pretty": "1:30 AM CEST on June 20, 2016", "mday": "20", "hour": "01", "min": "30", "tzname": "Europe/Warsaw", "year": "2016"}, "hum": "94", "icon": "rain", "metar": "METAR EPKK 192330Z 33014KT 9999 -RA BKN050 16/15 Q1016", "precipm": "-9999.00", "fog": "0", "wdird": "330", "rain": "1", "pressurem": "1016", "vism": "10.0", "tempi": "60.8", "utcdate": {"mon": "06", "pretty": "11:30 PM GMT on June 19, 2016", "mday": "19", "hour": "23", "min": "30", "tzname": "UTC", "year": "2016"}, "visi": "6.2", "tornado": "0", "hail": "0", "wdire": "NNW", "wspdi": "16.1", "windchilli": "-999", "wgusti": "-9999.0", "windchillm": "-999", "wspdm": "25.9", "dewptm": "15.0", "precipi": "-9999.00", "dewpti": "59.0", "thunder": "0", "wgustm": "-9999.0", "conds": "Light Rain", "snow": "0", "heatindexm": "-9999", "heatindexi": "-9999"}, {"tempm": "16", "pressurei": "30.05", "date": {"mon": "06", "pretty": "2:00 AM CEST on June 20, 2016", "mday": "20", "hour": "02", "min": "00", "tzname": "Europe/Warsaw", "year": "2016"}, "hum": "87", "icon": "rain", "metar": "AAXX 20001 12566 11665 73106 10163 20145 39888 40174 53004 60131 78096 879// 333 91208 93013", "precipm": "", "fog": "0", "wdird": "310", "rain": "1", "pressurem": "1017", "vism": "15", "tempi": "61", "utcdate": {"mon": "06", "pretty": "12:00 AM GMT on June 20, 2016", "mday": "20", "hour": "00", "min": "00", "tzname": "UTC", "year": "2016"}, "visi": "9", "tornado": "0", "hail": "0", "wdire": "NW", "wspdi": "13.4", "windchilli": "-999", "wgusti": "", "windchillm": "-999", "wspdm": "21.6", "dewptm": "14", "precipi": "", "dewpti": "58", "thunder": "0", "wgustm": "", "conds": "Light Rain Showers", "snow": "0", "heatindexm": "-9999", "heatindexi": "-9999"}, {"tempm": "17.0", "pressurei": "30.04", "date": {"mon": "06", "pretty": "2:00 AM CEST on June 20, 2016", "mday": "20", "hour": "02", "min": "00", "tzname": "Europe/Warsaw", "year": "2016"}, "hum": "88", "icon": "rain", "metar": "METAR EPKK 200000Z 32013KT 9999 -SHRA FEW020CB BKN047 17/15 Q1017", "precipm": "-9999.00", "fog": "0", "wdird": "320", "rain": "1", "pressurem": "1017", "vism": "10.0", "tempi": "62.6", "utcdate": {"mon": "06", "pretty": "12:00 AM GMT on June 20, 2016", "mday": "20", "hour": "00", "min": "00", "tzname": "UTC", "year": "2016"}, "visi": "6.2", "tornado": "0", "hail": "0", "wdire": "NW", "wspdi": "15.0", "windchilli": "-999", "wgusti": "-9999.0", "windchillm": "-999", "wspdm": "24.1", "dewptm": "15.0", "precipi": "-9999.00", "dewpti": "59.0", "thunder": "0", "wgustm": "-9999.0", "conds": "Light Rain Showers", "snow": "0", "heatindexm": "-9999", "heatindexi": "-9999"}, {"tempm": "16.0", "pressurei": "30.04", "date": {"mon": "06", "pretty": "2:30 AM CEST on June 20, 2016", "mday": "20", "hour": "02", "min": "30", "tzname": "Europe/Warsaw", "year": "2016"}, "hum": "94", "icon": "rain", "metar": "METAR EPKK 200030Z 32014KT 8000 -SHRA BKN040CB 16/15 Q1017", "precipm": "-9999.00", "fog": "0", "wdird": "320", "rain": "1", "pressurem": "1017", "vism": "8.0", "tempi": "60.8", "utcdate": {"mon": "06", "pretty": "12:30 AM GMT on June 20, 2016", "mday": "20", "hour": "00", "min": "30", "tzname": "UTC", "year": "2016"}, "visi": "5.0", "tornado": "0", "hail": "0", "wdire": "NW", "wspdi": "16.1", "windchilli": "-999", "wgusti": "-9999.0", "windchillm": "-999", "wspdm": "25.9", "dewptm": "15.0", "precipi": "-9999.00", "dewpti": "59.0", "thunder": "0", "wgustm": "-9999.0", "conds": "Light Rain Showers", "snow": "0", "heatindexm": "-9999", "heatindexi": "-9999"}, {"tempm": "16", "pressurei": "30.04", "date": {"mon": "06", "pretty": "3:00 AM CEST on June 20, 2016", "mday": "20", "hour": "03", "min": "00", "tzname": "Europe/Warsaw", "year": "2016"}, "hum": "88", "icon": "rain", "metar": "AAXX 20011 12566 41670 73206 10162 20147 39885 40171 56001 72588 875// 333 91207 555 57020 90005", "precipm": "", "fog": "0", "wdird": "320", "rain": "1", "pressurem": "1017", "vism": "20", "tempi": "61", "utcdate": {"mon": "06", "pretty": "1:00 AM GMT on June 20, 2016", "mday": "20", "hour": "01", "min": "00", "tzname": "UTC", "year": "2016"}, "visi": "12", "tornado": "0", "hail": "0", "wdire": "NW", "wspdi": "13.4", "windchilli": "-999", "wgusti": "", "windchillm": "-999", "wspdm": "21.6", "dewptm": "15", "precipi": "", "dewpti": "58", "thunder": "0", "wgustm": "", "conds": "Light Rain Showers", "snow": "0", "heatindexm": "-9999", "heatindexi": "-9999"}, {"tempm": "16.0", "pressurei": "30.04", "date": {"mon": "06", "pretty": "3:00 AM CEST on June 20, 2016", "mday": "20", "hour": "03", "min": "00", "tzname": "Europe/Warsaw", "year": "2016"}, "hum": "94", "icon": "mostlycloudy", "metar": "METAR EPKK 200100Z 32012KT 9999 BKN040 16/15 Q1017", "precipm": "-9999.00", "fog": "0", "wdird": "320", "rain": "0", "pressurem": "1017", "vism": "10.0", "tempi": "60.8", "utcdate": {"mon": "06", "pretty": "1:00 AM GMT on June 20, 2016", "mday": "20", "hour": "01", "min": "00", "tzname": "UTC", "year": "2016"}, "visi": "6.2", "tornado": "0", "hail": "0", "wdire": "NW", "wspdi": "13.8", "windchilli": "-999", "wgusti": "-9999.0", "windchillm": "-999", "wspdm": "22.2", "dewptm": "15.0", "precipi": "-9999.00", "dewpti": "59.0", "thunder": "0", "wgustm": "-9999.0", "conds": "Mostly Cloudy", "snow": "0", "heatindexm": "-9999", "heatindexi": "-9999"}, {"tempm": "17.0", "pressurei": "30.04", "date": {"mon": "06", "pretty": "3:30 AM CEST on June 20, 2016", "mday": "20", "hour": "03", "min": "30", "tzname": "Europe/Warsaw", "year": "2016"}, "hum": "88", "icon": "rain", "metar": "METAR EPKK 200130Z 34008KT 300V010 9999 -SHRA BKN040CB 17/15 Q1017", "precipm": "-9999.00", "fog": "0", "wdird": "340", "rain": "1", "pressurem": "1017", "vism": "10.0", "tempi": "62.6", "utcdate": {"mon": "06", "pretty": "1:30 AM GMT on June 20, 2016", "mday": "20", "hour": "01", "min": "30", "tzname": "UTC", "year": "2016"}, "visi": "6.2", "tornado": "0", "hail": "0", "wdire": "NNW", "wspdi": "9.2", "windchilli": "-999", "wgusti": "-9999.0", "windchillm": "-999", "wspdm": "14.8", "dewptm": "15.0", "precipi": "-9999.00", "dewpti": "59.0", "thunder": "0", "wgustm": "-9999.0", "conds": "Light Rain Showers", "snow": "0", "heatindexm": "-9999", "heatindexi": "-9999"}, {"tempm": "16", "pressurei": "30.02", "date": {"mon": "06", "pretty": "4:00 AM CEST on June 20, 2016", "mday": "20", "hour": "04", "min": "00", "tzname": "Europe/Warsaw", "year": "2016"}, "hum": "84", "icon": "rain", "metar": "AAXX 20021 12566 41670 73202 10165 20147 39881 40166 50001 76186 875// 333 91206 555 90005", "precipm": "", "fog": "0", "wdird": "320", "rain": "1", "pressurem": "1017", "vism": "20", "tempi": "62", "utcdate": {"mon": "06", "pretty": "2:00 AM GMT on June 20, 2016", "mday": "20", "hour": "02", "min": "00", "tzname": "UTC", "year": "2016"}, "visi": "12", "tornado": "0", "hail": "0", "wdire": "NW", "wspdi": "4.5", "windchilli": "-999", "wgusti": "", "windchillm": "-999", "wspdm": "7.2", "dewptm": "15", "precipi": "", "dewpti": "58", "thunder": "0", "wgustm": "", "conds": "Light Rain", "snow": "0", "heatindexm": "-9999", "heatindexi": "-9999"}, {"tempm": "17.0", "pressurei": "30.01", "date": {"mon": "06", "pretty": "4:00 AM CEST on June 20, 2016", "mday": "20", "hour": "04", "min": "00", "tzname": "Europe/Warsaw", "year": "2016"}, "hum": "88", "icon": "rain", "metar": "METAR EPKK 200200Z 34004KT 300V040 9999 -RA BKN040 17/15 Q1016", "precipm": "-9999.00", "fog": "0", "wdird": "340", "rain": "1", "pressurem": "1016", "vism": "10.0", "tempi": "62.6", "utcdate": {"mon": "06", "pretty": "2:00 AM GMT on June 20, 2016", "mday": "20", "hour": "02", "min": "00", "tzname": "UTC", "year": "2016"}, "visi": "6.2", "tornado": "0", "hail": "0", "wdire": "NNW", "wspdi": "4.6", "windchilli": "-999", "wgusti": "-9999.0", "windchillm": "-999", "wspdm": "7.4", "dewptm": "15.0", "precipi": "-9999.00", "dewpti": "59.0", "thunder": "0", "wgustm": "-9999.0", "conds": "Light Rain", "snow": "0", "heatindexm": "-9999", "heatindexi": "-9999"}, {"tempm": "17.0", "pressurei": "30.01", "date": {"mon": "06", "pretty": "4:30 AM CEST on June 20, 2016", "mday": "20", "hour": "04", "min": "30", "tzname": "Europe/Warsaw", "year": "2016"}, "hum": "82", "icon": "rain", "metar": "METAR EPKK 200230Z 27003KT 220V320 9999 -RA FEW020 17/14 Q1016", "precipm": "-9999.00", "fog": "0", "wdird": "270", "rain": "1", "pressurem": "1016", "vism": "10.0", "tempi": "62.6", "utcdate": {"mon": "06", "pretty": "2:30 AM GMT on June 20, 2016", "mday": "20", "hour": "02", "min": "30", "tzname": "UTC", "year": "2016"}, "visi": "6.2", "tornado": "0", "hail": "0", "wdire": "West", "wspdi": "3.5", "windchilli": "-999", "wgusti": "-9999.0", "windchillm": "-999", "wspdm": "5.6", "dewptm": "14.0", "precipi": "-9999.00", "dewpti": "57.2", "thunder": "0", "wgustm": "-9999.0", "conds": "Light Rain", "snow": "0", "heatindexm": "-9999", "heatindexi": "-9999"}, {"tempm": "17", "pressurei": "30.03", "date": {"mon": "06", "pretty": "5:00 AM CEST on June 20, 2016", "mday": "20", "hour": "05", "min": "00", "tzname": "Europe/Warsaw", "year": "2016"}, "hum": "82", "icon": "rain", "metar": "AAXX 20031 12566 41570 73602 10166 20144 39882 40167 55006 76186 8557/ 333 91207", "precipm": "", "fog": "0", "wdird": "0", "rain": "1", "pressurem": "1017", "vism": "20", "tempi": "62", "utcdate": {"mon": "06", "pretty": "3:00 AM GMT on June 20, 2016", "mday": "20", "hour": "03", "min": "00", "tzname": "UTC", "year": "2016"}, "visi": "12", "tornado": "0", "hail": "0", "wdire": "North", "wspdi": "4.5", "windchilli": "-999", "wgusti": "", "windchillm": "-999", "wspdm": "7.2", "dewptm": "14", "precipi": "", "dewpti": "58", "thunder": "0", "wgustm": "", "conds": "Light Rain", "snow": "0", "heatindexm": "-9999", "heatindexi": "-9999"}, {"tempm": "17.0", "pressurei": "30.01", "date": {"mon": "06", "pretty": "5:00 AM CEST on June 20, 2016", "mday": "20", "hour": "05", "min": "00", "tzname": "Europe/Warsaw", "year": "2016"}, "hum": "88", "icon": "rain", "metar": "METAR EPKK 200300Z VRB02KT 9999 -RA BKN020 17/15 Q1016", "precipm": "-9999.00", "fog": "0", "wdird": "0", "rain": "1", "pressurem": "1016", "vism": "10.0", "tempi": "62.6", "utcdate": {"mon": "06", "pretty": "3:00 AM GMT on June 20, 2016", "mday": "20", "hour": "03", "min": "00", "tzname": "UTC", "year": "2016"}, "visi": "6.2", "tornado": "0", "hail": "0", "wdire": "Variable", "wspdi": "2.3", "windchilli": "-999", "wgusti": "-9999.0", "windchillm": "-999", "wspdm": "3.7", "dewptm": "15.0", "precipi": "-9999.00", "dewpti": "59.0", "thunder": "0", "wgustm": "-9999.0", "conds": "Light Rain", "snow": "0", "heatindexm": "-9999", "heatindexi": "-9999"}, {"tempm": "17.0", "pressurei": "30.01", "date": {"mon": "06", "pretty": "5:30 AM CEST on June 20, 2016", "mday": "20", "hour": "05", "min": "30", "tzname": "Europe/Warsaw", "year": "2016"}, "hum": "88", "icon": "rain", "metar": "METAR EPKK 200330Z 34005KT 290V030 9999 -RA BKN020 17/15 Q1016", "precipm": "-9999.00", "fog": "0", "wdird": "340", "rain": "1", "pressurem": "1016", "vism": "10.0", "tempi": "62.6", "utcdate": {"mon": "06", "pretty": "3:30 AM GMT on June 20, 2016", "mday": "20", "hour": "03", "min": "30", "tzname": "UTC", "year": "2016"}, "visi": "6.2", "tornado": "0", "hail": "0", "wdire": "NNW", "wspdi": "5.8", "windchilli": "-999", "wgusti": "-9999.0", "windchillm": "-999", "wspdm": "9.3", "dewptm": "15.0", "precipi": "-9999.00", "dewpti": "59.0", "thunder": "0", "wgustm": "-9999.0", "conds": "Light Rain", "snow": "0", "heatindexm": "-9999", "heatindexi": "-9999"}, {"tempm": "17", "pressurei": "30.02", "date": {"mon": "06", "pretty": "6:00 AM CEST on June 20, 2016", "mday": "20", "hour": "06", "min": "00", "tzname": "Europe/Warsaw", "year": "2016"}, "hum": "84", "icon": "rain", "metar": "AAXX 20041 12566 41570 73401 10166 20146 39879 40164 57006 72162 8557/ 333 91202 555 90005", "precipm": "", "fog": "0", "wdird": "340", "rain": "1", "pressurem": "1016", "vism": "20", "tempi": "62", "utcdate": {"mon": "06", "pretty": "4:00 AM GMT on June 20, 2016", "mday": "20", "hour": "04", "min": "00", "tzname": "UTC", "year": "2016"}, "visi": "12", "tornado": "0", "hail": "0", "wdire": "NNW", "wspdi": "2.2", "windchilli": "-999", "wgusti": "", "windchillm": "-999", "wspdm": "3.6", "dewptm": "15", "precipi": "", "dewpti": "58", "thunder": "0", "wgustm": "", "conds": "Light Rain", "snow": "0", "heatindexm": "-9999", "heatindexi": "-9999"}, {"tempm": "17.0", "pressurei": "30.01", "date": {"mon": "06", "pretty": "6:00 AM CEST on June 20, 2016", "mday": "20", "hour": "06", "min": "00", "tzname": "Europe/Warsaw", "year": "2016"}, "hum": "88", "icon": "mostlycloudy", "metar": "METAR EPKK 200400Z 35003KT 280V040 9999 BKN020 17/15 Q1016", "precipm": "-9999.00", "fog": "0", "wdird": "350", "rain": "0", "pressurem": "1016", "vism": "10.0", "tempi": "62.6", "utcdate": {"mon": "06", "pretty": "4:00 AM GMT on June 20, 2016", "mday": "20", "hour": "04", "min": "00", "tzname": "UTC", "year": "2016"}, "visi": "6.2", "tornado": "0", "hail": "0", "wdire": "North", "wspdi": "3.5", "windchilli": "-999", "wgusti": "-9999.0", "windchillm": "-999", "wspdm": "5.6", "dewptm": "15.0", "precipi": "-9999.00", "dewpti": "59.0", "thunder": "0", "wgustm": "-9999.0", "conds": "Mostly Cloudy", "snow": "0", "heatindexm": "-9999", "heatindexi": "-9999"}, {"tempm": "17.0", "pressurei": "30.04", "date": {"mon": "06", "pretty": "6:30 AM CEST on June 20, 2016", "mday": "20", "hour": "06", "min": "30", "tzname": "Europe/Warsaw", "year": "2016"}, "hum": "88", "icon": "mostlycloudy", "metar": "METAR EPKK 200430Z VRB02KT 9999 BKN015 17/15 Q1017", "precipm": "-9999.00", "fog": "0", "wdird": "0", "rain": "0", "pressurem": "1017", "vism": "10.0", "tempi": "62.6", "utcdate": {"mon": "06", "pretty": "4:30 AM GMT on June 20, 2016", "mday": "20", "hour": "04", "min": "30", "tzname": "UTC", "year": "2016"}, "visi": "6.2", "tornado": "0", "hail": "0", "wdire": "Variable", "wspdi": "2.3", "windchilli": "-999", "wgusti": "-9999.0", "windchillm": "-999", "wspdm": "3.7", "dewptm": "15.0", "precipi": "-9999.00", "dewpti": "59.0", "thunder": "0", "wgustm": "-9999.0", "conds": "Mostly Cloudy", "snow": "0", "heatindexm": "-9999", "heatindexi": "-9999"}, {"tempm": "17", "pressurei": "30.04", "date": {"mon": "06", "pretty": "7:00 AM CEST on June 20, 2016", "mday": "20", "hour": "07", "min": "00", "tzname": "Europe/Warsaw", "year": "2016"}, "hum": "83", "icon": "mostlycloudy", "metar": "AAXX 20051 12566 42580 73301 10167 20145 39887 40172 53006 875// 333 91202 555 90005", "precipm": "", "fog": "0", "wdird": "330", "rain": "0", "pressurem": "1017", "vism": "30", "tempi": "62", "utcdate": {"mon": "06", "pretty": "5:00 AM GMT on June 20, 2016", "mday": "20", "hour": "05", "min": "00", "tzname": "UTC", "year": "2016"}, "visi": "19", "tornado": "0", "hail": "0", "wdire": "NNW", "wspdi": "2.2", "windchilli": "-999", "wgusti": "", "windchillm": "-999", "wspdm": "3.6", "dewptm": "14", "precipi": "", "dewpti": "58", "thunder": "0", "wgustm": "", "conds": "Mostly Cloudy", "snow": "0", "heatindexm": "-9999", "heatindexi": "-9999"}, {"tempm": "17.0", "pressurei": "30.04", "date": {"mon": "06", "pretty": "7:00 AM CEST on June 20, 2016", "mday": "20", "hour": "07", "min": "00", "tzname": "Europe/Warsaw", "year": "2016"}, "hum": "88", "icon": "mostlycloudy", "metar": "METAR EPKK 200500Z VRB02KT 9999 BKN015 17/15 Q1017", "precipm": "-9999.00", "fog": "0", "wdird": "0", "rain": "0", "pressurem": "1017", "vism": "10.0", "tempi": "62.6", "utcdate": {"mon": "06", "pretty": "5:00 AM GMT on June 20, 2016", "mday": "20", "hour": "05", "min": "00", "tzname": "UTC", "year": "2016"}, "visi": "6.2", "tornado": "0", "hail": "0", "wdire": "Variable", "wspdi": "2.3", "windchilli": "-999", "wgusti": "-9999.0", "windchillm": "-999", "wspdm": "3.7", "dewptm": "15.0", "precipi": "-9999.00", "dewpti": "59.0", "thunder": "0", "wgustm": "-9999.0", "conds": "Mostly Cloudy", "snow": "0", "heatindexm": "-9999", "heatindexi": "-9999"}, {"tempm": "16.0", "pressurei": "30.04", "date": {"mon": "06", "pretty": "7:30 AM CEST on June 20, 2016", "mday": "20", "hour": "07", "min": "30", "tzname": "Europe/Warsaw", "year": "2016"}, "hum": "94", "icon": "mostlycloudy", "metar": "METAR EPKK 200530Z VRB02KT 9999 BKN013 16/15 Q1017", "precipm": "-9999.00", "fog": "0", "wdird": "0", "rain": "0", "pressurem": "1017", "vism": "10.0", "tempi": "60.8", "utcdate": {"mon": "06", "pretty": "5:30 AM GMT on June 20, 2016", "mday": "20", "hour": "05", "min": "30", "tzname": "UTC", "year": "2016"}, "visi": "6.2", "tornado": "0", "hail": "0", "wdire": "Variable", "wspdi": "2.3", "windchilli": "-999", "wgusti": "-9999.0", "windchillm": "-999", "wspdm": "3.7", "dewptm": "15.0", "precipi": "-9999.00", "dewpti": "59.0", "thunder": "0", "wgustm": "-9999.0", "conds": "Mostly Cloudy", "snow": "0", "heatindexm": "-9999", "heatindexi": "-9999"}, {"tempm": "16", "pressurei": "30.05", "date": {"mon": "06", "pretty": "8:00 AM CEST on June 20, 2016", "mday": "20", "hour": "08", "min": "00", "tzname": "Europe/Warsaw", "year": "2016"}, "hum": "89", "icon": "rain", "metar": "AAXX 20061 12566 11470 82702 10164 20153 39888 40174 53006 60172 78086 879// 333 10218 20158 32015 70171 91207 93004", "precipm": "", "fog": "0", "wdird": "270", "rain": "1", "pressurem": "1017", "vism": "20", "tempi": "62", "utcdate": {"mon": "06", "pretty": "6:00 AM GMT on June 20, 2016", "mday": "20", "hour": "06", "min": "00", "tzname": "UTC", "year": "2016"}, "visi": "12", "tornado": "0", "hail": "0", "wdire": "West", "wspdi": "4.5", "windchilli": "-999", "wgusti": "", "windchillm": "-999", "wspdm": "7.2", "dewptm": "15", "precipi": "", "dewpti": "60", "thunder": "0", "wgustm": "", "conds": "Light Rain Showers", "snow": "0", "heatindexm": "-9999", "heatindexi": "-9999"}, {"tempm": "16.0", "pressurei": "30.04", "date": {"mon": "06", "pretty": "8:00 AM CEST on June 20, 2016", "mday": "20", "hour": "08", "min": "00", "tzname": "Europe/Warsaw", "year": "2016"}, "hum": "94", "icon": "rain", "metar": "METAR EPKK 200600Z 29003KT 9999 -SHRA FEW010TCU BKN014 16/15 Q1017", "precipm": "-9999.00", "fog": "0", "wdird": "290", "rain": "1", "pressurem": "1017", "vism": "10.0", "tempi": "60.8", "utcdate": {"mon": "06", "pretty": "6:00 AM GMT on June 20, 2016", "mday": "20", "hour": "06", "min": "00", "tzname": "UTC", "year": "2016"}, "visi": "6.2", "tornado": "0", "hail": "0", "wdire": "WNW", "wspdi": "3.5", "windchilli": "-999", "wgusti": "-9999.0", "windchillm": "-999", "wspdm": "5.6", "dewptm": "15.0", "precipi": "-9999.00", "dewpti": "59.0", "thunder": "0", "wgustm": "-9999.0", "conds": "Light Rain Showers", "snow": "0", "heatindexm": "-9999", "heatindexi": "-9999"}, {"tempm": "17.0", "pressurei": "30.04", "date": {"mon": "06", "pretty": "8:30 AM CEST on June 20, 2016", "mday": "20", "hour": "08", "min": "30", "tzname": "Europe/Warsaw", "year": "2016"}, "hum": "88", "icon": "mostlycloudy", "metar": "METAR EPKK 200630Z VRB02KT 9999 FEW006 BKN012 17/15 Q1017", "precipm": "-9999.00", "fog": "0", "wdird": "0", "rain": "0", "pressurem": "1017", "vism": "10.0", "tempi": "62.6", "utcdate": {"mon": "06", "pretty": "6:30 AM GMT on June 20, 2016", "mday": "20", "hour": "06", "min": "30", "tzname": "UTC", "year": "2016"}, "visi": "6.2", "tornado": "0", "hail": "0", "wdire": "Variable", "wspdi": "2.3", "windchilli": "-999", "wgusti": "-9999.0", "windchillm": "-999", "wspdm": "3.7", "dewptm": "15.0", "precipi": "-9999.00", "dewpti": "59.0", "thunder": "0", "wgustm": "-9999.0", "conds": "Mostly Cloudy", "snow": "0", "heatindexm": "-9999", "heatindexi": "-9999"}, {"tempm": "17", "pressurei": "30.05", "date": {"mon": "06", "pretty": "9:00 AM CEST on June 20, 2016", "mday": "20", "hour": "09", "min": "00", "tzname": "Europe/Warsaw", "year": "2016"}, "hum": "85", "icon": "rain", "metar": "AAXX 20071 12566 41280 82702 10170 20153 39890 40175 51011 72522 875// 333 87613 91202 555 57013 90005", "precipm": "", "fog": "0", "wdird": "270", "rain": "1", "pressurem": "1018", "vism": "30", "tempi": "63", "utcdate": {"mon": "06", "pretty": "7:00 AM GMT on June 20, 2016", "mday": "20", "hour": "07", "min": "00", "tzname": "UTC", "year": "2016"}, "visi": "19", "tornado": "0", "hail": "0", "wdire": "West", "wspdi": "4.5", "windchilli": "-999", "wgusti": "", "windchillm": "-999", "wspdm": "7.2", "dewptm": "15", "precipi": "", "dewpti": "60", "thunder": "0", "wgustm": "", "conds": "Light Rain Showers", "snow": "0", "heatindexm": "-9999", "heatindexi": "-9999"}, {"tempm": "17.0", "pressurei": "30.04", "date": {"mon": "06", "pretty": "9:00 AM CEST on June 20, 2016", "mday": "20", "hour": "09", "min": "00", "tzname": "Europe/Warsaw", "year": "2016"}, "hum": "88", "icon": "mostlycloudy", "metar": "METAR EPKK 200700Z 28003KT 9999 FEW006 BKN013 17/15 Q1017", "precipm": "-9999.00", "fog": "0", "wdird": "280", "rain": "0", "pressurem": "1017", "vism": "10.0", "tempi": "62.6", "utcdate": {"mon": "06", "pretty": "7:00 AM GMT on June 20, 2016", "mday": "20", "hour": "07", "min": "00", "tzname": "UTC", "year": "2016"}, "visi": "6.2", "tornado": "0", "hail": "0", "wdire": "West", "wspdi": "3.5", "windchilli": "-999", "wgusti": "-9999.0", "windchillm": "-999", "wspdm": "5.6", "dewptm": "15.0", "precipi": "-9999.00", "dewpti": "59.0", "thunder": "0", "wgustm": "-9999.0", "conds": "Mostly Cloudy", "snow": "0", "heatindexm": "-9999", "heatindexi": "-9999"}, {"tempm": "17.0", "pressurei": "30.04", "date": {"mon": "06", "pretty": "9:30 AM CEST on June 20, 2016", "mday": "20", "hour": "09", "min": "30", "tzname": "Europe/Warsaw", "year": "2016"}, "hum": "88", "icon": "mostlycloudy", "metar": "METAR EPKK 200730Z 25005KT 9999 FEW007 BKN012 17/15 Q1017", "precipm": "-9999.00", "fog": "0", "wdird": "250", "rain": "0", "pressurem": "1017", "vism": "10.0", "tempi": "62.6", "utcdate": {"mon": "06", "pretty": "7:30 AM GMT on June 20, 2016", "mday": "20", "hour": "07", "min": "30", "tzname": "UTC", "year": "2016"}, "visi": "6.2", "tornado": "0", "hail": "0", "wdire": "WSW", "wspdi": "5.8", "windchilli": "-999", "wgusti": "-9999.0", "windchillm": "-999", "wspdm": "9.3", "dewptm": "15.0", "precipi": "-9999.00", "dewpti": "59.0", "thunder": "0", "wgustm": "-9999.0", "conds": "Mostly Cloudy", "snow": "0", "heatindexm": "-9999", "heatindexi": "-9999"}, {"tempm": "18", "pressurei": "30.04", "date": {"mon": "06", "pretty": "10:00 AM CEST on June 20, 2016", "mday": "20", "hour": "10", "min": "00", "tzname": "Europe/Warsaw", "year": "2016"}, "hum": "80", "icon": "mostlycloudy", "metar": "AAXX 20081 12566 42382 72803 10179 20152 39889 40173 50002 875// 333 82707 87614 91203 555 90005", "precipm": "", "fog": "0", "wdird": "280", "rain": "0", "pressurem": "1017", "vism": "40", "tempi": "64", "utcdate": {"mon": "06", "pretty": "8:00 AM GMT on June 20, 2016", "mday": "20", "hour": "08", "min": "00", "tzname": "UTC", "year": "2016"}, "visi": "25", "tornado": "0", "hail": "0", "wdire": "West", "wspdi": "6.7", "windchilli": "-999", "wgusti": "", "windchillm": "-999", "wspdm": "10.8", "dewptm": "15", "precipi": "", "dewpti": "59", "thunder": "0", "wgustm": "", "conds": "Mostly Cloudy", "snow": "0", "heatindexm": "-9999", "heatindexi": "-9999"}, {"tempm": "18.0", "pressurei": "30.04", "date": {"mon": "06", "pretty": "10:00 AM CEST on June 20, 2016", "mday": "20", "hour": "10", "min": "00", "tzname": "Europe/Warsaw", "year": "2016"}, "hum": "88", "icon": "mostlycloudy", "metar": "METAR EPKK 200800Z 29005KT 250V320 9999 FEW007 BKN014 18/16 Q1017", "precipm": "-9999.00", "fog": "0", "wdird": "290", "rain": "0", "pressurem": "1017", "vism": "10.0", "tempi": "64.4", "utcdate": {"mon": "06", "pretty": "8:00 AM GMT on June 20, 2016", "mday": "20", "hour": "08", "min": "00", "tzname": "UTC", "year": "2016"}, "visi": "6.2", "tornado": "0", "hail": "0", "wdire": "WNW", "wspdi": "5.8", "windchilli": "-999", "wgusti": "-9999.0", "windchillm": "-999", "wspdm": "9.3", "dewptm": "16.0", "precipi": "-9999.00", "dewpti": "60.8", "thunder": "0", "wgustm": "-9999.0", "conds": "Mostly Cloudy", "snow": "0", "heatindexm": "-9999", "heatindexi": "-9999"}, {"tempm": "18.0", "pressurei": "30.06", "date": {"mon": "06", "pretty": "10:30 AM CEST on June 20, 2016", "mday": "20", "hour": "10", "min": "30", "tzname": "Europe/Warsaw", "year": "2016"}, "hum": "83", "icon": "mostlycloudy", "metar": "METAR EPKK 200830Z 28003KT 240V340 9999 FEW009 BKN015 18/15 Q1018", "precipm": "-9999.00", "fog": "0", "wdird": "280", "rain": "0", "pressurem": "1018", "vism": "10.0", "tempi": "64.4", "utcdate": {"mon": "06", "pretty": "8:30 AM GMT on June 20, 2016", "mday": "20", "hour": "08", "min": "30", "tzname": "UTC", "year": "2016"}, "visi": "6.2", "tornado": "0", "hail": "0", "wdire": "West", "wspdi": "3.5", "windchilli": "-999", "wgusti": "-9999.0", "windchillm": "-999", "wspdm": "5.6", "dewptm": "15.0", "precipi": "-9999.00", "dewpti": "59.0", "thunder": "0", "wgustm": "-9999.0", "conds": "Mostly Cloudy", "snow": "0", "heatindexm": "-9999", "heatindexi": "-9999"}, {"tempm": "18", "pressurei": "30.06", "date": {"mon": "06", "pretty": "11:00 AM CEST on June 20, 2016", "mday": "20", "hour": "11", "min": "00", "tzname": "Europe/Warsaw", "year": "2016"}, "hum": "78", "icon": "partlycloudy", "metar": "AAXX 20091 12566 41382 72702 10184 20155 39896 40180 53008 70282 875// 333 82709 87615 91203", "precipm": "", "fog": "0", "wdird": "270", "rain": "0", "pressurem": "1018", "vism": "40", "tempi": "65", "utcdate": {"mon": "06", "pretty": "9:00 AM GMT on June 20, 2016", "mday": "20", "hour": "09", "min": "00", "tzname": "UTC", "year": "2016"}, "visi": "25", "tornado": "0", "hail": "0", "wdire": "West", "wspdi": "4.5", "windchilli": "-999", "wgusti": "", "windchillm": "-999", "wspdm": "7.2", "dewptm": "16", "precipi": "", "dewpti": "60", "thunder": "0", "wgustm": "", "conds": "Partly Cloudy", "snow": "0", "heatindexm": "-9999", "heatindexi": "-9999"}, {"tempm": "18.0", "pressurei": "30.06", "date": {"mon": "06", "pretty": "11:00 AM CEST on June 20, 2016", "mday": "20", "hour": "11", "min": "00", "tzname": "Europe/Warsaw", "year": "2016"}, "hum": "83", "icon": "mostlycloudy", "metar": "METAR EPKK 200900Z 29003KT 250V360 9999 FEW009 BKN015 18/15 Q1018", "precipm": "-9999.00", "fog": "0", "wdird": "290", "rain": "0", "pressurem": "1018", "vism": "10.0", "tempi": "64.4", "utcdate": {"mon": "06", "pretty": "9:00 AM GMT on June 20, 2016", "mday": "20", "hour": "09", "min": "00", "tzname": "UTC", "year": "2016"}, "visi": "6.2", "tornado": "0", "hail": "0", "wdire": "WNW", "wspdi": "3.5", "windchilli": "-999", "wgusti": "-9999.0", "windchillm": "-999", "wspdm": "5.6", "dewptm": "15.0", "precipi": "-9999.00", "dewpti": "59.0", "thunder": "0", "wgustm": "-9999.0", "conds": "Mostly Cloudy", "snow": "0", "heatindexm": "-9999", "heatindexi": "-9999"}, {"tempm": "19.0", "pressurei": "30.06", "date": {"mon": "06", "pretty": "11:30 AM CEST on June 20, 2016", "mday": "20", "hour": "11", "min": "30", "tzname": "Europe/Warsaw", "year": "2016"}, "hum": "78", "icon": "mostlycloudy", "metar": "METAR EPKK 200930Z VRB01KT 9999 FEW012 BKN017 19/15 Q1018", "precipm": "-9999.00", "fog": "0", "wdird": "0", "rain": "0", "pressurem": "1018", "vism": "10.0", "tempi": "66.2", "utcdate": {"mon": "06", "pretty": "9:30 AM GMT on June 20, 2016", "mday": "20", "hour": "09", "min": "30", "tzname": "UTC", "year": "2016"}, "visi": "6.2", "tornado": "0", "hail": "0", "wdire": "Variable", "wspdi": "1.2", "windchilli": "-999", "wgusti": "-9999.0", "windchillm": "-999", "wspdm": "1.9", "dewptm": "15.0", "precipi": "-9999.00", "dewpti": "59.0", "thunder": "0", "wgustm": "-9999.0", "conds": "Mostly Cloudy", "snow": "0", "heatindexm": "-9999", "heatindexi": "-9999"}, {"tempm": "18", "pressurei": "30.08", "date": {"mon": "06", "pretty": "12:00 PM CEST on June 20, 2016", "mday": "20", "hour": "12", "min": "00", "tzname": "Europe/Warsaw", "year": "2016"}, "hum": "78", "icon": "mostlycloudy", "metar": "AAXX 20101 12566 42482 72502 10184 20155 39900 40184 53010 875// 333 87615 91202 555 90005", "precipm": "", "fog": "0", "wdird": "250", "rain": "0", "pressurem": "1018", "vism": "40", "tempi": "65", "utcdate": {"mon": "06", "pretty": "10:00 AM GMT on June 20, 2016", "mday": "20", "hour": "10", "min": "00", "tzname": "UTC", "year": "2016"}, "visi": "25", "tornado": "0", "hail": "0", "wdire": "WSW", "wspdi": "4.5", "windchilli": "-999", "wgusti": "", "windchillm": "-999", "wspdm": "7.2", "dewptm": "16", "precipi": "", "dewpti": "60", "thunder": "0", "wgustm": "", "conds": "Mostly Cloudy", "snow": "0", "heatindexm": "-9999", "heatindexi": "-9999"}, {"tempm": "18.0", "pressurei": "30.06", "date": {"mon": "06", "pretty": "12:00 PM CEST on June 20, 2016", "mday": "20", "hour": "12", "min": "00", "tzname": "Europe/Warsaw", "year": "2016"}, "hum": "88", "icon": "mostlycloudy", "metar": "METAR EPKK 201000Z 24004KT 9999 BKN015 18/16 Q1018", "precipm": "-9999.00", "fog": "0", "wdird": "240", "rain": "0", "pressurem": "1018", "vism": "10.0", "tempi": "64.4", "utcdate": {"mon": "06", "pretty": "10:00 AM GMT on June 20, 2016", "mday": "20", "hour": "10", "min": "00", "tzname": "UTC", "year": "2016"}, "visi": "6.2", "tornado": "0", "hail": "0", "wdire": "WSW", "wspdi": "4.6", "windchilli": "-999", "wgusti": "-9999.0", "windchillm": "-999", "wspdm": "7.4", "dewptm": "16.0", "precipi": "-9999.00", "dewpti": "60.8", "thunder": "0", "wgustm": "-9999.0", "conds": "Mostly Cloudy", "snow": "0", "heatindexm": "-9999", "heatindexi": "-9999"}, {"tempm": "19.0", "pressurei": "30.06", "date": {"mon": "06", "pretty": "12:30 PM CEST on June 20, 2016", "mday": "20", "hour": "12", "min": "30", "tzname": "Europe/Warsaw", "year": "2016"}, "hum": "78", "icon": "mostlycloudy", "metar": "METAR EPKK 201030Z 26005KT 230V290 9999 BKN015 19/15 Q1018", "precipm": "-9999.00", "fog": "0", "wdird": "260", "rain": "0", "pressurem": "1018", "vism": "10.0", "tempi": "66.2", "utcdate": {"mon": "06", "pretty": "10:30 AM GMT on June 20, 2016", "mday": "20", "hour": "10", "min": "30", "tzname": "UTC", "year": "2016"}, "visi": "6.2", "tornado": "0", "hail": "0", "wdire": "West", "wspdi": "5.8", "windchilli": "-999", "wgusti": "-9999.0", "windchillm": "-999", "wspdm": "9.3", "dewptm": "15.0", "precipi": "-9999.00", "dewpti": "59.0", "thunder": "0", "wgustm": "-9999.0", "conds": "Mostly Cloudy", "snow": "0", "heatindexm": "-9999", "heatindexi": "-9999"}, {"tempm": "20", "pressurei": "30.06", "date": {"mon": "06", "pretty": "1:00 PM CEST on June 20, 2016", "mday": "20", "hour": "13", "min": "00", "tzname": "Europe/Warsaw", "year": "2016"}, "hum": "74", "icon": "mostlycloudy", "metar": "AAXX 20111 12566 42482 72704 10200 20164 39895 40177 50006 8523/ 333 85815 91204 555 90005", "precipm": "", "fog": "0", "wdird": "270", "rain": "0", "pressurem": "1018", "vism": "40", "tempi": "68", "utcdate": {"mon": "06", "pretty": "11:00 AM GMT on June 20, 2016", "mday": "20", "hour": "11", "min": "00", "tzname": "UTC", "year": "2016"}, "visi": "25", "tornado": "0", "hail": "0", "wdire": "West", "wspdi": "8.9", "windchilli": "-999", "wgusti": "", "windchillm": "-999", "wspdm": "14.4", "dewptm": "16", "precipi": "", "dewpti": "62", "thunder": "0", "wgustm": "", "conds": "Mostly Cloudy", "snow": "0", "heatindexm": "-9999", "heatindexi": "-9999"}, {"tempm": "19.0", "pressurei": "30.06", "date": {"mon": "06", "pretty": "1:00 PM CEST on June 20, 2016", "mday": "20", "hour": "13", "min": "00", "tzname": "Europe/Warsaw", "year": "2016"}, "hum": "83", "icon": "mostlycloudy", "metar": "METAR EPKK 201100Z 29007KT 250V320 9999 BKN015 19/16 Q1018", "precipm": "-9999.00", "fog": "0", "wdird": "290", "rain": "0", "pressurem": "1018", "vism": "10.0", "tempi": "66.2", "utcdate": {"mon": "06", "pretty": "11:00 AM GMT on June 20, 2016", "mday": "20", "hour": "11", "min": "00", "tzname": "UTC", "year": "2016"}, "visi": "6.2", "tornado": "0", "hail": "0", "wdire": "WNW", "wspdi": "8.1", "windchilli": "-999", "wgusti": "-9999.0", "windchillm": "-999", "wspdm": "13.0", "dewptm": "16.0", "precipi": "-9999.00", "dewpti": "60.8", "thunder": "0", "wgustm": "-9999.0", "conds": "Mostly Cloudy", "snow": "0", "heatindexm": "-9999", "heatindexi": "-9999"}, {"tempm": "20.0", "pressurei": "30.06", "date": {"mon": "06", "pretty": "1:30 PM CEST on June 20, 2016", "mday": "20", "hour": "13", "min": "30", "tzname": "Europe/Warsaw", "year": "2016"}, "hum": "78", "icon": "mostlycloudy", "metar": "METAR EPKK 201130Z 29007KT 9999 BKN016 20/16 Q1018", "precipm": "-9999.00", "fog": "0", "wdird": "290", "rain": "0", "pressurem": "1018", "vism": "10.0", "tempi": "68.0", "utcdate": {"mon": "06", "pretty": "11:30 AM GMT on June 20, 2016", "mday": "20", "hour": "11", "min": "30", "tzname": "UTC", "year": "2016"}, "visi": "6.2", "tornado": "0", "hail": "0", "wdire": "WNW", "wspdi": "8.1", "windchilli": "-999", "wgusti": "-9999.0", "windchillm": "-999", "wspdm": "13.0", "dewptm": "16.0", "precipi": "-9999.00", "dewpti": "60.8", "thunder": "0", "wgustm": "-9999.0", "conds": "Mostly Cloudy", "snow": "0", "heatindexm": "-9999", "heatindexi": "-9999"}, {"tempm": "20", "pressurei": "30.06", "date": {"mon": "06", "pretty": "2:00 PM CEST on June 20, 2016", "mday": "20", "hour": "14", "min": "00", "tzname": "Europe/Warsaw", "year": "2016"}, "hum": "68", "icon": "partlycloudy", "metar": "AAXX 20121 12566 11480 62703 10204 20160 39897 40179 52001 69901 70182 85230 333 91204 93097", "precipm": "", "fog": "0", "wdird": "270", "rain": "0", "pressurem": "1018", "vism": "30", "tempi": "69", "utcdate": {"mon": "06", "pretty": "12:00 PM GMT on June 20, 2016", "mday": "20", "hour": "12", "min": "00", "tzname": "UTC", "year": "2016"}, "visi": "19", "tornado": "0", "hail": "0", "wdire": "West", "wspdi": "6.7", "windchilli": "-999", "wgusti": "", "windchillm": "-999", "wspdm": "10.8", "dewptm": "16", "precipi": "", "dewpti": "61", "thunder": "0", "wgustm": "", "conds": "Partly Cloudy", "snow": "0", "heatindexm": "-9999", "heatindexi": "-9999"}, {"tempm": "20.0", "pressurei": "30.06", "date": {"mon": "06", "pretty": "2:00 PM CEST on June 20, 2016", "mday": "20", "hour": "14", "min": "00", "tzname": "Europe/Warsaw", "year": "2016"}, "hum": "78", "icon": "mostlycloudy", "metar": "METAR EPKK 201200Z 29006KT 250V350 9999 BKN017 20/16 Q1018", "precipm": "-9999.00", "fog": "0", "wdird": "290", "rain": "0", "pressurem": "1018", "vism": "10.0", "tempi": "68.0", "utcdate": {"mon": "06", "pretty": "12:00 PM GMT on June 20, 2016", "mday": "20", "hour": "12", "min": "00", "tzname": "UTC", "year": "2016"}, "visi": "6.2", "tornado": "0", "hail": "0", "wdire": "WNW", "wspdi": "6.9", "windchilli": "-999", "wgusti": "-9999.0", "windchillm": "-999", "wspdm": "11.1", "dewptm": "16.0", "precipi": "-9999.00", "dewpti": "60.8", "thunder": "0", "wgustm": "-9999.0", "conds": "Mostly Cloudy", "snow": "0", "heatindexm": "-9999", "heatindexi": "-9999"}, {"tempm": "21.0", "pressurei": "30.06", "date": {"mon": "06", "pretty": "2:30 PM CEST on June 20, 2016", "mday": "20", "hour": "14", "min": "30", "tzname": "Europe/Warsaw", "year": "2016"}, "hum": "73", "icon": "mostlycloudy", "metar": "METAR EPKK 201230Z 31006KT 270V360 9999 FEW015 BKN023 21/16 Q1018", "precipm": "-9999.00", "fog": "0", "wdird": "310", "rain": "0", "pressurem": "1018", "vism": "10.0", "tempi": "69.8", "utcdate": {"mon": "06", "pretty": "12:30 PM GMT on June 20, 2016", "mday": "20", "hour": "12", "min": "30", "tzname": "UTC", "year": "2016"}, "visi": "6.2", "tornado": "0", "hail": "0", "wdire": "NW", "wspdi": "6.9", "windchilli": "-999", "wgusti": "-9999.0", "windchillm": "-999", "wspdm": "11.1", "dewptm": "16.0", "precipi": "-9999.00", "dewpti": "60.8", "thunder": "0", "wgustm": "-9999.0", "conds": "Mostly Cloudy", "snow": "0", "heatindexm": "-9999", "heatindexi": "-9999"}, {"tempm": "21", "pressurei": "30.06", "date": {"mon": "06", "pretty": "3:00 PM CEST on June 20, 2016", "mday": "20", "hour": "15", "min": "00", "tzname": "Europe/Warsaw", "year": "2016"}, "hum": "64", "icon": "mostlycloudy", "metar": "AAXX 20131 12566 42480 72704 10207 20153 39895 40177 56005 85932 333 91204 555 57057 90005", "precipm": "", "fog": "0", "wdird": "270", "rain": "0", "pressurem": "1018", "vism": "30", "tempi": "69", "utcdate": {"mon": "06", "pretty": "1:00 PM GMT on June 20, 2016", "mday": "20", "hour": "13", "min": "00", "tzname": "UTC", "year": "2016"}, "visi": "19", "tornado": "0", "hail": "0", "wdire": "West", "wspdi": "8.9", "windchilli": "-999", "wgusti": "", "windchillm": "-999", "wspdm": "14.4", "dewptm": "15", "precipi": "", "dewpti": "60", "thunder": "0", "wgustm": "", "conds": "Mostly Cloudy", "snow": "0", "heatindexm": "-9999", "heatindexi": "-9999"}, {"tempm": "21.0", "pressurei": "30.06", "date": {"mon": "06", "pretty": "3:00 PM CEST on June 20, 2016", "mday": "20", "hour": "15", "min": "00", "tzname": "Europe/Warsaw", "year": "2016"}, "hum": "68", "icon": "mostlycloudy", "metar": "METAR EPKK 201300Z 29007KT 270V330 9999 FEW017CB BKN023 21/15 Q1018", "precipm": "-9999.00", "fog": "0", "wdird": "290", "rain": "0", "pressurem": "1018", "vism": "10.0", "tempi": "69.8", "utcdate": {"mon": "06", "pretty": "1:00 PM GMT on June 20, 2016", "mday": "20", "hour": "13", "min": "00", "tzname": "UTC", "year": "2016"}, "visi": "6.2", "tornado": "0", "hail": "0", "wdire": "WNW", "wspdi": "8.1", "windchilli": "-999", "wgusti": "-9999.0", "windchillm": "-999", "wspdm": "13.0", "dewptm": "15.0", "precipi": "-9999.00", "dewpti": "59.0", "thunder": "0", "wgustm": "-9999.0", "conds": "Mostly Cloudy", "snow": "0", "heatindexm": "-9999", "heatindexi": "-9999"}, {"tempm": "20.0", "pressurei": "30.06", "date": {"mon": "06", "pretty": "3:30 PM CEST on June 20, 2016", "mday": "20", "hour": "15", "min": "30", "tzname": "Europe/Warsaw", "year": "2016"}, "hum": "78", "icon": "partlycloudy", "metar": "METAR EPKK 201330Z 30009KT 9999 FEW018CB SCT023 20/16 Q1018", "precipm": "-9999.00", "fog": "0", "wdird": "300", "rain": "0", "pressurem": "1018", "vism": "10.0", "tempi": "68.0", "utcdate": {"mon": "06", "pretty": "1:30 PM GMT on June 20, 2016", "mday": "20", "hour": "13", "min": "30", "tzname": "UTC", "year": "2016"}, "visi": "6.2", "tornado": "0", "hail": "0", "wdire": "WNW", "wspdi": "10.4", "windchilli": "-999", "wgusti": "-9999.0", "windchillm": "-999", "wspdm": "16.7", "dewptm": "16.0", "precipi": "-9999.00", "dewpti": "60.8", "thunder": "0", "wgustm": "-9999.0", "conds": "Scattered Clouds", "snow": "0", "heatindexm": "-9999", "heatindexi": "-9999"}, {"tempm": "20", "pressurei": "30.07", "date": {"mon": "06", "pretty": "4:00 PM CEST on June 20, 2016", "mday": "20", "hour": "16", "min": "00", "tzname": "Europe/Warsaw", "year": "2016"}, "hum": "71", "icon": "tstorms", "metar": "AAXX 20141 12566 41570 72904 10203 20165 39899 40181 52004 71782 84932 333 91206 555 90005", "precipm": "", "fog": "0", "wdird": "290", "rain": "0", "pressurem": "1018", "vism": "20", "tempi": "69", "utcdate": {"mon": "06", "pretty": "2:00 PM GMT on June 20, 2016", "mday": "20", "hour": "14", "min": "00", "tzname": "UTC", "year": "2016"}, "visi": "12", "tornado": "0", "hail": "0", "wdire": "WNW", "wspdi": "8.9", "windchilli": "-999", "wgusti": "", "windchillm": "-999", "wspdm": "14.4", "dewptm": "16", "precipi": "", "dewpti": "62", "thunder": "1", "wgustm": "", "conds": "Thunderstorm", "snow": "0", "heatindexm": "-9999", "heatindexi": "-9999"}, {"tempm": "20.0", "pressurei": "30.06", "date": {"mon": "06", "pretty": "4:00 PM CEST on June 20, 2016", "mday": "20", "hour": "16", "min": "00", "tzname": "Europe/Warsaw", "year": "2016"}, "hum": "78", "icon": "partlycloudy", "metar": "METAR EPKK 201400Z 31007KT 280V340 9999 VCTS FEW020CB SCT033 20/16 Q1018", "precipm": "-9999.00", "fog": "0", "wdird": "310", "rain": "0", "pressurem": "1018", "vism": "10.0", "tempi": "68.0", "utcdate": {"mon": "06", "pretty": "2:00 PM GMT on June 20, 2016", "mday": "20", "hour": "14", "min": "00", "tzname": "UTC", "year": "2016"}, "visi": "6.2", "tornado": "0", "hail": "0", "wdire": "NW", "wspdi": "8.1", "windchilli": "-999", "wgusti": "-9999.0", "windchillm": "-999", "wspdm": "13.0", "dewptm": "16.0", "precipi": "-9999.00", "dewpti": "60.8", "thunder": "1", "wgustm": "-9999.0", "conds": "Scattered Clouds", "snow": "0", "heatindexm": "-9999", "heatindexi": "-9999"}, {"tempm": "21.0", "pressurei": "30.06", "date": {"mon": "06", "pretty": "4:30 PM CEST on June 20, 2016", "mday": "20", "hour": "16", "min": "30", "tzname": "Europe/Warsaw", "year": "2016"}, "hum": "73", "icon": "mostlycloudy", "metar": "METAR EPKK 201430Z 29011KT 9999 FEW020CB BKN033 21/16 Q1018 RETS", "precipm": "-9999.00", "fog": "0", "wdird": "290", "rain": "0", "pressurem": "1018", "vism": "10.0", "tempi": "69.8", "utcdate": {"mon": "06", "pretty": "2:30 PM GMT on June 20, 2016", "mday": "20", "hour": "14", "min": "30", "tzname": "UTC", "year": "2016"}, "visi": "6.2", "tornado": "0", "hail": "0", "wdire": "WNW", "wspdi": "12.7", "windchilli": "-999", "wgusti": "-9999.0", "windchillm": "-999", "wspdm": "20.4", "dewptm": "16.0", "precipi": "-9999.00", "dewpti": "60.8", "thunder": "0", "wgustm": "-9999.0", "conds": "Mostly Cloudy", "snow": "0", "heatindexm": "-9999", "heatindexi": "-9999"}, {"tempm": "21", "pressurei": "30.07", "date": {"mon": "06", "pretty": "5:00 PM CEST on June 20, 2016", "mday": "20", "hour": "17", "min": "00", "tzname": "Europe/Warsaw", "year": "2016"}, "hum": "71", "icon": "tstorms", "metar": "AAXX 20151 12566 41570 72805 10206 20164 39899 40181 51002 72982 85932 333 91206", "precipm": "", "fog": "0", "wdird": "280", "rain": "0", "pressurem": "1018", "vism": "20", "tempi": "69", "utcdate": {"mon": "06", "pretty": "3:00 PM GMT on June 20, 2016", "mday": "20", "hour": "15", "min": "00", "tzname": "UTC", "year": "2016"}, "visi": "12", "tornado": "0", "hail": "0", "wdire": "West", "wspdi": "11.2", "windchilli": "-999", "wgusti": "", "windchillm": "-999", "wspdm": "18.0", "dewptm": "16", "precipi": "", "dewpti": "62", "thunder": "1", "wgustm": "", "conds": "Light Thunderstorm", "snow": "0", "heatindexm": "-9999", "heatindexi": "-9999"}, {"tempm": "20.0", "pressurei": "30.06", "date": {"mon": "06", "pretty": "5:00 PM CEST on June 20, 2016", "mday": "20", "hour": "17", "min": "00", "tzname": "Europe/Warsaw", "year": "2016"}, "hum": "78", "icon": "partlycloudy", "metar": "METAR EPKK 201500Z 29008KT 9999 FEW020CB SCT040 20/16 Q1018", "precipm": "-9999.00", "fog": "0", "wdird": "290", "rain": "0", "pressurem": "1018", "vism": "10.0", "tempi": "68.0", "utcdate": {"mon": "06", "pretty": "3:00 PM GMT on June 20, 2016", "mday": "20", "hour": "15", "min": "00", "tzname": "UTC", "year": "2016"}, "visi": "6.2", "tornado": "0", "hail": "0", "wdire": "WNW", "wspdi": "9.2", "windchilli": "-999", "wgusti": "-9999.0", "windchillm": "-999", "wspdm": "14.8", "dewptm": "16.0", "precipi": "-9999.00", "dewpti": "60.8", "thunder": "0", "wgustm": "-9999.0", "conds": "Scattered Clouds", "snow": "0", "heatindexm": "-9999", "heatindexi": "-9999"}, {"tempm": "21.0", "pressurei": "30.06", "date": {"mon": "06", "pretty": "5:30 PM CEST on June 20, 2016", "mday": "20", "hour": "17", "min": "30", "tzname": "Europe/Warsaw", "year": "2016"}, "hum": "73", "icon": "partlycloudy", "metar": "METAR EPKK 201530Z 26010KT 9999 FEW020CB SCT040 21/16 Q1018", "precipm": "-9999.00", "fog": "0", "wdird": "260", "rain": "0", "pressurem": "1018", "vism": "10.0", "tempi": "69.8", "utcdate": {"mon": "06", "pretty": "3:30 PM GMT on June 20, 2016", "mday": "20", "hour": "15", "min": "30", "tzname": "UTC", "year": "2016"}, "visi": "6.2", "tornado": "0", "hail": "0", "wdire": "West", "wspdi": "11.5", "windchilli": "-999", "wgusti": "-9999.0", "windchillm": "-999", "wspdm": "18.5", "dewptm": "16.0", "precipi": "-9999.00", "dewpti": "60.8", "thunder": "0", "wgustm": "-9999.0", "conds": "Scattered Clouds", "snow": "0", "heatindexm": "-9999", "heatindexi": "-9999"}, {"tempm": "21", "pressurei": "30.08", "date": {"mon": "06", "pretty": "6:00 PM CEST on June 20, 2016", "mday": "20", "hour": "18", "min": "00", "tzname": "Europe/Warsaw", "year": "2016"}, "hum": "61", "icon": "partlycloudy", "metar": "AAXX 20161 12566 42565 52805 10207 20148 39904 40186 52009 84352 333 91206 555 90005", "precipm": "", "fog": "0", "wdird": "280", "rain": "0", "pressurem": "1019", "vism": "15", "tempi": "69", "utcdate": {"mon": "06", "pretty": "4:00 PM GMT on June 20, 2016", "mday": "20", "hour": "16", "min": "00", "tzname": "UTC", "year": "2016"}, "visi": "9", "tornado": "0", "hail": "0", "wdire": "West", "wspdi": "11.2", "windchilli": "-999", "wgusti": "", "windchillm": "-999", "wspdm": "18.0", "dewptm": "15", "precipi": "", "dewpti": "59", "thunder": "0", "wgustm": "", "conds": "Partly Cloudy", "snow": "0", "heatindexm": "-9999", "heatindexi": "-9999"}, {"tempm": "21.0", "pressurei": "30.09", "date": {"mon": "06", "pretty": "6:00 PM CEST on June 20, 2016", "mday": "20", "hour": "18", "min": "00", "tzname": "Europe/Warsaw", "year": "2016"}, "hum": "68", "icon": "partlycloudy", "metar": "METAR EPKK 201600Z 29011KT 9999 FEW020CB 21/15 Q1019", "precipm": "-9999.00", "fog": "0", "wdird": "290", "rain": "0", "pressurem": "1019", "vism": "10.0", "tempi": "69.8", "utcdate": {"mon": "06", "pretty": "4:00 PM GMT on June 20, 2016", "mday": "20", "hour": "16", "min": "00", "tzname": "UTC", "year": "2016"}, "visi": "6.2", "tornado": "0", "hail": "0", "wdire": "WNW", "wspdi": "12.7", "windchilli": "-999", "wgusti": "-9999.0", "windchillm": "-999", "wspdm": "20.4", "dewptm": "15.0", "precipi": "-9999.00", "dewpti": "59.0", "thunder": "0", "wgustm": "-9999.0", "conds": "Partly Cloudy", "snow": "0", "heatindexm": "-9999", "heatindexi": "-9999"}, {"tempm": "20.0", "pressurei": "30.09", "date": {"mon": "06", "pretty": "6:30 PM CEST on June 20, 2016", "mday": "20", "hour": "18", "min": "30", "tzname": "Europe/Warsaw", "year": "2016"}, "hum": "73", "icon": "partlycloudy", "metar": "METAR EPKK 201630Z 28011KT 9999 FEW020CB SCT030 20/15 Q1019", "precipm": "-9999.00", "fog": "0", "wdird": "280", "rain": "0", "pressurem": "1019", "vism": "10.0", "tempi": "68.0", "utcdate": {"mon": "06", "pretty": "4:30 PM GMT on June 20, 2016", "mday": "20", "hour": "16", "min": "30", "tzname": "UTC", "year": "2016"}, "visi": "6.2", "tornado": "0", "hail": "0", "wdire": "West", "wspdi": "12.7", "windchilli": "-999", "wgusti": "-9999.0", "windchillm": "-999", "wspdm": "20.4", "dewptm": "15.0", "precipi": "-9999.00", "dewpti": "59.0", "thunder": "0", "wgustm": "-9999.0", "conds": "Scattered Clouds", "snow": "0", "heatindexm": "-9999", "heatindexi": "-9999"}, {"tempm": "19", "pressurei": "30.10", "date": {"mon": "06", "pretty": "7:00 PM CEST on June 20, 2016", "mday": "20", "hour": "19", "min": "00", "tzname": "Europe/Warsaw", "year": "2016"}, "hum": "72", "icon": "partlycloudy", "metar": "AAXX 20171 12566 42580 62604 10190 20151 39909 40193 53010 83532 333 91206 555 90005", "precipm": "", "fog": "0", "wdird": "260", "rain": "0", "pressurem": "1019", "vism": "30", "tempi": "66", "utcdate": {"mon": "06", "pretty": "5:00 PM GMT on June 20, 2016", "mday": "20", "hour": "17", "min": "00", "tzname": "UTC", "year": "2016"}, "visi": "19", "tornado": "0", "hail": "0", "wdire": "West", "wspdi": "8.9", "windchilli": "-999", "wgusti": "", "windchillm": "-999", "wspdm": "14.4", "dewptm": "15", "precipi": "", "dewpti": "59", "thunder": "0", "wgustm": "", "conds": "Partly Cloudy", "snow": "0", "heatindexm": "-9999", "heatindexi": "-9999"}, {"tempm": "19.0", "pressurei": "30.09", "date": {"mon": "06", "pretty": "7:00 PM CEST on June 20, 2016", "mday": "20", "hour": "19", "min": "00", "tzname": "Europe/Warsaw", "year": "2016"}, "hum": "78", "icon": "partlycloudy", "metar": "METAR EPKK 201700Z 27009KT 9999 SCT030 19/15 Q1019", "precipm": "-9999.00", "fog": "0", "wdird": "270", "rain": "0", "pressurem": "1019", "vism": "10.0", "tempi": "66.2", "utcdate": {"mon": "06", "pretty": "5:00 PM GMT on June 20, 2016", "mday": "20", "hour": "17", "min": "00", "tzname": "UTC", "year": "2016"}, "visi": "6.2", "tornado": "0", "hail": "0", "wdire": "West", "wspdi": "10.4", "windchilli": "-999", "wgusti": "-9999.0", "windchillm": "-999", "wspdm": "16.7", "dewptm": "15.0", "precipi": "-9999.00", "dewpti": "59.0", "thunder": "0", "wgustm": "-9999.0", "conds": "Scattered Clouds", "snow": "0", "heatindexm": "-9999", "heatindexi": "-9999"}, {"tempm": "19.0", "pressurei": "30.09", "date": {"mon": "06", "pretty": "7:30 PM CEST on June 20, 2016", "mday": "20", "hour": "19", "min": "30", "tzname": "Europe/Warsaw", "year": "2016"}, "hum": "78", "icon": "partlycloudy", "metar": "METAR EPKK 201730Z 27008KT 9999 SCT027 19/15 Q1019", "precipm": "-9999.00", "fog": "0", "wdird": "270", "rain": "0", "pressurem": "1019", "vism": "10.0", "tempi": "66.2", "utcdate": {"mon": "06", "pretty": "5:30 PM GMT on June 20, 2016", "mday": "20", "hour": "17", "min": "30", "tzname": "UTC", "year": "2016"}, "visi": "6.2", "tornado": "0", "hail": "0", "wdire": "West", "wspdi": "9.2", "windchilli": "-999", "wgusti": "-9999.0", "windchillm": "-999", "wspdm": "14.8", "dewptm": "15.0", "precipi": "-9999.00", "dewpti": "59.0", "thunder": "0", "wgustm": "-9999.0", "conds": "Scattered Clouds", "snow": "0", "heatindexm": "-9999", "heatindexi": "-9999"}, {"tempm": "18", "pressurei": "30.12", "date": {"mon": "06", "pretty": "8:00 PM CEST on June 20, 2016", "mday": "20", "hour": "20", "min": "00", "tzname": "Europe/Warsaw", "year": "2016"}, "hum": "78", "icon": "partlycloudy", "metar": "AAXX 20181 12566 11580 52604 10180 20149 39912 40197 52013 69922 70198 83532 333 10214 20164 91206 93092", "precipm": "", "fog": "0", "wdird": "260", "rain": "0", "pressurem": "1020", "vism": "30", "tempi": "64", "utcdate": {"mon": "06", "pretty": "6:00 PM GMT on June 20, 2016", "mday": "20", "hour": "18", "min": "00", "tzname": "UTC", "year": "2016"}, "visi": "19", "tornado": "0", "hail": "0", "wdire": "West", "wspdi": "8.9", "windchilli": "-999", "wgusti": "", "windchillm": "-999", "wspdm": "14.4", "dewptm": "15", "precipi": "", "dewpti": "59", "thunder": "0", "wgustm": "", "conds": "Partly Cloudy", "snow": "0", "heatindexm": "-9999", "heatindexi": "-9999"}, {"tempm": "18.0", "pressurei": "30.09", "date": {"mon": "06", "pretty": "8:00 PM CEST on June 20, 2016", "mday": "20", "hour": "20", "min": "00", "tzname": "Europe/Warsaw", "year": "2016"}, "hum": "83", "icon": "partlycloudy", "metar": "METAR EPKK 201800Z 27008KT 9999 SCT024 18/15 Q1019", "precipm": "-9999.00", "fog": "0", "wdird": "270", "rain": "0", "pressurem": "1019", "vism": "10.0", "tempi": "64.4", "utcdate": {"mon": "06", "pretty": "6:00 PM GMT on June 20, 2016", "mday": "20", "hour": "18", "min": "00", "tzname": "UTC", "year": "2016"}, "visi": "6.2", "tornado": "0", "hail": "0", "wdire": "West", "wspdi": "9.2", "windchilli": "-999", "wgusti": "-9999.0", "windchillm": "-999", "wspdm": "14.8", "dewptm": "15.0", "precipi": "-9999.00", "dewpti": "59.0", "thunder": "0", "wgustm": "-9999.0", "conds": "Scattered Clouds", "snow": "0", "heatindexm": "-9999", "heatindexi": "-9999"}, {"tempm": "18.0", "pressurei": "30.09", "date": {"mon": "06", "pretty": "8:30 PM CEST on June 20, 2016", "mday": "20", "hour": "20", "min": "30", "tzname": "Europe/Warsaw", "year": "2016"}, "hum": "83", "icon": "partlycloudy", "metar": "METAR EPKK 201830Z 27005KT 240V300 9999 SCT024 18/15 Q1019", "precipm": "-9999.00", "fog": "0", "wdird": "270", "rain": "0", "pressurem": "1019", "vism": "10.0", "tempi": "64.4", "utcdate": {"mon": "06", "pretty": "6:30 PM GMT on June 20, 2016", "mday": "20", "hour": "18", "min": "30", "tzname": "UTC", "year": "2016"}, "visi": "6.2", "tornado": "0", "hail": "0", "wdire": "West", "wspdi": "5.8", "windchilli": "-999", "wgusti": "-9999.0", "windchillm": "-999", "wspdm": "9.3", "dewptm": "15.0", "precipi": "-9999.00", "dewpti": "59.0", "thunder": "0", "wgustm": "-9999.0", "conds": "Scattered Clouds", "snow": "0", "heatindexm": "-9999", "heatindexi": "-9999"}, {"tempm": "18", "pressurei": "30.12", "date": {"mon": "06", "pretty": "9:00 PM CEST on June 20, 2016", "mday": "20", "hour": "21", "min": "00", "tzname": "Europe/Warsaw", "year": "2016"}, "hum": "80", "icon": "rain", "metar": "AAXX 20191 12566 41465 72902 10178 20152 39914 40199 51010 78022 85932 333 82614 91203 555 57037 90005", "precipm": "", "fog": "0", "wdird": "290", "rain": "1", "pressurem": "1020", "vism": "15", "tempi": "64", "utcdate": {"mon": "06", "pretty": "7:00 PM GMT on June 20, 2016", "mday": "20", "hour": "19", "min": "00", "tzname": "UTC", "year": "2016"}, "visi": "9", "tornado": "0", "hail": "0", "wdire": "WNW", "wspdi": "4.5", "windchilli": "-999", "wgusti": "", "windchillm": "-999", "wspdm": "7.2", "dewptm": "15", "precipi": "", "dewpti": "59", "thunder": "0", "wgustm": "", "conds": "Light Rain Showers", "snow": "0", "heatindexm": "-9999", "heatindexi": "-9999"}, {"tempm": "18.0", "pressurei": "30.12", "date": {"mon": "06", "pretty": "9:00 PM CEST on June 20, 2016", "mday": "20", "hour": "21", "min": "00", "tzname": "Europe/Warsaw", "year": "2016"}, "hum": "83", "icon": "rain", "metar": "METAR EPKK 201900Z 30004KT 9999 -SHRA FEW013 SCT020CB 18/15 Q1020", "precipm": "-9999.00", "fog": "0", "wdird": "300", "rain": "1", "pressurem": "1020", "vism": "10.0", "tempi": "64.4", "utcdate": {"mon": "06", "pretty": "7:00 PM GMT on June 20, 2016", "mday": "20", "hour": "19", "min": "00", "tzname": "UTC", "year": "2016"}, "visi": "6.2", "tornado": "0", "hail": "0", "wdire": "WNW", "wspdi": "4.6", "windchilli": "-999", "wgusti": "-9999.0", "windchillm": "-999", "wspdm": "7.4", "dewptm": "15.0", "precipi": "-9999.00", "dewpti": "59.0", "thunder": "0", "wgustm": "-9999.0", "conds": "Light Rain Showers", "snow": "0", "heatindexm": "-9999", "heatindexi": "-9999"}, {"tempm": "17.0", "pressurei": "30.12", "date": {"mon": "06", "pretty": "9:30 PM CEST on June 20, 2016", "mday": "20", "hour": "21", "min": "30", "tzname": "Europe/Warsaw", "year": "2016"}, "hum": "88", "icon": "rain", "metar": "METAR EPKK 201930Z 32003KT 280V350 9999 -SHRA FEW013 SCT025CB 17/15 Q1020", "precipm": "-9999.00", "fog": "0", "wdird": "320", "rain": "1", "pressurem": "1020", "vism": "10.0", "tempi": "62.6", "utcdate": {"mon": "06", "pretty": "7:30 PM GMT on June 20, 2016", "mday": "20", "hour": "19", "min": "30", "tzname": "UTC", "year": "2016"}, "visi": "6.2", "tornado": "0", "hail": "0", "wdire": "NW", "wspdi": "3.5", "windchilli": "-999", "wgusti": "-9999.0", "windchillm": "-999", "wspdm": "5.6", "dewptm": "15.0", "precipi": "-9999.00", "dewpti": "59.0", "thunder": "0", "wgustm": "-9999.0", "conds": "Light Rain Showers", "snow": "0", "heatindexm": "-9999", "heatindexi": "-9999"}, {"tempm": "17", "pressurei": "30.15", "date": {"mon": "06", "pretty": "10:00 PM CEST on June 20, 2016", "mday": "20", "hour": "22", "min": "00", "tzname": "Europe/Warsaw", "year": "2016"}, "hum": "81", "icon": "rain", "metar": "AAXX 20201 12566 41470 73101 10172 20148 39923 40209 53014 72582 875// 333 91202 555 0//// 1//// 2//// 30147 70218 90005", "precipm": "", "fog": "0", "wdird": "310", "rain": "1", "pressurem": "1021", "vism": "20", "tempi": "63", "utcdate": {"mon": "06", "pretty": "8:00 PM GMT on June 20, 2016", "mday": "20", "hour": "20", "min": "00", "tzname": "UTC", "year": "2016"}, "visi": "12", "tornado": "0", "hail": "0", "wdire": "NW", "wspdi": "2.2", "windchilli": "-999", "wgusti": "", "windchillm": "-999", "wspdm": "3.6", "dewptm": "15", "precipi": "", "dewpti": "59", "thunder": "0", "wgustm": "", "conds": "Light Rain Showers", "snow": "0", "heatindexm": "-9999", "heatindexi": "-9999"}, {"tempm": "17.0", "pressurei": "30.15", "date": {"mon": "06", "pretty": "10:00 PM CEST on June 20, 2016", "mday": "20", "hour": "22", "min": "00", "tzname": "Europe/Warsaw", "year": "2016"}, "hum": "88", "icon": "mostlycloudy", "metar": "METAR EPKK 202000Z VRB02KT 9999 FEW015 BKN023 17/15 Q1021", "precipm": "-9999.00", "fog": "0", "wdird": "0", "rain": "0", "pressurem": "1021", "vism": "10.0", "tempi": "62.6", "utcdate": {"mon": "06", "pretty": "8:00 PM GMT on June 20, 2016", "mday": "20", "hour": "20", "min": "00", "tzname": "UTC", "year": "2016"}, "visi": "6.2", "tornado": "0", "hail": "0", "wdire": "Variable", "wspdi": "2.3", "windchilli": "-999", "wgusti": "-9999.0", "windchillm": "-999", "wspdm": "3.7", "dewptm": "15.0", "precipi": "-9999.00", "dewpti": "59.0", "thunder": "0", "wgustm": "-9999.0", "conds": "Mostly Cloudy", "snow": "0", "heatindexm": "-9999", "heatindexi": "-9999"}, {"tempm": "17.0", "pressurei": "30.15", "date": {"mon": "06", "pretty": "10:30 PM CEST on June 20, 2016", "mday": "20", "hour": "22", "min": "30", "tzname": "Europe/Warsaw", "year": "2016"}, "hum": "88", "icon": "mostlycloudy", "metar": "METAR EPKK 202030Z 32003KT 9999 FEW014 BKN020 17/15 Q1021", "precipm": "-9999.00", "fog": "0", "wdird": "320", "rain": "0", "pressurem": "1021", "vism": "10.0", "tempi": "62.6", "utcdate": {"mon": "06", "pretty": "8:30 PM GMT on June 20, 2016", "mday": "20", "hour": "20", "min": "30", "tzname": "UTC", "year": "2016"}, "visi": "6.2", "tornado": "0", "hail": "0", "wdire": "NW", "wspdi": "3.5", "windchilli": "-999", "wgusti": "-9999.0", "windchillm": "-999", "wspdm": "5.6", "dewptm": "15.0", "precipi": "-9999.00", "dewpti": "59.0", "thunder": "0", "wgustm": "-9999.0", "conds": "Mostly Cloudy", "snow": "0", "heatindexm": "-9999", "heatindexi": "-9999"}, {"tempm": "17", "pressurei": "30.16", "date": {"mon": "06", "pretty": "11:00 PM CEST on June 20, 2016", "mday": "20", "hour": "23", "min": "00", "tzname": "Europe/Warsaw", "year": "2016"}, "hum": "81", "icon": "partlycloudy", "metar": "AAXX 20211 12566 41570 72901 10170 20148 39925 40211 52013 70182 875// 333 91203", "precipm": "", "fog": "0", "wdird": "290", "rain": "0", "pressurem": "1021", "vism": "20", "tempi": "63", "utcdate": {"mon": "06", "pretty": "9:00 PM GMT on June 20, 2016", "mday": "20", "hour": "21", "min": "00", "tzname": "UTC", "year": "2016"}, "visi": "12", "tornado": "0", "hail": "0", "wdire": "WNW", "wspdi": "2.2", "windchilli": "-999", "wgusti": "", "windchillm": "-999", "wspdm": "3.6", "dewptm": "15", "precipi": "", "dewpti": "59", "thunder": "0", "wgustm": "", "conds": "Partly Cloudy", "snow": "0", "heatindexm": "-9999", "heatindexi": "-9999"}, {"tempm": "17.0", "pressurei": "30.15", "date": {"mon": "06", "pretty": "11:00 PM CEST on June 20, 2016", "mday": "20", "hour": "23", "min": "00", "tzname": "Europe/Warsaw", "year": "2016"}, "hum": "88", "icon": "mostlycloudy", "metar": "METAR EPKK 202100Z VRB02KT 9999 BKN020 17/15 Q1021", "precipm": "-9999.00", "fog": "0", "wdird": "0", "rain": "0", "pressurem": "1021", "vism": "10.0", "tempi": "62.6", "utcdate": {"mon": "06", "pretty": "9:00 PM GMT on June 20, 2016", "mday": "20", "hour": "21", "min": "00", "tzname": "UTC", "year": "2016"}, "visi": "6.2", "tornado": "0", "hail": "0", "wdire": "Variable", "wspdi": "2.3", "windchilli": "-999", "wgusti": "-9999.0", "windchillm": "-999", "wspdm": "3.7", "dewptm": "15.0", "precipi": "-9999.00", "dewpti": "59.0", "thunder": "0", "wgustm": "-9999.0", "conds": "Mostly Cloudy", "snow": "0", "heatindexm": "-9999", "heatindexi": "-9999"}, {"tempm": "17.0", "pressurei": "30.15", "date": {"mon": "06", "pretty": "11:30 PM CEST on June 20, 2016", "mday": "20", "hour": "23", "min": "30", "tzname": "Europe/Warsaw", "year": "2016"}, "hum": "88", "icon": "mostlycloudy", "metar": "METAR EPKK 202130Z VRB02KT 9999 BKN020 17/15 Q1021", "precipm": "-9999.00", "fog": "0", "wdird": "0", "rain": "0", "pressurem": "1021", "vism": "10.0", "tempi": "62.6", "utcdate": {"mon": "06", "pretty": "9:30 PM GMT on June 20, 2016", "mday": "20", "hour": "21", "min": "30", "tzname": "UTC", "year": "2016"}, "visi": "6.2", "tornado": "0", "hail": "0", "wdire": "Variable", "wspdi": "2.3", "windchilli": "-999", "wgusti": "-9999.0", "windchillm": "-999", "wspdm": "3.7", "dewptm": "15.0", "precipi": "-9999.00", "dewpti": "59.0", "thunder": "0", "wgustm": "-9999.0", "conds": "Mostly Cloudy", "snow": "0", "heatindexm": "-9999", "heatindexi": "-9999"}], "utcdate": {"mon": "06", "pretty": "June 19, 2016", "mday": "19", "hour": "22", "min": "00", "tzname": "UTC", "year": "2016"}}, "response": {"version": "0.1", "termsofService": "http://www.wunderground.com/weather/api/d/terms.html", "features": {"history": 1}}}