{"response": {"features": {"history": 1}, "version": "0.1", "termsofService": "http://www.wunderground.com/weather/api/d/terms.html"}, "history": {"utcdate": {"year": "2017", "mon": "05", "min": "00", "hour": "22", "pretty": "May 30, 2017", "tzname": "UTC", "mday": "30"}, "observations": [{"rain": "0", "date": {"year": "2017", "mon": "05", "min": "00", "hour": "00", "pretty": "12:00 AM CEST on May 31, 2017", "tzname": "Europe/Warsaw", "mday": "31"}, "dewptm": "17", "heatindexi": "-9999", "visi": "9", "pressurem": "1014", "metar": "AAXX 30221 12566 42965 72501 10175 20167 39852 40136 55020 8707/ 333 91203 555 60212 90005", "thunder": "0", "windchilli": "-999", "fog": "0", "wdird": "250", "snow": "0", "wspdm": "3.6", "vism": "15", "icon": "mostlycloudy", "utcdate": {"year": "2017", "mon": "05", "min": "00", "hour": "22", "pretty": "10:00 PM GMT on May 30, 2017", "tzname": "UTC", "mday": "30"}, "wspdi": "2.2", "dewpti": "62", "windchillm": "-999", "wdire": "WSW", "tempi": "64", "wgustm": "", "pressurei": "29.94", "tempm": "18", "precipm": "", "hail": "0", "hum": "91", "precipi": "", "conds": "Mostly Cloudy", "wgusti": "", "heatindexm": "-9999", "tornado": "0"}, {"rain": "0", "date": {"year": "2017", "mon": "05", "min": "00", "hour": "00", "pretty": "12:00 AM CEST on May 31, 2017", "tzname": "Europe/Warsaw", "mday": "31"}, "dewptm": "16.0", "heatindexi": "-9999", "visi": "-9999.0", "pressurem": "1013", "metar": "METAR EPKK 302200Z 28005KT CAVOK 17/16 Q1013", "thunder": "0", "windchilli": "-999", "fog": "0", "wdird": "280", "snow": "0", "wspdm": "9.3", "vism": "-9999.0", "icon": "clear", "utcdate": {"year": "2017", "mon": "05", "min": "00", "hour": "22", "pretty": "10:00 PM GMT on May 30, 2017", "tzname": "UTC", "mday": "30"}, "wspdi": "5.8", "dewpti": "60.8", "windchillm": "-999", "wdire": "West", "tempi": "62.6", "wgustm": "-9999.0", "pressurei": "29.92", "tempm": "17.0", "precipm": "-9999.00", "hail": "0", "hum": "94", "precipi": "-9999.00", "conds": "Clear", "wgusti": "-9999.0", "heatindexm": "-9999", "tornado": "0"}, {"rain": "0", "date": {"year": "2017", "mon": "05", "min": "30", "hour": "00", "pretty": "12:30 AM CEST on May 31, 2017", "tzname": "Europe/Warsaw", "mday": "31"}, "dewptm": "16.0", "heatindexi": "-9999", "visi": "-9999.0", "pressurem": "1014", "metar": "METAR EPKK 302230Z 28006KT CAVOK 18/16 Q1014", "thunder": "0", "windchilli": "-999", "fog": "0", "wdird": "280", "snow": "0", "wspdm": "11.1", "vism": "-9999.0", "icon": "clear", "utcdate": {"year": "2017", "mon": "05", "min": "30", "hour": "22", "pretty": "10:30 PM GMT on May 30, 2017", "tzname": "UTC", "mday": "30"}, "wspdi": "6.9", "dewpti": "60.8", "windchillm": "-999", "wdire": "West", "tempi": "64.4", "wgustm": "-9999.0", "pressurei": "29.95", "tempm": "18.0", "precipm": "-9999.00", "hail": "0", "hum": "88", "precipi": "-9999.00", "conds": "Clear", "wgusti": "-9999.0", "heatindexm": "-9999", "tornado": "0"}, {"rain": "0", "date": {"year": "2017", "mon": "05", "min": "00", "hour": "01", "pretty": "1:00 AM CEST on May 31, 2017", "tzname": "Europe/Warsaw", "mday": "31"}, "dewptm": "16", "heatindexi": "-9999", "visi": "9", "pressurem": "1014", "metar": "AAXX 30231 12566 42665 72502 10177 20164 39859 40143 53001 8257/ 333 91203 555 90005", "thunder": "0", "windchilli": "-999", "fog": "0", "wdird": "250", "snow": "0", "wspdm": "7.2", "vism": "15", "icon": "partlycloudy", "utcdate": {"year": "2017", "mon": "05", "min": "00", "hour": "23", "pretty": "11:00 PM GMT on May 30, 2017", "tzname": "UTC", "mday": "30"}, "wspdi": "4.5", "dewpti": "62", "windchillm": "-999", "wdire": "WSW", "tempi": "64", "wgustm": "", "pressurei": "29.96", "tempm": "18", "precipm": "", "hail": "0", "hum": "89", "precipi": "", "conds": "Scattered Clouds", "wgusti": "", "heatindexm": "-9999", "tornado": "0"}, {"rain": "0", "date": {"year": "2017", "mon": "05", "min": "00", "hour": "01", "pretty": "1:00 AM CEST on May 31, 2017", "tzname": "Europe/Warsaw", "mday": "31"}, "dewptm": "16.0", "heatindexi": "-9999", "visi": "6.2", "pressurem": "1014", "metar": "METAR EPKK 302300Z 24003KT 210V270 9999 FEW038 18/16 Q1014", "thunder": "0", "windchilli": "-999", "fog": "0", "wdird": "240", "snow": "0", "wspdm": "5.6", "vism": "10.0", "icon": "partlycloudy", "utcdate": {"year": "2017", "mon": "05", "min": "00", "hour": "23", "pretty": "11:00 PM GMT on May 30, 2017", "tzname": "UTC", "mday": "30"}, "wspdi": "3.5", "dewpti": "60.8", "windchillm": "-999", "wdire": "WSW", "tempi": "64.4", "wgustm": "-9999.0", "pressurei": "29.95", "tempm": "18.0", "precipm": "-9999.00", "hail": "0", "hum": "88", "precipi": "-9999.00", "conds": "Partly Cloudy", "wgusti": "-9999.0", "heatindexm": "-9999", "tornado": "0"}, {"rain": "0", "date": {"year": "2017", "mon": "05", "min": "30", "hour": "01", "pretty": "1:30 AM CEST on May 31, 2017", "tzname": "Europe/Warsaw", "mday": "31"}, "dewptm": "16.0", "heatindexi": "-9999", "visi": "6.2", "pressurem": "1014", "metar": "METAR EPKK 302330Z 22007KT 9999 FEW052 18/16 Q1014", "thunder": "0", "windchilli": "-999", "fog": "0", "wdird": "220", "snow": "0", "wspdm": "13.0", "vism": "10.0", "icon": "partlycloudy", "utcdate": {"year": "2017", "mon": "05", "min": "30", "hour": "23", "pretty": "11:30 PM GMT on May 30, 2017", "tzname": "UTC", "mday": "30"}, "wspdi": "8.1", "dewpti": "60.8", "windchillm": "-999", "wdire": "SW", "tempi": "64.4", "wgustm": "-9999.0", "pressurei": "29.95", "tempm": "18.0", "precipm": "-9999.00", "hail": "0", "hum": "88", "precipi": "-9999.00", "conds": "Partly Cloudy", "wgusti": "-9999.0", "heatindexm": "-9999", "tornado": "0"}, {"rain": "0", "date": {"year": "2017", "mon": "05", "min": "00", "hour": "02", "pretty": "2:00 AM CEST on May 31, 2017", "tzname": "Europe/Warsaw", "mday": "31"}, "dewptm": "16", "heatindexi": "-9999", "visi": "12", "pressurem": "1014", "metar": "AAXX 31001 12566 11970 72304 10178 20161 39857 40140 50010 69941 70198 8707/ 333 91205 93094", "thunder": "0", "windchilli": "-999", "fog": "0", "wdird": "230", "snow": "0", "wspdm": "14.4", "vism": "20", "icon": "partlycloudy", "utcdate": {"year": "2017", "mon": "05", "min": "00", "hour": "00", "pretty": "12:00 AM GMT on May 31, 2017", "tzname": "UTC", "mday": "31"}, "wspdi": "8.9", "dewpti": "61", "windchillm": "-999", "wdire": "SW", "tempi": "64", "wgustm": "", "pressurei": "29.95", "tempm": "18", "precipm": "", "hail": "0", "hum": "87", "precipi": "", "conds": "Partly Cloudy", "wgusti": "", "heatindexm": "-9999", "tornado": "0"}, {"rain": "0", "date": {"year": "2017", "mon": "05", "min": "00", "hour": "02", "pretty": "2:00 AM CEST on May 31, 2017", "tzname": "Europe/Warsaw", "mday": "31"}, "dewptm": "16.0", "heatindexi": "-9999", "visi": "-9999.0", "pressurem": "1014", "metar": "METAR EPKK 310000Z 23009KT CAVOK 18/16 Q1014", "thunder": "0", "windchilli": "-999", "fog": "0", "wdird": "230", "snow": "0", "wspdm": "16.7", "vism": "-9999.0", "icon": "clear", "utcdate": {"year": "2017", "mon": "05", "min": "00", "hour": "00", "pretty": "12:00 AM GMT on May 31, 2017", "tzname": "UTC", "mday": "31"}, "wspdi": "10.4", "dewpti": "60.8", "windchillm": "-999", "wdire": "SW", "tempi": "64.4", "wgustm": "-9999.0", "pressurei": "29.95", "tempm": "18.0", "precipm": "-9999.00", "hail": "0", "hum": "88", "precipi": "-9999.00", "conds": "Clear", "wgusti": "-9999.0", "heatindexm": "-9999", "tornado": "0"}, {"rain": "1", "date": {"year": "2017", "mon": "05", "min": "30", "hour": "02", "pretty": "2:30 AM CEST on May 31, 2017", "tzname": "Europe/Warsaw", "mday": "31"}, "dewptm": "16.0", "heatindexi": "-9999", "visi": "6.2", "pressurem": "1014", "metar": "METAR EPKK 310030Z 25008KT 9999 -SHRA FEW053CB 18/16 Q1014", "thunder": "0", "windchilli": "-999", "fog": "0", "wdird": "250", "snow": "0", "wspdm": "14.8", "vism": "10.0", "icon": "rain", "utcdate": {"year": "2017", "mon": "05", "min": "30", "hour": "00", "pretty": "12:30 AM GMT on May 31, 2017", "tzname": "UTC", "mday": "31"}, "wspdi": "9.2", "dewpti": "60.8", "windchillm": "-999", "wdire": "WSW", "tempi": "64.4", "wgustm": "-9999.0", "pressurei": "29.95", "tempm": "18.0", "precipm": "-9999.00", "hail": "0", "hum": "88", "precipi": "-9999.00", "conds": "Light Rain Showers", "wgusti": "-9999.0", "heatindexm": "-9999", "tornado": "0"}, {"rain": "0", "date": {"year": "2017", "mon": "05", "min": "00", "hour": "03", "pretty": "3:00 AM CEST on May 31, 2017", "tzname": "Europe/Warsaw", "mday": "31"}, "dewptm": "16.0", "heatindexi": "-9999", "visi": "6.2", "pressurem": "1014", "metar": "METAR EPKK 310100Z 25009KT 9999 FEW046CB 18/16 Q1014", "thunder": "0", "windchilli": "-999", "fog": "0", "wdird": "250", "snow": "0", "wspdm": "16.7", "vism": "10.0", "icon": "partlycloudy", "utcdate": {"year": "2017", "mon": "05", "min": "00", "hour": "01", "pretty": "1:00 AM GMT on May 31, 2017", "tzname": "UTC", "mday": "31"}, "wspdi": "10.4", "dewpti": "60.8", "windchillm": "-999", "wdire": "WSW", "tempi": "64.4", "wgustm": "-9999.0", "pressurei": "29.95", "tempm": "18.0", "precipm": "-9999.00", "hail": "0", "hum": "88", "precipi": "-9999.00", "conds": "Partly Cloudy", "wgusti": "-9999.0", "heatindexm": "-9999", "tornado": "0"}, {"rain": "0", "date": {"year": "2017", "mon": "05", "min": "30", "hour": "03", "pretty": "3:30 AM CEST on May 31, 2017", "tzname": "Europe/Warsaw", "mday": "31"}, "dewptm": "16.0", "heatindexi": "-9999", "visi": "6.2", "pressurem": "1014", "metar": "METAR EPKK 310130Z 22007KT 9999 FEW040CB 18/16 Q1014", "thunder": "0", "windchilli": "-999", "fog": "0", "wdird": "220", "snow": "0", "wspdm": "13.0", "vism": "10.0", "icon": "partlycloudy", "utcdate": {"year": "2017", "mon": "05", "min": "30", "hour": "01", "pretty": "1:30 AM GMT on May 31, 2017", "tzname": "UTC", "mday": "31"}, "wspdi": "8.1", "dewpti": "60.8", "windchillm": "-999", "wdire": "SW", "tempi": "64.4", "wgustm": "-9999.0", "pressurei": "29.95", "tempm": "18.0", "precipm": "-9999.00", "hail": "0", "hum": "88", "precipi": "-9999.00", "conds": "Partly Cloudy", "wgusti": "-9999.0", "heatindexm": "-9999", "tornado": "0"}, {"rain": "0", "date": {"year": "2017", "mon": "05", "min": "00", "hour": "04", "pretty": "4:00 AM CEST on May 31, 2017", "tzname": "Europe/Warsaw", "mday": "31"}, "dewptm": "16", "heatindexi": "-9999", "visi": "19", "pressurem": "1014", "metar": "AAXX 31021 12566 42680 62302 10174 20159 39856 40140 56003 82532 333 91204 555 90005", "thunder": "0", "windchilli": "-999", "fog": "0", "wdird": "230", "snow": "0", "wspdm": "7.2", "vism": "30", "icon": "partlycloudy", "utcdate": {"year": "2017", "mon": "05", "min": "00", "hour": "02", "pretty": "2:00 AM GMT on May 31, 2017", "tzname": "UTC", "mday": "31"}, "wspdi": "4.5", "dewpti": "61", "windchillm": "-999", "wdire": "SW", "tempi": "63", "wgustm": "", "pressurei": "29.95", "tempm": "17", "precipm": "", "hail": "0", "hum": "89", "precipi": "", "conds": "Scattered Clouds", "wgusti": "", "heatindexm": "-9999", "tornado": "0"}, {"rain": "0", "date": {"year": "2017", "mon": "05", "min": "00", "hour": "04", "pretty": "4:00 AM CEST on May 31, 2017", "tzname": "Europe/Warsaw", "mday": "31"}, "dewptm": "16.0", "heatindexi": "-9999", "visi": "6.2", "pressurem": "1014", "metar": "METAR EPKK 310200Z 21004KT 9999 FEW060 17/16 Q1014", "thunder": "0", "windchilli": "-999", "fog": "0", "wdird": "210", "snow": "0", "wspdm": "7.4", "vism": "10.0", "icon": "partlycloudy", "utcdate": {"year": "2017", "mon": "05", "min": "00", "hour": "02", "pretty": "2:00 AM GMT on May 31, 2017", "tzname": "UTC", "mday": "31"}, "wspdi": "4.6", "dewpti": "60.8", "windchillm": "-999", "wdire": "SSW", "tempi": "62.6", "wgustm": "-9999.0", "pressurei": "29.95", "tempm": "17.0", "precipm": "-9999.00", "hail": "0", "hum": "94", "precipi": "-9999.00", "conds": "Partly Cloudy", "wgusti": "-9999.0", "heatindexm": "-9999", "tornado": "0"}, {"rain": "0", "date": {"year": "2017", "mon": "05", "min": "30", "hour": "04", "pretty": "4:30 AM CEST on May 31, 2017", "tzname": "Europe/Warsaw", "mday": "31"}, "dewptm": "16.0", "heatindexi": "-9999", "visi": "-9999.0", "pressurem": "1014", "metar": "METAR EPKK 310230Z VRB02KT CAVOK 17/16 Q1014", "thunder": "0", "windchilli": "-999", "fog": "0", "wdird": "0", "snow": "0", "wspdm": "3.7", "vism": "-9999.0", "icon": "clear", "utcdate": {"year": "2017", "mon": "05", "min": "30", "hour": "02", "pretty": "2:30 AM GMT on May 31, 2017", "tzname": "UTC", "mday": "31"}, "wspdi": "2.3", "dewpti": "60.8", "windchillm": "-999", "wdire": "Variable", "tempi": "62.6", "wgustm": "-9999.0", "pressurei": "29.95", "tempm": "17.0", "precipm": "-9999.00", "hail": "0", "hum": "94", "precipi": "-9999.00", "conds": "Clear", "wgusti": "-9999.0", "heatindexm": "-9999", "tornado": "0"}, {"rain": "0", "date": {"year": "2017", "mon": "05", "min": "00", "hour": "05", "pretty": "5:00 AM CEST on May 31, 2017", "tzname": "Europe/Warsaw", "mday": "31"}, "dewptm": "16", "heatindexi": "-9999", "visi": "19", "pressurem": "1014", "metar": "AAXX 31031 12566 41980 62804 10168 20155 39860 40144 53003 70182 83032 333 91205", "thunder": "0", "windchilli": "-999", "fog": "0", "wdird": "280", "snow": "0", "wspdm": "14.4", "vism": "30", "icon": "partlycloudy", "utcdate": {"year": "2017", "mon": "05", "min": "00", "hour": "03", "pretty": "3:00 AM GMT on May 31, 2017", "tzname": "UTC", "mday": "31"}, "wspdi": "8.9", "dewpti": "60", "windchillm": "-999", "wdire": "West", "tempi": "62", "wgustm": "", "pressurei": "29.96", "tempm": "17", "precipm": "", "hail": "0", "hum": "90", "precipi": "", "conds": "Partly Cloudy", "wgusti": "", "heatindexm": "-9999", "tornado": "0"}, {"rain": "0", "date": {"year": "2017", "mon": "05", "min": "00", "hour": "05", "pretty": "5:00 AM CEST on May 31, 2017", "tzname": "Europe/Warsaw", "mday": "31"}, "dewptm": "15.0", "heatindexi": "-9999", "visi": "-9999.0", "pressurem": "1014", "metar": "METAR EPKK 310300Z 28006KT CAVOK 17/15 Q1014", "thunder": "0", "windchilli": "-999", "fog": "0", "wdird": "280", "snow": "0", "wspdm": "11.1", "vism": "-9999.0", "icon": "clear", "utcdate": {"year": "2017", "mon": "05", "min": "00", "hour": "03", "pretty": "3:00 AM GMT on May 31, 2017", "tzname": "UTC", "mday": "31"}, "wspdi": "6.9", "dewpti": "59.0", "windchillm": "-999", "wdire": "West", "tempi": "62.6", "wgustm": "-9999.0", "pressurei": "29.95", "tempm": "17.0", "precipm": "-9999.00", "hail": "0", "hum": "88", "precipi": "-9999.00", "conds": "Clear", "wgusti": "-9999.0", "heatindexm": "-9999", "tornado": "0"}, {"rain": "0", "date": {"year": "2017", "mon": "05", "min": "30", "hour": "05", "pretty": "5:30 AM CEST on May 31, 2017", "tzname": "Europe/Warsaw", "mday": "31"}, "dewptm": "16.0", "heatindexi": "-9999", "visi": "-9999.0", "pressurem": "1014", "metar": "METAR EPKK 310330Z 28007KT CAVOK 17/16 Q1014", "thunder": "0", "windchilli": "-999", "fog": "0", "wdird": "280", "snow": "0", "wspdm": "13.0", "vism": "-9999.0", "icon": "clear", "utcdate": {"year": "2017", "mon": "05", "min": "30", "hour": "03", "pretty": "3:30 AM GMT on May 31, 2017", "tzname": "UTC", "mday": "31"}, "wspdi": "8.1", "dewpti": "60.8", "windchillm": "-999", "wdire": "West", "tempi": "62.6", "wgustm": "-9999.0", "pressurei": "29.95", "tempm": "17.0", "precipm": "-9999.00", "hail": "0", "hum": "94", "precipi": "-9999.00", "conds": "Clear", "wgusti": "-9999.0", "heatindexm": "-9999", "tornado": "0"}, {"rain": "0", "date": {"year": "2017", "mon": "05", "min": "00", "hour": "06", "pretty": "6:00 AM CEST on May 31, 2017", "tzname": "Europe/Warsaw", "mday": "31"}, "dewptm": "16", "heatindexi": "-9999", "visi": "25", "pressurem": "1015", "metar": "AAXX 31041 12566 42982 72703 10176 20158 39864 40148 53008 84052 333 91204 555 90005", "thunder": "0", "windchilli": "-999", "fog": "0", "wdird": "270", "snow": "0", "wspdm": "10.8", "vism": "40", "icon": "partlycloudy", "utcdate": {"year": "2017", "mon": "05", "min": "00", "hour": "04", "pretty": "4:00 AM GMT on May 31, 2017", "tzname": "UTC", "mday": "31"}, "wspdi": "6.7", "dewpti": "60", "windchillm": "-999", "wdire": "West", "tempi": "64", "wgustm": "", "pressurei": "29.97", "tempm": "18", "precipm": "", "hail": "0", "hum": "84", "precipi": "", "conds": "Partly Cloudy", "wgusti": "", "heatindexm": "-9999", "tornado": "0"}, {"rain": "0", "date": {"year": "2017", "mon": "05", "min": "00", "hour": "06", "pretty": "6:00 AM CEST on May 31, 2017", "tzname": "Europe/Warsaw", "mday": "31"}, "dewptm": "16.0", "heatindexi": "-9999", "visi": "-9999.0", "pressurem": "1014", "metar": "METAR EPKK 310400Z 28006KT CAVOK 18/16 Q1014", "thunder": "0", "windchilli": "-999", "fog": "0", "wdird": "280", "snow": "0", "wspdm": "11.1", "vism": "-9999.0", "icon": "clear", "utcdate": {"year": "2017", "mon": "05", "min": "00", "hour": "04", "pretty": "4:00 AM GMT on May 31, 2017", "tzname": "UTC", "mday": "31"}, "wspdi": "6.9", "dewpti": "60.8", "windchillm": "-999", "wdire": "West", "tempi": "64.4", "wgustm": "-9999.0", "pressurei": "29.95", "tempm": "18.0", "precipm": "-9999.00", "hail": "0", "hum": "88", "precipi": "-9999.00", "conds": "Clear", "wgusti": "-9999.0", "heatindexm": "-9999", "tornado": "0"}, {"rain": "0", "date": {"year": "2017", "mon": "05", "min": "30", "hour": "06", "pretty": "6:30 AM CEST on May 31, 2017", "tzname": "Europe/Warsaw", "mday": "31"}, "dewptm": "16.0", "heatindexi": "-9999", "visi": "-9999.0", "pressurem": "1015", "metar": "METAR EPKK 310430Z 26006KT 230V290 CAVOK 18/16 Q1015", "thunder": "0", "windchilli": "-999", "fog": "0", "wdird": "260", "snow": "0", "wspdm": "11.1", "vism": "-9999.0", "icon": "clear", "utcdate": {"year": "2017", "mon": "05", "min": "30", "hour": "04", "pretty": "4:30 AM GMT on May 31, 2017", "tzname": "UTC", "mday": "31"}, "wspdi": "6.9", "dewpti": "60.8", "windchillm": "-999", "wdire": "West", "tempi": "64.4", "wgustm": "-9999.0", "pressurei": "29.98", "tempm": "18.0", "precipm": "-9999.00", "hail": "0", "hum": "88", "precipi": "-9999.00", "conds": "Clear", "wgusti": "-9999.0", "heatindexm": "-9999", "tornado": "0"}, {"rain": "0", "date": {"year": "2017", "mon": "05", "min": "00", "hour": "07", "pretty": "7:00 AM CEST on May 31, 2017", "tzname": "Europe/Warsaw", "mday": "31"}, "dewptm": "16", "heatindexi": "-9999", "visi": "25", "pressurem": "1016", "metar": "AAXX 31051 12566 42982 62404 10179 20161 39871 40155 53015 82032 333 91204 555 90005", "thunder": "0", "windchilli": "-999", "fog": "0", "wdird": "240", "snow": "0", "wspdm": "14.4", "vism": "40", "icon": "partlycloudy", "utcdate": {"year": "2017", "mon": "05", "min": "00", "hour": "05", "pretty": "5:00 AM GMT on May 31, 2017", "tzname": "UTC", "mday": "31"}, "wspdi": "8.9", "dewpti": "61", "windchillm": "-999", "wdire": "WSW", "tempi": "64", "wgustm": "", "pressurei": "29.99", "tempm": "18", "precipm": "", "hail": "0", "hum": "87", "precipi": "", "conds": "Scattered Clouds", "wgusti": "", "heatindexm": "-9999", "tornado": "0"}, {"rain": "0", "date": {"year": "2017", "mon": "05", "min": "00", "hour": "07", "pretty": "7:00 AM CEST on May 31, 2017", "tzname": "Europe/Warsaw", "mday": "31"}, "dewptm": "16.0", "heatindexi": "-9999", "visi": "-9999.0", "pressurem": "1015", "metar": "METAR EPKK 310500Z 26007KT CAVOK 18/16 Q1015", "thunder": "0", "windchilli": "-999", "fog": "0", "wdird": "260", "snow": "0", "wspdm": "13.0", "vism": "-9999.0", "icon": "clear", "utcdate": {"year": "2017", "mon": "05", "min": "00", "hour": "05", "pretty": "5:00 AM GMT on May 31, 2017", "tzname": "UTC", "mday": "31"}, "wspdi": "8.1", "dewpti": "60.8", "windchillm": "-999", "wdire": "West", "tempi": "64.4", "wgustm": "-9999.0", "pressurei": "29.98", "tempm": "18.0", "precipm": "-9999.00", "hail": "0", "hum": "88", "precipi": "-9999.00", "conds": "Clear", "wgusti": "-9999.0", "heatindexm": "-9999", "tornado": "0"}, {"rain": "0", "date": {"year": "2017", "mon": "05", "min": "30", "hour": "07", "pretty": "7:30 AM CEST on May 31, 2017", "tzname": "Europe/Warsaw", "mday": "31"}, "dewptm": "16.0", "heatindexi": "-9999", "visi": "-9999.0", "pressurem": "1015", "metar": "METAR EPKK 310530Z 22006KT CAVOK 19/16 Q1015", "thunder": "0", "windchilli": "-999", "fog": "0", "wdird": "220", "snow": "0", "wspdm": "11.1", "vism": "-9999.0", "icon": "clear", "utcdate": {"year": "2017", "mon": "05", "min": "30", "hour": "05", "pretty": "5:30 AM GMT on May 31, 2017", "tzname": "UTC", "mday": "31"}, "wspdi": "6.9", "dewpti": "60.8", "windchillm": "-999", "wdire": "SW", "tempi": "66.2", "wgustm": "-9999.0", "pressurei": "29.98", "tempm": "19.0", "precipm": "-9999.00", "hail": "0", "hum": "83", "precipi": "-9999.00", "conds": "Clear", "wgusti": "-9999.0", "heatindexm": "-9999", "tornado": "0"}, {"rain": "0", "date": {"year": "2017", "mon": "05", "min": "00", "hour": "08", "pretty": "8:00 AM CEST on May 31, 2017", "tzname": "Europe/Warsaw", "mday": "31"}, "dewptm": "16", "heatindexi": "-9999", "visi": "25", "pressurem": "1016", "metar": "AAXX 31061 12566 11982 62506 10192 20164 39876 40159 52016 69972 70182 81032 333 10192 20165 31015 70050 91206 93093", "thunder": "0", "windchilli": "-999", "fog": "0", "wdird": "250", "snow": "0", "wspdm": "21.6", "vism": "40", "icon": "partlycloudy", "utcdate": {"year": "2017", "mon": "05", "min": "00", "hour": "06", "pretty": "6:00 AM GMT on May 31, 2017", "tzname": "UTC", "mday": "31"}, "wspdi": "13.4", "dewpti": "62", "windchillm": "-999", "wdire": "WSW", "tempi": "67", "wgustm": "", "pressurei": "30.00", "tempm": "19", "precipm": "", "hail": "0", "hum": "77", "precipi": "", "conds": "Partly Cloudy", "wgusti": "", "heatindexm": "-9999", "tornado": "0"}, {"rain": "0", "date": {"year": "2017", "mon": "05", "min": "00", "hour": "08", "pretty": "8:00 AM CEST on May 31, 2017", "tzname": "Europe/Warsaw", "mday": "31"}, "dewptm": "16.0", "heatindexi": "-9999", "visi": "-9999.0", "pressurem": "1016", "metar": "METAR EPKK 310600Z 24010KT CAVOK 19/16 Q1016", "thunder": "0", "windchilli": "-999", "fog": "0", "wdird": "240", "snow": "0", "wspdm": "18.5", "vism": "-9999.0", "icon": "clear", "utcdate": {"year": "2017", "mon": "05", "min": "00", "hour": "06", "pretty": "6:00 AM GMT on May 31, 2017", "tzname": "UTC", "mday": "31"}, "wspdi": "11.5", "dewpti": "60.8", "windchillm": "-999", "wdire": "WSW", "tempi": "66.2", "wgustm": "-9999.0", "pressurei": "30.01", "tempm": "19.0", "precipm": "-9999.00", "hail": "0", "hum": "83", "precipi": "-9999.00", "conds": "Clear", "wgusti": "-9999.0", "heatindexm": "-9999", "tornado": "0"}, {"rain": "0", "date": {"year": "2017", "mon": "05", "min": "30", "hour": "08", "pretty": "8:30 AM CEST on May 31, 2017", "tzname": "Europe/Warsaw", "mday": "31"}, "dewptm": "16.0", "heatindexi": "-9999", "visi": "6.2", "pressurem": "1016", "metar": "METAR EPKK 310630Z 25012KT 9999 FEW018 20/16 Q1016", "thunder": "0", "windchilli": "-999", "fog": "0", "wdird": "250", "snow": "0", "wspdm": "22.2", "vism": "10.0", "icon": "partlycloudy", "utcdate": {"year": "2017", "mon": "05", "min": "30", "hour": "06", "pretty": "6:30 AM GMT on May 31, 2017", "tzname": "UTC", "mday": "31"}, "wspdi": "13.8", "dewpti": "60.8", "windchillm": "-999", "wdire": "WSW", "tempi": "68.0", "wgustm": "-9999.0", "pressurei": "30.01", "tempm": "20.0", "precipm": "-9999.00", "hail": "0", "hum": "78", "precipi": "-9999.00", "conds": "Partly Cloudy", "wgusti": "-9999.0", "heatindexm": "-9999", "tornado": "0"}, {"rain": "0", "date": {"year": "2017", "mon": "05", "min": "00", "hour": "09", "pretty": "9:00 AM CEST on May 31, 2017", "tzname": "Europe/Warsaw", "mday": "31"}, "dewptm": "17", "heatindexi": "-9999", "visi": "25", "pressurem": "1016", "metar": "AAXX 31071 12566 42582 52705 10205 20167 39879 40160 51015 84232 333 91206 555 57036 90005", "thunder": "0", "windchilli": "-999", "fog": "0", "wdird": "270", "snow": "0", "wspdm": "18.0", "vism": "40", "icon": "partlycloudy", "utcdate": {"year": "2017", "mon": "05", "min": "00", "hour": "07", "pretty": "7:00 AM GMT on May 31, 2017", "tzname": "UTC", "mday": "31"}, "wspdi": "11.2", "dewpti": "62", "windchillm": "-999", "wdire": "West", "tempi": "69", "wgustm": "", "pressurei": "30.01", "tempm": "20", "precipm": "", "hail": "0", "hum": "72", "precipi": "", "conds": "Partly Cloudy", "wgusti": "", "heatindexm": "-9999", "tornado": "0"}, {"rain": "0", "date": {"year": "2017", "mon": "05", "min": "00", "hour": "09", "pretty": "9:00 AM CEST on May 31, 2017", "tzname": "Europe/Warsaw", "mday": "31"}, "dewptm": "16.0", "heatindexi": "-9999", "visi": "6.2", "pressurem": "1016", "metar": "METAR EPKK 310700Z 26009KT 9999 SCT020 20/16 Q1016", "thunder": "0", "windchilli": "-999", "fog": "0", "wdird": "260", "snow": "0", "wspdm": "16.7", "vism": "10.0", "icon": "partlycloudy", "utcdate": {"year": "2017", "mon": "05", "min": "00", "hour": "07", "pretty": "7:00 AM GMT on May 31, 2017", "tzname": "UTC", "mday": "31"}, "wspdi": "10.4", "dewpti": "60.8", "windchillm": "-999", "wdire": "West", "tempi": "68.0", "wgustm": "-9999.0", "pressurei": "30.01", "tempm": "20.0", "precipm": "-9999.00", "hail": "0", "hum": "78", "precipi": "-9999.00", "conds": "Scattered Clouds", "wgusti": "-9999.0", "heatindexm": "-9999", "tornado": "0"}, {"rain": "0", "date": {"year": "2017", "mon": "05", "min": "30", "hour": "09", "pretty": "9:30 AM CEST on May 31, 2017", "tzname": "Europe/Warsaw", "mday": "31"}, "dewptm": "17.0", "heatindexi": "-9999", "visi": "6.2", "pressurem": "1016", "metar": "METAR EPKK 310730Z 26014KT 9999 BKN020 20/17 Q1016", "thunder": "0", "windchilli": "-999", "fog": "0", "wdird": "260", "snow": "0", "wspdm": "25.9", "vism": "10.0", "icon": "mostlycloudy", "utcdate": {"year": "2017", "mon": "05", "min": "30", "hour": "07", "pretty": "7:30 AM GMT on May 31, 2017", "tzname": "UTC", "mday": "31"}, "wspdi": "16.1", "dewpti": "62.6", "windchillm": "-999", "wdire": "West", "tempi": "68.0", "wgustm": "-9999.0", "pressurei": "30.01", "tempm": "20.0", "precipm": "-9999.00", "hail": "0", "hum": "83", "precipi": "-9999.00", "conds": "Mostly Cloudy", "wgusti": "-9999.0", "heatindexm": "-9999", "tornado": "0"}, {"rain": "0", "date": {"year": "2017", "mon": "05", "min": "00", "hour": "10", "pretty": "10:00 AM CEST on May 31, 2017", "tzname": "Europe/Warsaw", "mday": "31"}, "dewptm": "17", "heatindexi": "-9999", "visi": "16", "pressurem": "1016", "metar": "AAXX 31081 12566 42575 62606 10211 20169 39882 40163 52011 8525/ 333 91207 555 90005", "thunder": "0", "windchilli": "-999", "fog": "0", "wdird": "260", "snow": "0", "wspdm": "21.6", "vism": "25", "icon": "mostlycloudy", "utcdate": {"year": "2017", "mon": "05", "min": "00", "hour": "08", "pretty": "8:00 AM GMT on May 31, 2017", "tzname": "UTC", "mday": "31"}, "wspdi": "13.4", "dewpti": "62", "windchillm": "-999", "wdire": "West", "tempi": "70", "wgustm": "", "pressurei": "30.01", "tempm": "21", "precipm": "", "hail": "0", "hum": "70", "precipi": "", "conds": "Mostly Cloudy", "wgusti": "", "heatindexm": "-9999", "tornado": "0"}, {"rain": "0", "date": {"year": "2017", "mon": "05", "min": "00", "hour": "10", "pretty": "10:00 AM CEST on May 31, 2017", "tzname": "Europe/Warsaw", "mday": "31"}, "dewptm": "17.0", "heatindexi": "-9999", "visi": "6.2", "pressurem": "1016", "metar": "METAR EPKK 310800Z 25014KT 9999 BKN020 21/17 Q1016", "thunder": "0", "windchilli": "-999", "fog": "0", "wdird": "250", "snow": "0", "wspdm": "25.9", "vism": "10.0", "icon": "mostlycloudy", "utcdate": {"year": "2017", "mon": "05", "min": "00", "hour": "08", "pretty": "8:00 AM GMT on May 31, 2017", "tzname": "UTC", "mday": "31"}, "wspdi": "16.1", "dewpti": "62.6", "windchillm": "-999", "wdire": "WSW", "tempi": "69.8", "wgustm": "-9999.0", "pressurei": "30.01", "tempm": "21.0", "precipm": "-9999.00", "hail": "0", "hum": "78", "precipi": "-9999.00", "conds": "Mostly Cloudy", "wgusti": "-9999.0", "heatindexm": "-9999", "tornado": "0"}, {"rain": "0", "date": {"year": "2017", "mon": "05", "min": "30", "hour": "10", "pretty": "10:30 AM CEST on May 31, 2017", "tzname": "Europe/Warsaw", "mday": "31"}, "dewptm": "16.0", "heatindexi": "-9999", "visi": "6.2", "pressurem": "1017", "metar": "METAR EPKK 310830Z 29015KT 9999 BKN020 21/16 Q1017", "thunder": "0", "windchilli": "-999", "fog": "0", "wdird": "290", "snow": "0", "wspdm": "27.8", "vism": "10.0", "icon": "mostlycloudy", "utcdate": {"year": "2017", "mon": "05", "min": "30", "hour": "08", "pretty": "8:30 AM GMT on May 31, 2017", "tzname": "UTC", "mday": "31"}, "wspdi": "17.3", "dewpti": "60.8", "windchillm": "-999", "wdire": "WNW", "tempi": "69.8", "wgustm": "-9999.0", "pressurei": "30.04", "tempm": "21.0", "precipm": "-9999.00", "hail": "0", "hum": "73", "precipi": "-9999.00", "conds": "Mostly Cloudy", "wgusti": "-9999.0", "heatindexm": "-9999", "tornado": "0"}, {"rain": "0", "date": {"year": "2017", "mon": "05", "min": "00", "hour": "11", "pretty": "11:00 AM CEST on May 31, 2017", "tzname": "Europe/Warsaw", "mday": "31"}, "dewptm": "17", "heatindexi": "-9999", "visi": "12", "pressurem": "1017", "metar": "AAXX 31091 12566 42570 72807 10219 20166 39888 40168 53012 878// 333 91208", "thunder": "0", "windchilli": "-999", "fog": "0", "wdird": "280", "snow": "0", "wspdm": "25.2", "vism": "20", "icon": "mostlycloudy", "utcdate": {"year": "2017", "mon": "05", "min": "00", "hour": "09", "pretty": "9:00 AM GMT on May 31, 2017", "tzname": "UTC", "mday": "31"}, "wspdi": "15.7", "dewpti": "62", "windchillm": "-999", "wdire": "West", "tempi": "71", "wgustm": "", "pressurei": "30.03", "tempm": "22", "precipm": "", "hail": "0", "hum": "65", "precipi": "", "conds": "Mostly Cloudy", "wgusti": "", "heatindexm": "-9999", "tornado": "0"}, {"rain": "0", "date": {"year": "2017", "mon": "05", "min": "00", "hour": "11", "pretty": "11:00 AM CEST on May 31, 2017", "tzname": "Europe/Warsaw", "mday": "31"}, "dewptm": "16.0", "heatindexi": "-9999", "visi": "6.2", "pressurem": "1017", "metar": "METAR EPKK 310900Z 29010KT 260V320 9999 BKN023 22/16 Q1017", "thunder": "0", "windchilli": "-999", "fog": "0", "wdird": "290", "snow": "0", "wspdm": "18.5", "vism": "10.0", "icon": "mostlycloudy", "utcdate": {"year": "2017", "mon": "05", "min": "00", "hour": "09", "pretty": "9:00 AM GMT on May 31, 2017", "tzname": "UTC", "mday": "31"}, "wspdi": "11.5", "dewpti": "60.8", "windchillm": "-999", "wdire": "WNW", "tempi": "71.6", "wgustm": "-9999.0", "pressurei": "30.04", "tempm": "22.0", "precipm": "-9999.00", "hail": "0", "hum": "69", "precipi": "-9999.00", "conds": "Mostly Cloudy", "wgusti": "-9999.0", "heatindexm": "-9999", "tornado": "0"}, {"rain": "1", "date": {"year": "2017", "mon": "05", "min": "30", "hour": "11", "pretty": "11:30 AM CEST on May 31, 2017", "tzname": "Europe/Warsaw", "mday": "31"}, "dewptm": "16.0", "heatindexi": "-9999", "visi": "6.2", "pressurem": "1017", "metar": "METAR EPKK 310930Z 29014KT 9999 -SHRA SCT020CB SCT040 21/16 Q1017", "thunder": "0", "windchilli": "-999", "fog": "0", "wdird": "290", "snow": "0", "wspdm": "25.9", "vism": "10.0", "icon": "rain", "utcdate": {"year": "2017", "mon": "05", "min": "30", "hour": "09", "pretty": "9:30 AM GMT on May 31, 2017", "tzname": "UTC", "mday": "31"}, "wspdi": "16.1", "dewpti": "60.8", "windchillm": "-999", "wdire": "WNW", "tempi": "69.8", "wgustm": "-9999.0", "pressurei": "30.04", "tempm": "21.0", "precipm": "-9999.00", "hail": "0", "hum": "73", "precipi": "-9999.00", "conds": "Light Rain Showers", "wgusti": "-9999.0", "heatindexm": "-9999", "tornado": "0"}, {"rain": "1", "date": {"year": "2017", "mon": "05", "min": "00", "hour": "12", "pretty": "12:00 PM CEST on May 31, 2017", "tzname": "Europe/Warsaw", "mday": "31"}, "dewptm": "16", "heatindexi": "-9999", "visi": "9", "pressurem": "1017", "metar": "AAXX 31101 12566 41565 72805 10202 20164 39891 40173 52012 78022 878// 333 91207 555 90005", "thunder": "0", "windchilli": "-999", "fog": "0", "wdird": "280", "snow": "0", "wspdm": "18.0", "vism": "15", "icon": "rain", "utcdate": {"year": "2017", "mon": "05", "min": "00", "hour": "10", "pretty": "10:00 AM GMT on May 31, 2017", "tzname": "UTC", "mday": "31"}, "wspdi": "11.2", "dewpti": "62", "windchillm": "-999", "wdire": "West", "tempi": "68", "wgustm": "", "pressurei": "30.04", "tempm": "20", "precipm": "", "hail": "0", "hum": "74", "precipi": "", "conds": "Light Rain Showers", "wgusti": "", "heatindexm": "-9999", "tornado": "0"}, {"rain": "1", "date": {"year": "2017", "mon": "05", "min": "00", "hour": "12", "pretty": "12:00 PM CEST on May 31, 2017", "tzname": "Europe/Warsaw", "mday": "31"}, "dewptm": "16.0", "heatindexi": "-9999", "visi": "6.2", "pressurem": "1017", "metar": "METAR EPKK 311000Z 29009KT 9999 -SHRA SCT023TCU BKN030 20/16 Q1017", "thunder": "0", "windchilli": "-999", "fog": "0", "wdird": "290", "snow": "0", "wspdm": "16.7", "vism": "10.0", "icon": "rain", "utcdate": {"year": "2017", "mon": "05", "min": "00", "hour": "10", "pretty": "10:00 AM GMT on May 31, 2017", "tzname": "UTC", "mday": "31"}, "wspdi": "10.4", "dewpti": "60.8", "windchillm": "-999", "wdire": "WNW", "tempi": "68.0", "wgustm": "-9999.0", "pressurei": "30.04", "tempm": "20.0", "precipm": "-9999.00", "hail": "0", "hum": "78", "precipi": "-9999.00", "conds": "Light Rain Showers", "wgusti": "-9999.0", "heatindexm": "-9999", "tornado": "0"}, {"rain": "0", "date": {"year": "2017", "mon": "05", "min": "30", "hour": "12", "pretty": "12:30 PM CEST on May 31, 2017", "tzname": "Europe/Warsaw", "mday": "31"}, "dewptm": "15.0", "heatindexi": "-9999", "visi": "6.2", "pressurem": "1017", "metar": "METAR EPKK 311030Z 29012KT 260V320 9999 SCT023 21/15 Q1017", "thunder": "0", "windchilli": "-999", "fog": "0", "wdird": "290", "snow": "0", "wspdm": "22.2", "vism": "10.0", "icon": "partlycloudy", "utcdate": {"year": "2017", "mon": "05", "min": "30", "hour": "10", "pretty": "10:30 AM GMT on May 31, 2017", "tzname": "UTC", "mday": "31"}, "wspdi": "13.8", "dewpti": "59.0", "windchillm": "-999", "wdire": "WNW", "tempi": "69.8", "wgustm": "-9999.0", "pressurei": "30.04", "tempm": "21.0", "precipm": "-9999.00", "hail": "0", "hum": "68", "precipi": "-9999.00", "conds": "Scattered Clouds", "wgusti": "-9999.0", "heatindexm": "-9999", "tornado": "0"}, {"rain": "1", "date": {"year": "2017", "mon": "05", "min": "00", "hour": "13", "pretty": "1:00 PM CEST on May 31, 2017", "tzname": "Europe/Warsaw", "mday": "31"}, "dewptm": "15", "heatindexi": "-9999", "visi": "22", "pressurem": "1016", "metar": "AAXX 31111 12566 41581 52607 10227 20153 39886 40165 50004 72522 82232 333 91111 91207 555 90005", "thunder": "0", "windchilli": "-999", "fog": "0", "wdird": "260", "snow": "0", "wspdm": "25.2", "vism": "35", "icon": "rain", "utcdate": {"year": "2017", "mon": "05", "min": "00", "hour": "11", "pretty": "11:00 AM GMT on May 31, 2017", "tzname": "UTC", "mday": "31"}, "wspdi": "15.7", "dewpti": "60", "windchillm": "-999", "wdire": "West", "tempi": "73", "wgustm": "", "pressurei": "30.02", "tempm": "23", "precipm": "", "hail": "0", "hum": "54", "precipi": "", "conds": "Light Rain Showers", "wgusti": "", "heatindexm": "-9999", "tornado": "0"}, {"rain": "0", "date": {"year": "2017", "mon": "05", "min": "00", "hour": "13", "pretty": "1:00 PM CEST on May 31, 2017", "tzname": "Europe/Warsaw", "mday": "31"}, "dewptm": "15.0", "heatindexi": "-9999", "visi": "6.2", "pressurem": "1017", "metar": "METAR EPKK 311100Z 26011G21KT 230V290 9999 SCT030 23/15 Q1017", "thunder": "0", "windchilli": "-999", "fog": "0", "wdird": "260", "snow": "0", "wspdm": "20.4", "vism": "10.0", "icon": "partlycloudy", "utcdate": {"year": "2017", "mon": "05", "min": "00", "hour": "11", "pretty": "11:00 AM GMT on May 31, 2017", "tzname": "UTC", "mday": "31"}, "wspdi": "12.7", "dewpti": "59.0", "windchillm": "-999", "wdire": "West", "tempi": "73.4", "wgustm": "38.9", "pressurei": "30.04", "tempm": "23.0", "precipm": "-9999.00", "hail": "0", "hum": "61", "precipi": "-9999.00", "conds": "Scattered Clouds", "wgusti": "24.2", "heatindexm": "-9999", "tornado": "0"}, {"rain": "0", "date": {"year": "2017", "mon": "05", "min": "30", "hour": "13", "pretty": "1:30 PM CEST on May 31, 2017", "tzname": "Europe/Warsaw", "mday": "31"}, "dewptm": "14.0", "heatindexi": "-9999", "visi": "6.2", "pressurem": "1017", "metar": "METAR EPKK 311130Z 27012KT 240V300 9999 FEW030TCU SCT066 23/14 Q1017", "thunder": "0", "windchilli": "-999", "fog": "0", "wdird": "270", "snow": "0", "wspdm": "22.2", "vism": "10.0", "icon": "partlycloudy", "utcdate": {"year": "2017", "mon": "05", "min": "30", "hour": "11", "pretty": "11:30 AM GMT on May 31, 2017", "tzname": "UTC", "mday": "31"}, "wspdi": "13.8", "dewpti": "57.2", "windchillm": "-999", "wdire": "West", "tempi": "73.4", "wgustm": "-9999.0", "pressurei": "30.04", "tempm": "23.0", "precipm": "-9999.00", "hail": "0", "hum": "57", "precipi": "-9999.00", "conds": "Scattered Clouds", "wgusti": "-9999.0", "heatindexm": "-9999", "tornado": "0"}, {"rain": "0", "date": {"year": "2017", "mon": "05", "min": "00", "hour": "14", "pretty": "2:00 PM CEST on May 31, 2017", "tzname": "Europe/Warsaw", "mday": "31"}, "dewptm": "14", "heatindexi": "-9999", "visi": "25", "pressurem": "1016", "metar": "AAXX 31121 12566 11682 62908 10227 20143 39886 40165 56002 69911 70382 85832 333 91112 91208 93091", "thunder": "0", "windchilli": "-999", "fog": "0", "wdird": "290", "snow": "0", "wspdm": "28.8", "vism": "40", "icon": "partlycloudy", "utcdate": {"year": "2017", "mon": "05", "min": "00", "hour": "12", "pretty": "12:00 PM GMT on May 31, 2017", "tzname": "UTC", "mday": "31"}, "wspdi": "17.9", "dewpti": "58", "windchillm": "-999", "wdire": "WNW", "tempi": "73", "wgustm": "", "pressurei": "30.02", "tempm": "23", "precipm": "", "hail": "0", "hum": "49", "precipi": "", "conds": "Partly Cloudy", "wgusti": "", "heatindexm": "-9999", "tornado": "0"}, {"rain": "0", "date": {"year": "2017", "mon": "05", "min": "00", "hour": "14", "pretty": "2:00 PM CEST on May 31, 2017", "tzname": "Europe/Warsaw", "mday": "31"}, "dewptm": "14.0", "heatindexi": "-9999", "visi": "6.2", "pressurem": "1017", "metar": "METAR EPKK 311200Z 29015KT 250V320 9999 SCT036TCU BKN053 23/14 Q1017", "thunder": "0", "windchilli": "-999", "fog": "0", "wdird": "290", "snow": "0", "wspdm": "27.8", "vism": "10.0", "icon": "mostlycloudy", "utcdate": {"year": "2017", "mon": "05", "min": "00", "hour": "12", "pretty": "12:00 PM GMT on May 31, 2017", "tzname": "UTC", "mday": "31"}, "wspdi": "17.3", "dewpti": "57.2", "windchillm": "-999", "wdire": "WNW", "tempi": "73.4", "wgustm": "-9999.0", "pressurei": "30.04", "tempm": "23.0", "precipm": "-9999.00", "hail": "0", "hum": "57", "precipi": "-9999.00", "conds": "Mostly Cloudy", "wgusti": "-9999.0", "heatindexm": "-9999", "tornado": "0"}, {"rain": "0", "date": {"year": "2017", "mon": "05", "min": "30", "hour": "14", "pretty": "2:30 PM CEST on May 31, 2017", "tzname": "Europe/Warsaw", "mday": "31"}, "dewptm": "14.0", "heatindexi": "-9999", "visi": "6.2", "pressurem": "1017", "metar": "METAR EPKK 311230Z 25014KT 9999 FEW038TCU SCT062 24/14 Q1017", "thunder": "0", "windchilli": "-999", "fog": "0", "wdird": "250", "snow": "0", "wspdm": "25.9", "vism": "10.0", "icon": "partlycloudy", "utcdate": {"year": "2017", "mon": "05", "min": "30", "hour": "12", "pretty": "12:30 PM GMT on May 31, 2017", "tzname": "UTC", "mday": "31"}, "wspdi": "16.1", "dewpti": "57.2", "windchillm": "-999", "wdire": "WSW", "tempi": "75.2", "wgustm": "-9999.0", "pressurei": "30.04", "tempm": "24.0", "precipm": "-9999.00", "hail": "0", "hum": "53", "precipi": "-9999.00", "conds": "Scattered Clouds", "wgusti": "-9999.0", "heatindexm": "-9999", "tornado": "0"}, {"rain": "0", "date": {"year": "2017", "mon": "05", "min": "00", "hour": "15", "pretty": "3:00 PM CEST on May 31, 2017", "tzname": "Europe/Warsaw", "mday": "31"}, "dewptm": "14.0", "heatindexi": "-9999", "visi": "6.2", "pressurem": "1017", "metar": "METAR EPKK 311300Z 28016KT 9999 SCT040 24/14 Q1017", "thunder": "0", "windchilli": "-999", "fog": "0", "wdird": "280", "snow": "0", "wspdm": "29.6", "vism": "10.0", "icon": "partlycloudy", "utcdate": {"year": "2017", "mon": "05", "min": "00", "hour": "13", "pretty": "1:00 PM GMT on May 31, 2017", "tzname": "UTC", "mday": "31"}, "wspdi": "18.4", "dewpti": "57.2", "windchillm": "-999", "wdire": "West", "tempi": "75.2", "wgustm": "-9999.0", "pressurei": "30.04", "tempm": "24.0", "precipm": "-9999.00", "hail": "0", "hum": "53", "precipi": "-9999.00", "conds": "Scattered Clouds", "wgusti": "-9999.0", "heatindexm": "-9999", "tornado": "0"}, {"rain": "0", "date": {"year": "2017", "mon": "05", "min": "30", "hour": "15", "pretty": "3:30 PM CEST on May 31, 2017", "tzname": "Europe/Warsaw", "mday": "31"}, "dewptm": "14.0", "heatindexi": "-9999", "visi": "6.2", "pressurem": "1016", "metar": "METAR EPKK 311330Z 29012KT 260V320 9999 FEW040 SCT050 24/14 Q1016", "thunder": "0", "windchilli": "-999", "fog": "0", "wdird": "290", "snow": "0", "wspdm": "22.2", "vism": "10.0", "icon": "partlycloudy", "utcdate": {"year": "2017", "mon": "05", "min": "30", "hour": "13", "pretty": "1:30 PM GMT on May 31, 2017", "tzname": "UTC", "mday": "31"}, "wspdi": "13.8", "dewpti": "57.2", "windchillm": "-999", "wdire": "WNW", "tempi": "75.2", "wgustm": "-9999.0", "pressurei": "30.01", "tempm": "24.0", "precipm": "-9999.00", "hail": "0", "hum": "53", "precipi": "-9999.00", "conds": "Scattered Clouds", "wgusti": "-9999.0", "heatindexm": "-9999", "tornado": "0"}, {"rain": "0", "date": {"year": "2017", "mon": "05", "min": "00", "hour": "16", "pretty": "4:00 PM CEST on May 31, 2017", "tzname": "Europe/Warsaw", "mday": "31"}, "dewptm": "13", "heatindexi": "-9999", "visi": "25", "pressurem": "1016", "metar": "AAXX 31141 12566 42682 42708 10238 20131 39881 40159 58005 84200 333 91208 555 90005", "thunder": "0", "windchilli": "-999", "fog": "0", "wdird": "270", "snow": "0", "wspdm": "28.8", "vism": "40", "icon": "partlycloudy", "utcdate": {"year": "2017", "mon": "05", "min": "00", "hour": "14", "pretty": "2:00 PM GMT on May 31, 2017", "tzname": "UTC", "mday": "31"}, "wspdi": "17.9", "dewpti": "56", "windchillm": "-999", "wdire": "West", "tempi": "75", "wgustm": "", "pressurei": "30.00", "tempm": "24", "precipm": "", "hail": "0", "hum": "40", "precipi": "", "conds": "Partly Cloudy", "wgusti": "", "heatindexm": "-9999", "tornado": "0"}, {"rain": "0", "date": {"year": "2017", "mon": "05", "min": "00", "hour": "16", "pretty": "4:00 PM CEST on May 31, 2017", "tzname": "Europe/Warsaw", "mday": "31"}, "dewptm": "13.0", "heatindexi": "-9999", "visi": "6.2", "pressurem": "1016", "metar": "METAR EPKK 311400Z 27013KT 240V310 9999 SCT043TCU 24/13 Q1016", "thunder": "0", "windchilli": "-999", "fog": "0", "wdird": "270", "snow": "0", "wspdm": "24.1", "vism": "10.0", "icon": "partlycloudy", "utcdate": {"year": "2017", "mon": "05", "min": "00", "hour": "14", "pretty": "2:00 PM GMT on May 31, 2017", "tzname": "UTC", "mday": "31"}, "wspdi": "15.0", "dewpti": "55.4", "windchillm": "-999", "wdire": "West", "tempi": "75.2", "wgustm": "-9999.0", "pressurei": "30.01", "tempm": "24.0", "precipm": "-9999.00", "hail": "0", "hum": "50", "precipi": "-9999.00", "conds": "Scattered Clouds", "wgusti": "-9999.0", "heatindexm": "-9999", "tornado": "0"}, {"rain": "0", "date": {"year": "2017", "mon": "05", "min": "30", "hour": "16", "pretty": "4:30 PM CEST on May 31, 2017", "tzname": "Europe/Warsaw", "mday": "31"}, "dewptm": "13.0", "heatindexi": "-9999", "visi": "6.2", "pressurem": "1016", "metar": "METAR EPKK 311430Z 30012KT 270V330 9999 FEW043 23/13 Q1016", "thunder": "0", "windchilli": "-999", "fog": "0", "wdird": "300", "snow": "0", "wspdm": "22.2", "vism": "10.0", "icon": "partlycloudy", "utcdate": {"year": "2017", "mon": "05", "min": "30", "hour": "14", "pretty": "2:30 PM GMT on May 31, 2017", "tzname": "UTC", "mday": "31"}, "wspdi": "13.8", "dewpti": "55.4", "windchillm": "-999", "wdire": "WNW", "tempi": "73.4", "wgustm": "-9999.0", "pressurei": "30.01", "tempm": "23.0", "precipm": "-9999.00", "hail": "0", "hum": "53", "precipi": "-9999.00", "conds": "Partly Cloudy", "wgusti": "-9999.0", "heatindexm": "-9999", "tornado": "0"}, {"rain": "0", "date": {"year": "2017", "mon": "05", "min": "00", "hour": "17", "pretty": "5:00 PM CEST on May 31, 2017", "tzname": "Europe/Warsaw", "mday": "31"}, "dewptm": "13", "heatindexi": "-9999", "visi": "25", "pressurem": "1016", "metar": "AAXX 31151 12566 42682 32907 10231 20130 39880 40159 57006 82230 333 91113 91209", "thunder": "0", "windchilli": "-999", "fog": "0", "wdird": "290", "snow": "0", "wspdm": "25.2", "vism": "40", "icon": "partlycloudy", "utcdate": {"year": "2017", "mon": "05", "min": "00", "hour": "15", "pretty": "3:00 PM GMT on May 31, 2017", "tzname": "UTC", "mday": "31"}, "wspdi": "15.7", "dewpti": "55", "windchillm": "-999", "wdire": "WNW", "tempi": "74", "wgustm": "", "pressurei": "30.00", "tempm": "23", "precipm": "", "hail": "0", "hum": "42", "precipi": "", "conds": "Scattered Clouds", "wgusti": "", "heatindexm": "-9999", "tornado": "0"}, {"rain": "0", "date": {"year": "2017", "mon": "05", "min": "00", "hour": "17", "pretty": "5:00 PM CEST on May 31, 2017", "tzname": "Europe/Warsaw", "mday": "31"}, "dewptm": "13.0", "heatindexi": "-9999", "visi": "6.2", "pressurem": "1016", "metar": "METAR EPKK 311500Z 28012KT 250V310 9999 FEW044 24/13 Q1016", "thunder": "0", "windchilli": "-999", "fog": "0", "wdird": "280", "snow": "0", "wspdm": "22.2", "vism": "10.0", "icon": "partlycloudy", "utcdate": {"year": "2017", "mon": "05", "min": "00", "hour": "15", "pretty": "3:00 PM GMT on May 31, 2017", "tzname": "UTC", "mday": "31"}, "wspdi": "13.8", "dewpti": "55.4", "windchillm": "-999", "wdire": "West", "tempi": "75.2", "wgustm": "-9999.0", "pressurei": "30.01", "tempm": "24.0", "precipm": "-9999.00", "hail": "0", "hum": "50", "precipi": "-9999.00", "conds": "Partly Cloudy", "wgusti": "-9999.0", "heatindexm": "-9999", "tornado": "0"}, {"rain": "0", "date": {"year": "2017", "mon": "05", "min": "30", "hour": "17", "pretty": "5:30 PM CEST on May 31, 2017", "tzname": "Europe/Warsaw", "mday": "31"}, "dewptm": "13.0", "heatindexi": "-9999", "visi": "6.2", "pressurem": "1016", "metar": "METAR EPKK 311530Z 28015KT 9999 SCT040 SCT060 23/13 Q1016", "thunder": "0", "windchilli": "-999", "fog": "0", "wdird": "280", "snow": "0", "wspdm": "27.8", "vism": "10.0", "icon": "partlycloudy", "utcdate": {"year": "2017", "mon": "05", "min": "30", "hour": "15", "pretty": "3:30 PM GMT on May 31, 2017", "tzname": "UTC", "mday": "31"}, "wspdi": "17.3", "dewpti": "55.4", "windchillm": "-999", "wdire": "West", "tempi": "73.4", "wgustm": "-9999.0", "pressurei": "30.01", "tempm": "23.0", "precipm": "-9999.00", "hail": "0", "hum": "53", "precipi": "-9999.00", "conds": "Scattered Clouds", "wgusti": "-9999.0", "heatindexm": "-9999", "tornado": "0"}, {"rain": "0", "date": {"year": "2017", "mon": "05", "min": "00", "hour": "18", "pretty": "6:00 PM CEST on May 31, 2017", "tzname": "Europe/Warsaw", "mday": "31"}, "dewptm": "12", "heatindexi": "-9999", "visi": "25", "pressurem": "1016", "metar": "AAXX 31161 12566 42682 32806 10230 20123 39881 40160 55003 82204 333 91208 555 90005", "thunder": "0", "windchilli": "-999", "fog": "0", "wdird": "280", "snow": "0", "wspdm": "21.6", "vism": "40", "icon": "partlycloudy", "utcdate": {"year": "2017", "mon": "05", "min": "00", "hour": "16", "pretty": "4:00 PM GMT on May 31, 2017", "tzname": "UTC", "mday": "31"}, "wspdi": "13.4", "dewpti": "54", "windchillm": "-999", "wdire": "West", "tempi": "73", "wgustm": "", "pressurei": "30.01", "tempm": "23", "precipm": "", "hail": "0", "hum": "41", "precipi": "", "conds": "Scattered Clouds", "wgusti": "", "heatindexm": "-9999", "tornado": "0"}, {"rain": "0", "date": {"year": "2017", "mon": "05", "min": "00", "hour": "18", "pretty": "6:00 PM CEST on May 31, 2017", "tzname": "Europe/Warsaw", "mday": "31"}, "dewptm": "13.0", "heatindexi": "-9999", "visi": "6.2", "pressurem": "1016", "metar": "METAR EPKK 311600Z 28013KT 9999 FEW046 23/13 Q1016", "thunder": "0", "windchilli": "-999", "fog": "0", "wdird": "280", "snow": "0", "wspdm": "24.1", "vism": "10.0", "icon": "partlycloudy", "utcdate": {"year": "2017", "mon": "05", "min": "00", "hour": "16", "pretty": "4:00 PM GMT on May 31, 2017", "tzname": "UTC", "mday": "31"}, "wspdi": "15.0", "dewpti": "55.4", "windchillm": "-999", "wdire": "West", "tempi": "73.4", "wgustm": "-9999.0", "pressurei": "30.01", "tempm": "23.0", "precipm": "-9999.00", "hail": "0", "hum": "53", "precipi": "-9999.00", "conds": "Partly Cloudy", "wgusti": "-9999.0", "heatindexm": "-9999", "tornado": "0"}, {"rain": "0", "date": {"year": "2017", "mon": "05", "min": "30", "hour": "18", "pretty": "6:30 PM CEST on May 31, 2017", "tzname": "Europe/Warsaw", "mday": "31"}, "dewptm": "11.0", "heatindexi": "-9999", "visi": "6.2", "pressurem": "1016", "metar": "METAR EPKK 311630Z 27012KT 9999 FEW046 23/11 Q1016", "thunder": "0", "windchilli": "-999", "fog": "0", "wdird": "270", "snow": "0", "wspdm": "22.2", "vism": "10.0", "icon": "partlycloudy", "utcdate": {"year": "2017", "mon": "05", "min": "30", "hour": "16", "pretty": "4:30 PM GMT on May 31, 2017", "tzname": "UTC", "mday": "31"}, "wspdi": "13.8", "dewpti": "51.8", "windchillm": "-999", "wdire": "West", "tempi": "73.4", "wgustm": "-9999.0", "pressurei": "30.01", "tempm": "23.0", "precipm": "-9999.00", "hail": "0", "hum": "47", "precipi": "-9999.00", "conds": "Partly Cloudy", "wgusti": "-9999.0", "heatindexm": "-9999", "tornado": "0"}, {"rain": "0", "date": {"year": "2017", "mon": "05", "min": "00", "hour": "19", "pretty": "7:00 PM CEST on May 31, 2017", "tzname": "Europe/Warsaw", "mday": "31"}, "dewptm": "12.0", "heatindexi": "-9999", "visi": "6.2", "pressurem": "1016", "metar": "METAR EPKK 311700Z 27011KT 9999 FEW050 22/12 Q1016", "thunder": "0", "windchilli": "-999", "fog": "0", "wdird": "270", "snow": "0", "wspdm": "20.4", "vism": "10.0", "icon": "partlycloudy", "utcdate": {"year": "2017", "mon": "05", "min": "00", "hour": "17", "pretty": "5:00 PM GMT on May 31, 2017", "tzname": "UTC", "mday": "31"}, "wspdi": "12.7", "dewpti": "53.6", "windchillm": "-999", "wdire": "West", "tempi": "71.6", "wgustm": "-9999.0", "pressurei": "30.01", "tempm": "22.0", "precipm": "-9999.00", "hail": "0", "hum": "53", "precipi": "-9999.00", "conds": "Partly Cloudy", "wgusti": "-9999.0", "heatindexm": "-9999", "tornado": "0"}, {"rain": "0", "date": {"year": "2017", "mon": "05", "min": "30", "hour": "19", "pretty": "7:30 PM CEST on May 31, 2017", "tzname": "Europe/Warsaw", "mday": "31"}, "dewptm": "11.0", "heatindexi": "-9999", "visi": "6.2", "pressurem": "1016", "metar": "METAR EPKK 311730Z 28010KT 9999 FEW050 22/11 Q1016", "thunder": "0", "windchilli": "-999", "fog": "0", "wdird": "280", "snow": "0", "wspdm": "18.5", "vism": "10.0", "icon": "partlycloudy", "utcdate": {"year": "2017", "mon": "05", "min": "30", "hour": "17", "pretty": "5:30 PM GMT on May 31, 2017", "tzname": "UTC", "mday": "31"}, "wspdi": "11.5", "dewpti": "51.8", "windchillm": "-999", "wdire": "West", "tempi": "71.6", "wgustm": "-9999.0", "pressurei": "30.01", "tempm": "22.0", "precipm": "-9999.00", "hail": "0", "hum": "50", "precipi": "-9999.00", "conds": "Partly Cloudy", "wgusti": "-9999.0", "heatindexm": "-9999", "tornado": "0"}, {"rain": "0", "date": {"year": "2017", "mon": "05", "min": "00", "hour": "20", "pretty": "8:00 PM CEST on May 31, 2017", "tzname": "Europe/Warsaw", "mday": "31"}, "dewptm": "12", "heatindexi": "-9999", "visi": "25", "pressurem": "1016", "metar": "AAXX 31181 12566 12782 62602 10202 20122 39882 40164 51002 69912 81504 333 10245 20192 91113 91209 93000", "thunder": "0", "windchilli": "-999", "fog": "0", "wdird": "260", "snow": "0", "wspdm": "7.2", "vism": "40", "icon": "partlycloudy", "utcdate": {"year": "2017", "mon": "05", "min": "00", "hour": "18", "pretty": "6:00 PM GMT on May 31, 2017", "tzname": "UTC", "mday": "31"}, "wspdi": "4.5", "dewpti": "54", "windchillm": "-999", "wdire": "West", "tempi": "68", "wgustm": "", "pressurei": "30.02", "tempm": "20", "precipm": "", "hail": "0", "hum": "51", "precipi": "", "conds": "Scattered Clouds", "wgusti": "", "heatindexm": "-9999", "tornado": "0"}, {"rain": "0", "date": {"year": "2017", "mon": "05", "min": "00", "hour": "20", "pretty": "8:00 PM CEST on May 31, 2017", "tzname": "Europe/Warsaw", "mday": "31"}, "dewptm": "12.0", "heatindexi": "-9999", "visi": "6.2", "pressurem": "1016", "metar": "METAR EPKK 311800Z 26005KT 9999 FEW053 20/12 Q1016", "thunder": "0", "windchilli": "-999", "fog": "0", "wdird": "260", "snow": "0", "wspdm": "9.3", "vism": "10.0", "icon": "partlycloudy", "utcdate": {"year": "2017", "mon": "05", "min": "00", "hour": "18", "pretty": "6:00 PM GMT on May 31, 2017", "tzname": "UTC", "mday": "31"}, "wspdi": "5.8", "dewpti": "53.6", "windchillm": "-999", "wdire": "West", "tempi": "68.0", "wgustm": "-9999.0", "pressurei": "30.01", "tempm": "20.0", "precipm": "-9999.00", "hail": "0", "hum": "60", "precipi": "-9999.00", "conds": "Partly Cloudy", "wgusti": "-9999.0", "heatindexm": "-9999", "tornado": "0"}, {"rain": "0", "date": {"year": "2017", "mon": "05", "min": "30", "hour": "20", "pretty": "8:30 PM CEST on May 31, 2017", "tzname": "Europe/Warsaw", "mday": "31"}, "dewptm": "12.0", "heatindexi": "-9999", "visi": "-9999.0", "pressurem": "1017", "metar": "METAR EPKK 311830Z 22005KT CAVOK 19/12 Q1017", "thunder": "0", "windchilli": "-999", "fog": "0", "wdird": "220", "snow": "0", "wspdm": "9.3", "vism": "-9999.0", "icon": "clear", "utcdate": {"year": "2017", "mon": "05", "min": "30", "hour": "18", "pretty": "6:30 PM GMT on May 31, 2017", "tzname": "UTC", "mday": "31"}, "wspdi": "5.8", "dewpti": "53.6", "windchillm": "-999", "wdire": "SW", "tempi": "66.2", "wgustm": "-9999.0", "pressurei": "30.04", "tempm": "19.0", "precipm": "-9999.00", "hail": "0", "hum": "64", "precipi": "-9999.00", "conds": "Clear", "wgusti": "-9999.0", "heatindexm": "-9999", "tornado": "0"}, {"rain": "0", "date": {"year": "2017", "mon": "05", "min": "00", "hour": "21", "pretty": "9:00 PM CEST on May 31, 2017", "tzname": "Europe/Warsaw", "mday": "31"}, "dewptm": "13", "heatindexi": "-9999", "visi": "25", "pressurem": "1017", "metar": "AAXX 31191 12566 42982 42702 10177 20126 39889 40173 53008 80001 333 91202 555 57094 90005", "thunder": "0", "windchilli": "-999", "fog": "0", "wdird": "270", "snow": "0", "wspdm": "7.2", "vism": "40", "icon": "clear", "utcdate": {"year": "2017", "mon": "05", "min": "00", "hour": "19", "pretty": "7:00 PM GMT on May 31, 2017", "tzname": "UTC", "mday": "31"}, "wspdi": "4.5", "dewpti": "55", "windchillm": "-999", "wdire": "West", "tempi": "64", "wgustm": "", "pressurei": "30.04", "tempm": "18", "precipm": "", "hail": "0", "hum": "64", "precipi": "", "conds": "Clear", "wgusti": "", "heatindexm": "-9999", "tornado": "0"}, {"rain": "0", "date": {"year": "2017", "mon": "05", "min": "00", "hour": "21", "pretty": "9:00 PM CEST on May 31, 2017", "tzname": "Europe/Warsaw", "mday": "31"}, "dewptm": "12.0", "heatindexi": "-9999", "visi": "-9999.0", "pressurem": "1017", "metar": "METAR EPKK 311900Z 30003KT 270V350 CAVOK 18/12 Q1017", "thunder": "0", "windchilli": "-999", "fog": "0", "wdird": "300", "snow": "0", "wspdm": "5.6", "vism": "-9999.0", "icon": "clear", "utcdate": {"year": "2017", "mon": "05", "min": "00", "hour": "19", "pretty": "7:00 PM GMT on May 31, 2017", "tzname": "UTC", "mday": "31"}, "wspdi": "3.5", "dewpti": "53.6", "windchillm": "-999", "wdire": "WNW", "tempi": "64.4", "wgustm": "-9999.0", "pressurei": "30.04", "tempm": "18.0", "precipm": "-9999.00", "hail": "0", "hum": "68", "precipi": "-9999.00", "conds": "Clear", "wgusti": "-9999.0", "heatindexm": "-9999", "tornado": "0"}, {"rain": "0", "date": {"year": "2017", "mon": "05", "min": "30", "hour": "21", "pretty": "9:30 PM CEST on May 31, 2017", "tzname": "Europe/Warsaw", "mday": "31"}, "dewptm": "12.0", "heatindexi": "-9999", "visi": "-9999.0", "pressurem": "1017", "metar": "METAR EPKK 311930Z VRB01KT CAVOK 17/12 Q1017", "thunder": "0", "windchilli": "-999", "fog": "0", "wdird": "0", "snow": "0", "wspdm": "1.9", "vism": "-9999.0", "icon": "clear", "utcdate": {"year": "2017", "mon": "05", "min": "30", "hour": "19", "pretty": "7:30 PM GMT on May 31, 2017", "tzname": "UTC", "mday": "31"}, "wspdi": "1.2", "dewpti": "53.6", "windchillm": "-999", "wdire": "Variable", "tempi": "62.6", "wgustm": "-9999.0", "pressurei": "30.04", "tempm": "17.0", "precipm": "-9999.00", "hail": "0", "hum": "72", "precipi": "-9999.00", "conds": "Clear", "wgusti": "-9999.0", "heatindexm": "-9999", "tornado": "0"}, {"rain": "0", "date": {"year": "2017", "mon": "05", "min": "00", "hour": "22", "pretty": "10:00 PM CEST on May 31, 2017", "tzname": "Europe/Warsaw", "mday": "31"}, "dewptm": "12", "heatindexi": "-9999", "visi": "19", "pressurem": "1018", "metar": "AAXX 31201 12566 42980 22401 10162 20120 39895 40181 53013 80001 333 91202 555 0//// 1//// 2//// 30150 90005", "thunder": "0", "windchilli": "-999", "fog": "0", "wdird": "240", "snow": "0", "wspdm": "3.6", "vism": "30", "icon": "clear", "utcdate": {"year": "2017", "mon": "05", "min": "00", "hour": "20", "pretty": "8:00 PM GMT on May 31, 2017", "tzname": "UTC", "mday": "31"}, "wspdi": "2.2", "dewpti": "54", "windchillm": "-999", "wdire": "WSW", "tempi": "61", "wgustm": "", "pressurei": "30.07", "tempm": "16", "precipm": "", "hail": "0", "hum": "70", "precipi": "", "conds": "Clear", "wgusti": "", "heatindexm": "-9999", "tornado": "0"}, {"rain": "0", "date": {"year": "2017", "mon": "05", "min": "00", "hour": "22", "pretty": "10:00 PM CEST on May 31, 2017", "tzname": "Europe/Warsaw", "mday": "31"}, "dewptm": "12.0", "heatindexi": "-9999", "visi": "-9999.0", "pressurem": "1018", "metar": "METAR EPKK 312000Z VRB02KT CAVOK 16/12 Q1018", "thunder": "0", "windchilli": "-999", "fog": "0", "wdird": "0", "snow": "0", "wspdm": "3.7", "vism": "-9999.0", "icon": "clear", "utcdate": {"year": "2017", "mon": "05", "min": "00", "hour": "20", "pretty": "8:00 PM GMT on May 31, 2017", "tzname": "UTC", "mday": "31"}, "wspdi": "2.3", "dewpti": "53.6", "windchillm": "-999", "wdire": "Variable", "tempi": "60.8", "wgustm": "-9999.0", "pressurei": "30.06", "tempm": "16.0", "precipm": "-9999.00", "hail": "0", "hum": "77", "precipi": "-9999.00", "conds": "Clear", "wgusti": "-9999.0", "heatindexm": "-9999", "tornado": "0"}, {"rain": "0", "date": {"year": "2017", "mon": "05", "min": "30", "hour": "22", "pretty": "10:30 PM CEST on May 31, 2017", "tzname": "Europe/Warsaw", "mday": "31"}, "dewptm": "11.0", "heatindexi": "-9999", "visi": "-9999.0", "pressurem": "1018", "metar": "METAR EPKK 312030Z 27005KT CAVOK 15/11 Q1018", "thunder": "0", "windchilli": "-999", "fog": "0", "wdird": "270", "snow": "0", "wspdm": "9.3", "vism": "-9999.0", "icon": "clear", "utcdate": {"year": "2017", "mon": "05", "min": "30", "hour": "20", "pretty": "8:30 PM GMT on May 31, 2017", "tzname": "UTC", "mday": "31"}, "wspdi": "5.8", "dewpti": "51.8", "windchillm": "-999", "wdire": "West", "tempi": "59.0", "wgustm": "-9999.0", "pressurei": "30.06", "tempm": "15.0", "precipm": "-9999.00", "hail": "0", "hum": "77", "precipi": "-9999.00", "conds": "Clear", "wgusti": "-9999.0", "heatindexm": "-9999", "tornado": "0"}, {"rain": "0", "date": {"year": "2017", "mon": "05", "min": "00", "hour": "23", "pretty": "11:00 PM CEST on May 31, 2017", "tzname": "Europe/Warsaw", "mday": "31"}, "dewptm": "11", "heatindexi": "-9999", "visi": "19", "pressurem": "1018", "metar": "AAXX 31211 12566 42980 02802 10143 20109 39894 40182 50012 333 91203", "thunder": "0", "windchilli": "-999", "fog": "0", "wdird": "280", "snow": "0", "wspdm": "7.2", "vism": "30", "icon": "", "utcdate": {"year": "2017", "mon": "05", "min": "00", "hour": "21", "pretty": "9:00 PM GMT on May 31, 2017", "tzname": "UTC", "mday": "31"}, "wspdi": "4.5", "dewpti": "52", "windchillm": "-999", "wdire": "West", "tempi": "58", "wgustm": "", "pressurei": "30.07", "tempm": "14", "precipm": "", "hail": "0", "hum": "73", "precipi": "", "conds": "", "wgusti": "", "heatindexm": "-9999", "tornado": "0"}, {"rain": "0", "date": {"year": "2017", "mon": "05", "min": "00", "hour": "23", "pretty": "11:00 PM CEST on May 31, 2017", "tzname": "Europe/Warsaw", "mday": "31"}, "dewptm": "11.0", "heatindexi": "-9999", "visi": "-9999.0", "pressurem": "1018", "metar": "METAR EPKK 312100Z 28006KT CAVOK 14/11 Q1018", "thunder": "0", "windchilli": "-999", "fog": "0", "wdird": "280", "snow": "0", "wspdm": "11.1", "vism": "-9999.0", "icon": "clear", "utcdate": {"year": "2017", "mon": "05", "min": "00", "hour": "21", "pretty": "9:00 PM GMT on May 31, 2017", "tzname": "UTC", "mday": "31"}, "wspdi": "6.9", "dewpti": "51.8", "windchillm": "-999", "wdire": "West", "tempi": "57.2", "wgustm": "-9999.0", "pressurei": "30.06", "tempm": "14.0", "precipm": "-9999.00", "hail": "0", "hum": "82", "precipi": "-9999.00", "conds": "Clear", "wgusti": "-9999.0", "heatindexm": "-9999", "tornado": "0"}, {"rain": "0", "date": {"year": "2017", "mon": "05", "min": "30", "hour": "23", "pretty": "11:30 PM CEST on May 31, 2017", "tzname": "Europe/Warsaw", "mday": "31"}, "dewptm": "11.0", "heatindexi": "-9999", "visi": "-9999.0", "pressurem": "1018", "metar": "METAR EPKK 312130Z VRB02KT CAVOK 14/11 Q1018", "thunder": "0", "windchilli": "-999", "fog": "0", "wdird": "0", "snow": "0", "wspdm": "3.7", "vism": "-9999.0", "icon": "clear", "utcdate": {"year": "2017", "mon": "05", "min": "30", "hour": "21", "pretty": "9:30 PM GMT on May 31, 2017", "tzname": "UTC", "mday": "31"}, "wspdi": "2.3", "dewpti": "51.8", "windchillm": "-999", "wdire": "Variable", "tempi": "57.2", "wgustm": "-9999.0", "pressurei": "30.06", "tempm": "14.0", "precipm": "-9999.00", "hail": "0", "hum": "82", "precipi": "-9999.00", "conds": "Clear", "wgusti": "-9999.0", "heatindexm": "-9999", "tornado": "0"}], "date": {"year": "2017", "mon": "05", "min": "00", "hour": "00", "pretty": "May 31, 2017", "tzname": "Europe/Warsaw", "mday": "31"}, "dailysummary": [{"precipsource": "Precip6GroupSynop", "meanwindspdm": "13", "date": {"year": "2017", "mon": "05", "min": "00", "hour": "00", "pretty": "12:00 AM CEST on May 31, 2017", "tzname": "Europe/Warsaw", "mday": "31"}, "maxwspdm": "30", "meanwdire": "West", "meanwdird": "266", "heatingdegreedays": "0", "mintempi": "57", "mindewptm": "11", "maxhumidity": "94", "since1sepcoolingdegreedaysnormal": "", "meanpressurem": "1015.81", "monthtodatesnowfalli": "", "monthtodatesnowfallm": "", "fog": "0", "meanwindspdi": "8", "snow": "0", "maxpressurem": "1018", "since1jancoolingdegreedays": "", "since1julsnowfallm": "", "since1julsnowfalli": "", "meandewptm": "15", "meandewpti": "58", "coolingdegreedaysnormal": "", "snowdepthi": "", "maxwspdi": "18", "minvisi": "6.2", "precipm": "0.1", "hail": "0", "maxvism": "30.0", "monthtodatecoolingdegreedays": "", "monthtodatecoolingdegreedaysnormal": "", "meantempi": "66", "coolingdegreedays": "2", "minwspdm": "2", "rain": "1", "since1sepheatingdegreedaysnormal": "", "minpressurei": "29.92", "heatingdegreedaysnormal": "", "snowfalli": "", "since1julheatingdegreedays": "", "minwspdi": "1", "maxtempi": "76", "minhumidity": "40", "mintempm": "14", "since1sepheatingdegreedays": "", "since1julheatingdegreedaysnormal": "", "gdegreedays": "16", "minvism": "10.0", "maxvisi": "19.0", "maxdewpti": "63", "thunder": "0", "meanvisi": "8.2", "since1sepcoolingdegreedays": "", "maxtempm": "24", "snowdepthm": "", "snowfallm": "", "humidity": "72", "meanpressurei": "30.00", "meanvism": "13.3", "meantempm": "19", "minpressurem": "1013", "since1jancoolingdegreedaysnormal": "", "monthtodateheatingdegreedays": "", "maxdewptm": "17", "monthtodateheatingdegreedaysnormal": "", "mindewpti": "52", "precipi": "0.00", "tornado": "0", "maxpressurei": "30.07"}]}}